[{"gameId": 401752872, "driveId": "4017528721", "id": "401752872101849903", "driveNumber": 1, "playNumber": 1, "offense": "Nebraska", "offenseConference": "Big Ten", "offenseScore": 0, "defense": "Minnesota", "defenseConference": "Big Ten", "defenseScore": 0, "home": "Minnesota", "away": "Nebraska", "period": 1, "clock": {"minutes": 15, "seconds": 0}, "offenseTimeouts": 3, "defenseTimeouts": 3, "yardline": 65, "yardsToGoal": 65, "down": 1, "distance": 10, "yardsGained": 0, "scoring": false, "playType": "Kickoff", "playText": "John Hohl kickoff for 65 yds for a touchback", "ppa": null, "wallclock": "2025-10-18T00:06:05.000Z"}, {"gameId": 401752872, "driveId": "4017528721", "id": "401752872101874001", "driveNumber": 1, "playNumber": 5, "offense": "Minnesota", "offenseConference": "Big Ten", "offenseScore": 0, "defense": "Nebraska", "defenseConference": "Big Ten", "defenseScore": 0, "home": "Minnesota", "away": "Nebraska", "period": 1, "clock": {"minutes": 12, "seconds": 59}, "offenseTimeouts": 3, "defenseTimeouts": 3, "yardline": 33, "yardsToGoal": 67, "down": 4, "distance": 2, "yardsGained": 0, "scoring": false, "playType": "Punt", "playText": "Tom Weston punt for 42 yds, punt out-of-bounds at the NEB 25", "ppa": null, "wallclock": "2025-10-18T00:09:07.000Z"}, {"gameId": 401752872, "driveId": "4017528721", "id": "401752872101854501", "driveNumber": 1, "playNumber": 2, "offense": "Minnesota", "offenseConference": "Big Ten", "offenseScore": 0, "defense": "Nebraska", "defenseConference": "Big Ten", "defenseScore": 0, "home": "Minnesota", "away": "Nebraska", "period": 1, "clock": {"minutes": 14, "seconds": 54}, "offenseTimeouts": 3, "defenseTimeouts": 3, "yardline": 25, "yardsToGoal": 75, "down": 1, "distance": 10, "yardsGained": 4, "scoring": false, "playType": "Rush", "playText": "Darius Taylor run for 4 yds to the MINN 29", "ppa": -0.1142886249388964, "wallclock": "2025-10-18T00:07:00.000Z"}, {"gameId": 401752872, "driveId": "4017528721", "id": "401752872101858301", "driveNumber": 1, "playNumber": 3, "offense": "Minnesota", "offenseConference": "Big Ten", "offenseScore": 0, "defense": "Nebraska", "defenseConference": "Big Ten", "defenseScore": 0, "home": "Minnesota", "away": "Nebraska", "period": 1, "clock": {"minutes": 14, "seconds": 16}, "offenseTimeouts": 3, "defenseTimeouts": 3, "yardline": 29, "yardsToGoal": 71, "down": 2, "distance": 6, "yardsGained": 2, "scoring": false, "playType": "Rush", "playText": "Darius Taylor run for 2 yds to the MINN 31", "ppa": -0.4204436586168807, "wallclock": "2025-10-18T00:07:34.000Z"}, {"gameId": 401752872, "driveId": "4017528721", "id": "401752872101866401", "driveNumber": 1, "playNumber": 4, "offense": "Minnesota", "offenseConference": "Big Ten", "offenseScore": 0, "defense": "Nebraska", "defenseConference": "Big Ten", "defenseScore": 0, "home": "Minnesota", "away": "Nebraska", "period": 1, "clock": {"minutes": 13, "seconds": 35}, "offenseTimeouts": 3, "defenseTimeouts": 3, "yardline": 31, "yardsToGoal": 69, "down": 3, "distance": 4, "yardsGained": 2, "scoring": false, "playType": "Pass Reception", "playText": "Drake Lindsey pass complete to Javon Tracy for 2 yds to the MINN 33", "ppa": -0.286169567325814, "wallclock": "2025-10-18T00:08:25.000Z"}, {"gameId": 401752872, "driveId": "4017528722", "id": "401752872101886901", "driveNumber": 2, "playNumber": 4, "offense": "Nebraska", "offenseConference": "Big Ten", "offenseScore": 0, "defense": "Minnesota", "defenseConference": "Big Ten", "defenseScore": 0, "home": "Minnesota", "away": "Nebraska", "period": 1, "clock": {"minutes": 11, "seconds": 30}, "offenseTimeouts": 3, "defenseTimeouts": 3, "yardline": 74, "yardsToGoal": 74, "down": 4, "distance": 9, "yardsGained": 2, "scoring": false, "playType": "Punt", "playText": "Archie Wilson punt for 53 yds , Koi Perich returns for 2 yds to the MINN 23", "ppa": null, "wallclock": "2025-10-18T00:11:44.000Z"}, {"gameId": 401752872, "driveId": "4017528722", "id": "401752872101875001", "driveNumber": 2, "playNumber": 1, "offense": "Nebraska", "offenseConference": "Big Ten", "offenseScore": 0, "defense": "Minnesota", "defenseConference": "Big Ten", "defenseScore": 0, "home": "Minnesota", "away": "Nebraska", "period": 1, "clock": {"minutes": 12, "seconds": 49}, "offenseTimeouts": 3, "defenseTimeouts": 3, "yardline": 75, "yardsToGoal": 75, "down": 1, "distance": 10, "yardsGained": 3, "scoring": false, "playType": "Pass Reception", "playText": "Dylan Raiola pass complete to Nyziah Hunter for 3 yds to the NEB 28", "ppa": -0.2957674139440157, "wallclock": "2025-10-18T00:09:44.000Z"}, {"gameId": 401752872, "driveId": "4017528722", "id": "401752872101878001", "driveNumber": 2, "playNumber": 2, "offense": "Nebraska", "offenseConference": "Big Ten", "offenseScore": 0, "defense": "Minnesota", "defenseConference": "Big Ten", "defenseScore": 0, "home": "Minnesota", "away": "Nebraska", "period": 1, "clock": {"minutes": 12, "seconds": 19}, "offenseTimeouts": 3, "defenseTimeouts": 3, "yardline": 72, "yardsToGoal": 72, "down": 2, "distance": 7, "yardsGained": -2, "scoring": false, "playType": "Sack", "playText": "Dylan Raiola sacked by Anthony Smith for a loss of 2 yards to the NEB 26", "ppa": -0.7000260823603801, "wallclock": "2025-10-18T00:10:06.000Z"}, {"gameId": 401752872, "driveId": "4017528722", "id": "401752872101885801", "driveNumber": 2, "playNumber": 3, "offense": "Nebraska", "offenseConference": "Big Ten", "offenseScore": 0, "defense": "Minnesota", "defenseConference": "Big Ten", "defenseScore": 0, "home": "Minnesota", "away": "Nebraska", "period": 1, "clock": {"minutes": 11, "seconds": 41}, "offenseTimeouts": 3, "defenseTimeouts": 3, "yardline": 74, "yardsToGoal": 74, "down": 3, "distance": 9, "yardsGained": 0, "scoring": false, "playType": "Pass Incompletion", "playText": "Dylan Raiola pass incomplete to Nyziah Hunter", "ppa": -0.18876768235831598, "wallclock": "2025-10-18T00:10:45.000Z"}, {"gameId": 401752872, "driveId": "4017528723", "id": "401752872101887502", "driveNumber": 3, "playNumber": 1, "offense": "Minnesota", "offenseConference": "Big Ten", "offenseScore": 0, "defense": "Nebraska", "defenseConference": "Big Ten", "defenseScore": 0, "home": "Minnesota", "away": "Nebraska", "period": 1, "clock": {"minutes": 11, "seconds": 24}, "offenseTimeouts": 3, "defenseTimeouts": 3, "yardline": 23, "yardsToGoal": 77, "down": 1, "distance": 10, "yardsGained": 5, "scoring": false, "playType": "Penalty", "playText": "(11:28) No Huddle Taylor,Darius rush middle for 2 yards gain to the MINN25 (Jeudy,Elijah; Guthrie,Rex) PENALTY NEB Offside (McCullough,Dasan) 5 yards from MINN23 to MINN28. NO PLAY.", "ppa": null, "wallclock": "2025-10-18T00:14:48.000Z"}, {"gameId": 401752872, "driveId": "4017528723", "id": "401752872101917601", "driveNumber": 3, "playNumber": 6, "offense": "Minnesota", "offenseConference": "Big Ten", "offenseScore": 0, "defense": "Nebraska", "defenseConference": "Big Ten", "defenseScore": 0, "home": "Minnesota", "away": "Nebraska", "period": 1, "clock": {"minutes": 8, "seconds": 23}, "offenseTimeouts": 2, "defenseTimeouts": 3, "yardline": 45, "yardsToGoal": 55, "down": 2, "distance": 5, "yardsGained": 0, "scoring": false, "playType": "Timeout", "playText": "Timeout Minnesota, clock 08:23", "ppa": null, "wallclock": "2025-10-18T00:06:05.000Z"}, {"gameId": 401752872, "driveId": "4017528723", "id": "401752872101935701", "driveNumber": 3, "playNumber": 9, "offense": "Minnesota", "offenseConference": "Big Ten", "offenseScore": 0, "defense": "Nebraska", "defenseConference": "Big Ten", "defenseScore": 0, "home": "Minnesota", "away": "Nebraska", "period": 1, "clock": {"minutes": 6, "seconds": 42}, "offenseTimeouts": 2, "defenseTimeouts": 3, "yardline": 48, "yardsToGoal": 52, "down": 4, "distance": 2, "yardsGained": 0, "scoring": false, "playType": "Punt", "playText": "Tom Weston punt for 37 yds, punt out-of-bounds at the NEB 15", "ppa": null, "wallclock": "2025-10-18T00:23:40.000Z"}, {"gameId": 401752872, "driveId": "4017528723", "id": "401752872101889701", "driveNumber": 3, "playNumber": 2, "offense": "Minnesota", "offenseConference": "Big Ten", "offenseScore": 0, "defense": "Nebraska", "defenseConference": "Big Ten", "defenseScore": 0, "home": "Minnesota", "away": "Nebraska", "period": 1, "clock": {"minutes": 11, "seconds": 2}, "offenseTimeouts": 3, "defenseTimeouts": 3, "yardline": 28, "yardsToGoal": 72, "down": 1, "distance": 5, "yardsGained": 3, "scoring": false, "playType": "Pass Reception", "playText": "Drake Lindsey pass complete to Jameson Geers for 3 yds to the MINN 31", "ppa": -0.4918369489845507, "wallclock": "2025-10-18T00:15:26.000Z"}, {"gameId": 401752872, "driveId": "4017528723", "id": "401752872101897901", "driveNumber": 3, "playNumber": 3, "offense": "Minnesota", "offenseConference": "Big Ten", "offenseScore": 0, "defense": "Nebraska", "defenseConference": "Big Ten", "defenseScore": 0, "home": "Minnesota", "away": "Nebraska", "period": 1, "clock": {"minutes": 10, "seconds": 20}, "offenseTimeouts": 3, "defenseTimeouts": 3, "yardline": 31, "yardsToGoal": 69, "down": 2, "distance": 2, "yardsGained": 1, "scoring": false, "playType": "Rush", "playText": "Darius Taylor run for 1 yd to the MINN 32", "ppa": -0.8833398767918083, "wallclock": "2025-10-18T00:16:11.000Z"}, {"gameId": 401752872, "driveId": "4017528723", "id": "401752872101905501", "driveNumber": 3, "playNumber": 4, "offense": "Minnesota", "offenseConference": "Big Ten", "offenseScore": 0, "defense": "Nebraska", "defenseConference": "Big Ten", "defenseScore": 0, "home": "Minnesota", "away": "Nebraska", "period": 1, "clock": {"minutes": 9, "seconds": 44}, "offenseTimeouts": 3, "defenseTimeouts": 3, "yardline": 32, "yardsToGoal": 68, "down": 3, "distance": 1, "yardsGained": 8, "scoring": false, "playType": "Rush", "playText": "Darius Taylor run for 8 yds to the MINN 40 for a 1ST down", "ppa": 1.4695518301693369, "wallclock": "2025-10-18T00:16:50.000Z"}, {"gameId": 401752872, "driveId": "4017528723", "id": "401752872101909701", "driveNumber": 3, "playNumber": 5, "offense": "Minnesota", "offenseConference": "Big Ten", "offenseScore": 0, "defense": "Nebraska", "defenseConference": "Big Ten", "defenseScore": 0, "home": "Minnesota", "away": "Nebraska", "period": 1, "clock": {"minutes": 9, "seconds": 2}, "offenseTimeouts": 3, "defenseTimeouts": 3, "yardline": 40, "yardsToGoal": 60, "down": 1, "distance": 10, "yardsGained": 5, "scoring": false, "playType": "Rush", "playText": "Cam Davis run for 5 yds to the MINN 45", "ppa": 0.1106144250151839, "wallclock": "2025-10-18T00:17:25.000Z"}, {"gameId": 401752872, "driveId": "4017528723", "id": "401752872101918101", "driveNumber": 3, "playNumber": 7, "offense": "Minnesota", "offenseConference": "Big Ten", "offenseScore": 0, "defense": "Nebraska", "defenseConference": "Big Ten", "defenseScore": 0, "home": "Minnesota", "away": "Nebraska", "period": 1, "clock": {"minutes": 8, "seconds": 18}, "offenseTimeouts": 2, "defenseTimeouts": 3, "yardline": 45, "yardsToGoal": 55, "down": 2, "distance": 5, "yardsGained": 1, "scoring": false, "playType": "Rush", "playText": "Darius Taylor run for 1 yd to the MINN 46", "ppa": -0.9460322471233891, "wallclock": "2025-10-18T00:22:09.000Z"}, {"gameId": 401752872, "driveId": "4017528723", "id": "401752872101926801", "driveNumber": 3, "playNumber": 8, "offense": "Minnesota", "offenseConference": "Big Ten", "offenseScore": 0, "defense": "Nebraska", "defenseConference": "Big Ten", "defenseScore": 0, "home": "Minnesota", "away": "Nebraska", "period": 1, "clock": {"minutes": 7, "seconds": 31}, "offenseTimeouts": 2, "defenseTimeouts": 3, "yardline": 46, "yardsToGoal": 54, "down": 3, "distance": 4, "yardsGained": 2, "scoring": false, "playType": "Pass Reception", "playText": "Drake Lindsey pass complete to Darius Taylor for 2 yds to the MINN 48", "ppa": -0.5535354899718747, "wallclock": "2025-10-18T00:22:56.000Z"}, {"gameId": 401752872, "driveId": "4017528724", "id": "401752872101977102", "driveNumber": 4, "playNumber": 7, "offense": "Nebraska", "offenseConference": "Big Ten", "offenseScore": 0, "defense": "Minnesota", "defenseConference": "Big Ten", "defenseScore": 0, "home": "Minnesota", "away": "Nebraska", "period": 1, "clock": {"minutes": 2, "seconds": 28}, "offenseTimeouts": 3, "defenseTimeouts": 2, "yardline": 39, "yardsToGoal": 39, "down": 3, "distance": 5, "yardsGained": 15, "scoring": false, "playType": "Penalty", "playText": "(02:32) Shotgun Raiola,Dylan pass incomplete deep left to Key,Dane thrown to MINN18 PENALTY MINN Pass Interference (Brown,Kerry) 15 yards from MINN39 to MINN24, 1ST DOWN. NO PLAY.", "ppa": null, "wallclock": "2025-10-18T00:31:49.000Z"}, {"gameId": 401752872, "driveId": "4017528724", "id": "401752872101999901", "driveNumber": 4, "playNumber": 13, "offense": "Nebraska", "offenseConference": "Big Ten", "offenseScore": 3, "defense": "Minnesota", "defenseConference": "Big Ten", "defenseScore": 0, "home": "Minnesota", "away": "Nebraska", "period": 1, "clock": {"minutes": 0, "seconds": 0}, "offenseTimeouts": 3, "defenseTimeouts": 2, "yardline": 15, "yardsToGoal": 15, "down": 4, "distance": 11, "yardsGained": 33, "scoring": true, "playType": "Field Goal Good", "playText": "Kyle Cunanan 33 yd FG GOOD", "ppa": null, "wallclock": "2025-10-18T00:39:31.000Z"}, {"gameId": 401752872, "driveId": "4017528724", "id": "401752872101999902", "driveNumber": 4, "playNumber": 14, "offense": "Nebraska", "offenseConference": "Big Ten", "offenseScore": 3, "defense": "Minnesota", "defenseConference": "Big Ten", "defenseScore": 0, "home": "Minnesota", "away": "Nebraska", "period": 1, "clock": {"minutes": 0, "seconds": 0}, "offenseTimeouts": 3, "defenseTimeouts": 2, "yardline": 15, "yardsToGoal": 15, "down": 0, "distance": 11, "yardsGained": -50, "scoring": false, "playType": "End Period", "playText": "End of 1st Quarter", "ppa": null, "wallclock": "2025-10-18T00:39:31.000Z"}, {"gameId": 401752872, "driveId": "4017528724", "id": "401752872102854501", "driveNumber": 4, "playNumber": 15, "offense": "Nebraska", "offenseConference": "Big Ten", "offenseScore": 3, "defense": "Minnesota", "defenseConference": "Big Ten", "defenseScore": 0, "home": "Minnesota", "away": "Nebraska", "period": 2, "clock": {"minutes": 14, "seconds": 54}, "offenseTimeouts": 3, "defenseTimeouts": 2, "yardline": 65, "yardsToGoal": 65, "down": 1, "distance": 10, "yardsGained": 26, "scoring": false, "playType": "Kickoff Return (Offense)", "playText": "John Hohl kickoff for 61 yds , Koi Perich return for 26 yds to the MINN 39 Minnesota Penalty, Offensive Holding (10 Yards) to the MINN 10", "ppa": null, "wallclock": "2025-10-18T00:44:57.000Z"}, {"gameId": 401752872, "driveId": "4017528724", "id": "401752872101936401", "driveNumber": 4, "playNumber": 1, "offense": "Nebraska", "offenseConference": "Big Ten", "offenseScore": 0, "defense": "Minnesota", "defenseConference": "Big Ten", "defenseScore": 0, "home": "Minnesota", "away": "Nebraska", "period": 1, "clock": {"minutes": 6, "seconds": 35}, "offenseTimeouts": 3, "defenseTimeouts": 2, "yardline": 85, "yardsToGoal": 85, "down": 1, "distance": 10, "yardsGained": 2, "scoring": false, "playType": "Rush", "playText": "Emmett Johnson run for 2 yds to the NEB 17", "ppa": -0.28628930380234063, "wallclock": "2025-10-18T00:27:35.000Z"}, {"gameId": 401752872, "driveId": "4017528724", "id": "401752872101944401", "driveNumber": 4, "playNumber": 2, "offense": "Nebraska", "offenseConference": "Big Ten", "offenseScore": 0, "defense": "Minnesota", "defenseConference": "Big Ten", "defenseScore": 0, "home": "Minnesota", "away": "Nebraska", "period": 1, "clock": {"minutes": 5, "seconds": 55}, "offenseTimeouts": 3, "defenseTimeouts": 2, "yardline": 83, "yardsToGoal": 83, "down": 2, "distance": 8, "yardsGained": 3, "scoring": false, "playType": "Pass Reception", "playText": "Dylan Raiola pass complete to Emmett Johnson for 3 yds to the NEB 20", "ppa": -0.12103300290610175, "wallclock": "2025-10-18T00:28:09.000Z"}, {"gameId": 401752872, "driveId": "4017528724", "id": "401752872101949501", "driveNumber": 4, "playNumber": 3, "offense": "Nebraska", "offenseConference": "Big Ten", "offenseScore": 0, "defense": "Minnesota", "defenseConference": "Big Ten", "defenseScore": 0, "home": "Minnesota", "away": "Nebraska", "period": 1, "clock": {"minutes": 5, "seconds": 4}, "offenseTimeouts": 3, "defenseTimeouts": 2, "yardline": 80, "yardsToGoal": 80, "down": 3, "distance": 5, "yardsGained": 26, "scoring": false, "playType": "Pass Reception", "playText": "Dylan Raiola pass complete to Luke Lindenmeyer for 26 yds to the NEB 46 for a 1ST down", "ppa": 2.8433863188984443, "wallclock": "2025-10-18T00:29:01.000Z"}, {"gameId": 401752872, "driveId": "4017528724", "id": "401752872101956201", "driveNumber": 4, "playNumber": 4, "offense": "Nebraska", "offenseConference": "Big Ten", "offenseScore": 0, "defense": "Minnesota", "defenseConference": "Big Ten", "defenseScore": 0, "home": "Minnesota", "away": "Nebraska", "period": 1, "clock": {"minutes": 4, "seconds": 37}, "offenseTimeouts": 3, "defenseTimeouts": 2, "yardline": 54, "yardsToGoal": 54, "down": 1, "distance": 10, "yardsGained": 10, "scoring": false, "playType": "Rush", "playText": "Emmett Johnson run for 10 yds to the MINN 44 for a 1ST down", "ppa": 0.7720151801751867, "wallclock": "2025-10-18T00:29:32.000Z"}, {"gameId": 401752872, "driveId": "4017528724", "id": "401752872101964701", "driveNumber": 4, "playNumber": 5, "offense": "Nebraska", "offenseConference": "Big Ten", "offenseScore": 0, "defense": "Minnesota", "defenseConference": "Big Ten", "defenseScore": 0, "home": "Minnesota", "away": "Nebraska", "period": 1, "clock": {"minutes": 3, "seconds": 52}, "offenseTimeouts": 3, "defenseTimeouts": 2, "yardline": 44, "yardsToGoal": 44, "down": 1, "distance": 10, "yardsGained": 3, "scoring": false, "playType": "Rush", "playText": "Emmett Johnson run for 3 yds to the MINN 41", "ppa": -0.3178831342797892, "wallclock": "2025-10-18T00:30:10.000Z"}, {"gameId": 401752872, "driveId": "4017528724", "id": "401752872101969101", "driveNumber": 4, "playNumber": 6, "offense": "Nebraska", "offenseConference": "Big Ten", "offenseScore": 0, "defense": "Minnesota", "defenseConference": "Big Ten", "defenseScore": 0, "home": "Minnesota", "away": "Nebraska", "period": 1, "clock": {"minutes": 3, "seconds": 8}, "offenseTimeouts": 3, "defenseTimeouts": 2, "yardline": 41, "yardsToGoal": 41, "down": 2, "distance": 7, "yardsGained": 2, "scoring": false, "playType": "Rush", "playText": "Emmett Johnson run for 2 yds to the MINN 39", "ppa": -0.5797879244568735, "wallclock": "2025-10-18T00:30:59.000Z"}, {"gameId": 401752872, "driveId": "4017528724", "id": "401752872101977701", "driveNumber": 4, "playNumber": 8, "offense": "Nebraska", "offenseConference": "Big Ten", "offenseScore": 0, "defense": "Minnesota", "defenseConference": "Big Ten", "defenseScore": 0, "home": "Minnesota", "away": "Nebraska", "period": 1, "clock": {"minutes": 2, "seconds": 22}, "offenseTimeouts": 3, "defenseTimeouts": 2, "yardline": 24, "yardsToGoal": 24, "down": 1, "distance": 10, "yardsGained": 0, "scoring": false, "playType": "Rush", "playText": "Emmett Johnson run for no gain to the MINN 24", "ppa": -0.4346450377339437, "wallclock": "2025-10-18T00:32:37.000Z"}, {"gameId": 401752872, "driveId": "4017528724", "id": "401752872101987401", "driveNumber": 4, "playNumber": 9, "offense": "Nebraska", "offenseConference": "Big Ten", "offenseScore": 0, "defense": "Minnesota", "defenseConference": "Big Ten", "defenseScore": 0, "home": "Minnesota", "away": "Nebraska", "period": 1, "clock": {"minutes": 1, "seconds": 25}, "offenseTimeouts": 3, "defenseTimeouts": 2, "yardline": 24, "yardsToGoal": 24, "down": 2, "distance": 10, "yardsGained": 10, "scoring": false, "playType": "Pass Reception", "playText": "Dylan Raiola pass complete to Nyziah Hunter for 10 yds to the MINN 14 for a 1ST down", "ppa": 0.5677998111618372, "wallclock": "2025-10-18T00:34:16.000Z"}, {"gameId": 401752872, "driveId": "4017528724", "id": "401752872101989201", "driveNumber": 4, "playNumber": 10, "offense": "Nebraska", "offenseConference": "Big Ten", "offenseScore": 0, "defense": "Minnesota", "defenseConference": "Big Ten", "defenseScore": 0, "home": "Minnesota", "away": "Nebraska", "period": 1, "clock": {"minutes": 1, "seconds": 7}, "offenseTimeouts": 3, "defenseTimeouts": 2, "yardline": 14, "yardsToGoal": 14, "down": 1, "distance": 10, "yardsGained": 4, "scoring": false, "playType": "Rush", "playText": "Emmett Johnson run for 4 yds to the MINN 10", "ppa": -0.0183111493425885, "wallclock": "2025-10-18T00:37:59.000Z"}, {"gameId": 401752872, "driveId": "4017528724", "id": "401752872101996201", "driveNumber": 4, "playNumber": 11, "offense": "Nebraska", "offenseConference": "Big Ten", "offenseScore": 0, "defense": "Minnesota", "defenseConference": "Big Ten", "defenseScore": 0, "home": "Minnesota", "away": "Nebraska", "period": 1, "clock": {"minutes": 0, "seconds": 37}, "offenseTimeouts": 3, "defenseTimeouts": 2, "yardline": 10, "yardsToGoal": 10, "down": 2, "distance": 6, "yardsGained": 0, "scoring": false, "playType": "Pass Incompletion", "playText": "Dylan Raiola pass incomplete to Dane Key", "ppa": -0.3266289588252625, "wallclock": "2025-10-18T00:38:11.000Z"}, {"gameId": 401752872, "driveId": "4017528724", "id": "401752872101997101", "driveNumber": 4, "playNumber": 12, "offense": "Nebraska", "offenseConference": "Big Ten", "offenseScore": 0, "defense": "Minnesota", "defenseConference": "Big Ten", "defenseScore": 0, "home": "Minnesota", "away": "Nebraska", "period": 1, "clock": {"minutes": 0, "seconds": 28}, "offenseTimeouts": 3, "defenseTimeouts": 2, "yardline": 10, "yardsToGoal": 10, "down": 3, "distance": 6, "yardsGained": -5, "scoring": false, "playType": "Sack", "playText": "Dylan Raiola sacked by Deven Eastern for a loss of 5 yards to the MINN 15", "ppa": -1.007766558774101, "wallclock": "2025-10-18T00:38:58.000Z"}, {"gameId": 401752872, "driveId": "4017528725", "id": "401752872102855501", "driveNumber": 5, "playNumber": 1, "offense": "Minnesota", "offenseConference": "Big Ten", "offenseScore": 0, "defense": "Nebraska", "defenseConference": "Big Ten", "defenseScore": 3, "home": "Minnesota", "away": "Nebraska", "period": 2, "clock": {"minutes": 14, "seconds": 44}, "offenseTimeouts": 2, "defenseTimeouts": 3, "yardline": 10, "yardsToGoal": 90, "down": 1, "distance": 10, "yardsGained": 15, "scoring": false, "playType": "Pass Reception", "playText": "Drake Lindsey pass complete to Malachi Coleman for 15 yds to the MINN 25 for a 1ST down", "ppa": 0.716089133415883, "wallclock": "2025-10-18T00:45:51.000Z"}, {"gameId": 401752872, "driveId": "4017528725", "id": "401752872102857901", "driveNumber": 5, "playNumber": 2, "offense": "Minnesota", "offenseConference": "Big Ten", "offenseScore": 0, "defense": "Nebraska", "defenseConference": "Big Ten", "defenseScore": 3, "home": "Minnesota", "away": "Nebraska", "period": 2, "clock": {"minutes": 14, "seconds": 20}, "offenseTimeouts": 2, "defenseTimeouts": 3, "yardline": 25, "yardsToGoal": 75, "down": 1, "distance": 10, "yardsGained": 3, "scoring": false, "playType": "Pass Reception", "playText": "Drake Lindsey pass complete to Drew Biber for 3 yds to the MINN 28", "ppa": -0.2957674139440157, "wallclock": "2025-10-18T00:46:20.000Z"}, {"gameId": 401752872, "driveId": "4017528725", "id": "401752872102864201", "driveNumber": 5, "playNumber": 3, "offense": "Minnesota", "offenseConference": "Big Ten", "offenseScore": 0, "defense": "Nebraska", "defenseConference": "Big Ten", "defenseScore": 3, "home": "Minnesota", "away": "Nebraska", "period": 2, "clock": {"minutes": 13, "seconds": 57}, "offenseTimeouts": 2, "defenseTimeouts": 3, "yardline": 28, "yardsToGoal": 72, "down": 2, "distance": 7, "yardsGained": 71, "scoring": false, "playType": "Rush", "playText": "Darius Taylor run for 71 yds to the NEB 1 for a 1ST down", "ppa": 5.435501258544894, "wallclock": "2025-10-18T00:47:09.000Z"}, {"gameId": 401752872, "driveId": "4017528725", "id": "401752872102867901", "driveNumber": 5, "playNumber": 4, "offense": "Minnesota", "offenseConference": "Big Ten", "offenseScore": 7, "defense": "Nebraska", "defenseConference": "Big Ten", "defenseScore": 3, "home": "Minnesota", "away": "Nebraska", "period": 2, "clock": {"minutes": 13, "seconds": 20}, "offenseTimeouts": 2, "defenseTimeouts": 3, "yardline": 99, "yardsToGoal": 1, "down": 1, "distance": 1, "yardsGained": 1, "scoring": true, "playType": "Rushing Touchdown", "playText": "Drake Lindsey run for 1 yd for a TD (Brady Denaburg KICK)", "ppa": 0.938021275120443, "wallclock": "2025-10-18T00:47:49.000Z"}, {"gameId": 401752872, "driveId": "4017528726", "id": "401752872102867903", "driveNumber": 6, "playNumber": 1, "offense": "Minnesota", "offenseConference": "Big Ten", "offenseScore": 7, "defense": "Nebraska", "defenseConference": "Big Ten", "defenseScore": 3, "home": "Minnesota", "away": "Nebraska", "period": 2, "clock": {"minutes": 13, "seconds": 20}, "offenseTimeouts": 2, "defenseTimeouts": 3, "yardline": 35, "yardsToGoal": 65, "down": 1, "distance": 10, "yardsGained": 0, "scoring": false, "playType": "Kickoff", "playText": "Brady Denaburg kickoff for 65 yds for a touchback", "ppa": null, "wallclock": "2025-10-18T00:47:49.000Z"}, {"gameId": 401752872, "driveId": "4017528726", "id": "401752872102884701", "driveNumber": 6, "playNumber": 5, "offense": "Nebraska", "offenseConference": "Big Ten", "offenseScore": 3, "defense": "Minnesota", "defenseConference": "Big Ten", "defenseScore": 7, "home": "Minnesota", "away": "Nebraska", "period": 2, "clock": {"minutes": 11, "seconds": 52}, "offenseTimeouts": 3, "defenseTimeouts": 2, "yardline": 74, "yardsToGoal": 74, "down": 4, "distance": 9, "yardsGained": 0, "scoring": false, "playType": "Punt", "playText": "Archie Wilson punt for 36 yds, fair catch by Koi Perich at the MINN 38", "ppa": null, "wallclock": "2025-10-18T00:55:16.000Z"}, {"gameId": 401752872, "driveId": "4017528726", "id": "401752872102868501", "driveNumber": 6, "playNumber": 2, "offense": "Nebraska", "offenseConference": "Big Ten", "offenseScore": 3, "defense": "Minnesota", "defenseConference": "Big Ten", "defenseScore": 7, "home": "Minnesota", "away": "Nebraska", "period": 2, "clock": {"minutes": 13, "seconds": 14}, "offenseTimeouts": 3, "defenseTimeouts": 2, "yardline": 75, "yardsToGoal": 75, "down": 1, "distance": 10, "yardsGained": 5, "scoring": false, "playType": "Rush", "playText": "Isaiah Mozee run for 5 yds to the NEB 30", "ppa": 0.0945451165334843, "wallclock": "2025-10-18T00:53:04.000Z"}, {"gameId": 401752872, "driveId": "4017528726", "id": "401752872102875301", "driveNumber": 6, "playNumber": 3, "offense": "Nebraska", "offenseConference": "Big Ten", "offenseScore": 3, "defense": "Minnesota", "defenseConference": "Big Ten", "defenseScore": 7, "home": "Minnesota", "away": "Nebraska", "period": 2, "clock": {"minutes": 12, "seconds": 46}, "offenseTimeouts": 3, "defenseTimeouts": 2, "yardline": 70, "yardsToGoal": 70, "down": 2, "distance": 5, "yardsGained": -4, "scoring": false, "playType": "Sack", "playText": "Dylan Raiola sacked by Karter Menz for a loss of 4 yards to the NEB 26", "ppa": -1.09033861283788, "wallclock": "2025-10-18T00:53:25.000Z"}, {"gameId": 401752872, "driveId": "4017528726", "id": "401752872102884001", "driveNumber": 6, "playNumber": 4, "offense": "Nebraska", "offenseConference": "Big Ten", "offenseScore": 3, "defense": "Minnesota", "defenseConference": "Big Ten", "defenseScore": 7, "home": "Minnesota", "away": "Nebraska", "period": 2, "clock": {"minutes": 11, "seconds": 59}, "offenseTimeouts": 3, "defenseTimeouts": 2, "yardline": 74, "yardsToGoal": 74, "down": 3, "distance": 9, "yardsGained": 0, "scoring": false, "playType": "Pass Incompletion", "playText": "Dylan Raiola pass incomplete to Luke Lindenmeyer", "ppa": -0.18876768235831598, "wallclock": "2025-10-18T00:54:34.000Z"}, {"gameId": 401752872, "driveId": "40175287211", "id": "401752872103849903", "driveNumber": 11, "playNumber": 1, "offense": "Minnesota", "offenseConference": "Big Ten", "offenseScore": 7, "defense": "Nebraska", "defenseConference": "Big Ten", "defenseScore": 6, "home": "Minnesota", "away": "Nebraska", "period": 3, "clock": {"minutes": 15, "seconds": 0}, "offenseTimeouts": 3, "defenseTimeouts": 3, "yardline": 35, "yardsToGoal": 65, "down": 1, "distance": 10, "yardsGained": 0, "scoring": false, "playType": "Kickoff", "playText": "Brady Denaburg kickoff for 65 yds for a touchback", "ppa": null, "wallclock": "2025-10-17T00:00:00.000Z"}, {"gameId": 401752872, "driveId": "40175287211", "id": "401752872103888001", "driveNumber": 11, "playNumber": 9, "offense": "Nebraska", "offenseConference": "Big Ten", "offenseScore": 6, "defense": "Minnesota", "defenseConference": "Big Ten", "defenseScore": 7, "home": "Minnesota", "away": "Nebraska", "period": 3, "clock": {"minutes": 11, "seconds": 19}, "offenseTimeouts": 3, "defenseTimeouts": 3, "yardline": 51, "yardsToGoal": 51, "down": 4, "distance": 18, "yardsGained": 0, "scoring": false, "playType": "Punt", "playText": "Archie Wilson punt for 49 yds", "ppa": null, "wallclock": "2025-10-18T02:00:58.000Z"}, {"gameId": 401752872, "driveId": "40175287211", "id": "401752872103854401", "driveNumber": 11, "playNumber": 2, "offense": "Nebraska", "offenseConference": "Big Ten", "offenseScore": 6, "defense": "Minnesota", "defenseConference": "Big Ten", "defenseScore": 7, "home": "Minnesota", "away": "Nebraska", "period": 3, "clock": {"minutes": 14, "seconds": 55}, "offenseTimeouts": 3, "defenseTimeouts": 3, "yardline": 75, "yardsToGoal": 75, "down": 1, "distance": 10, "yardsGained": 3, "scoring": false, "playType": "Rush", "playText": "Emmett Johnson run for 3 yds to the NEB 28", "ppa": -0.2957674139440157, "wallclock": "2025-10-17T00:00:00.000Z"}, {"gameId": 401752872, "driveId": "40175287211", "id": "401752872103858401", "driveNumber": 11, "playNumber": 3, "offense": "Nebraska", "offenseConference": "Big Ten", "offenseScore": 6, "defense": "Minnesota", "defenseConference": "Big Ten", "defenseScore": 7, "home": "Minnesota", "away": "Nebraska", "period": 3, "clock": {"minutes": 14, "seconds": 15}, "offenseTimeouts": 3, "defenseTimeouts": 3, "yardline": 72, "yardsToGoal": 72, "down": 2, "distance": 7, "yardsGained": 5, "scoring": false, "playType": "Pass Reception", "playText": "Dylan Raiola pass complete to Nyziah Hunter for 5 yds to the NEB 33", "ppa": 0.0761799593184067, "wallclock": "2025-10-17T00:00:00.000Z"}, {"gameId": 401752872, "driveId": "40175287211", "id": "401752872103865401", "driveNumber": 11, "playNumber": 4, "offense": "Nebraska", "offenseConference": "Big Ten", "offenseScore": 6, "defense": "Minnesota", "defenseConference": "Big Ten", "defenseScore": 7, "home": "Minnesota", "away": "Nebraska", "period": 3, "clock": {"minutes": 13, "seconds": 45}, "offenseTimeouts": 3, "defenseTimeouts": 3, "yardline": 67, "yardsToGoal": 67, "down": 3, "distance": 2, "yardsGained": 12, "scoring": false, "playType": "Pass Reception", "playText": "Dylan Raiola pass complete to Emmett Johnson for 12 yds to the NEB 45 for a 1ST down", "ppa": 2.0207293370305655, "wallclock": "2025-10-18T01:53:54.000Z"}, {"gameId": 401752872, "driveId": "40175287211", "id": "401752872103868001", "driveNumber": 11, "playNumber": 5, "offense": "Nebraska", "offenseConference": "Big Ten", "offenseScore": 6, "defense": "Minnesota", "defenseConference": "Big Ten", "defenseScore": 7, "home": "Minnesota", "away": "Nebraska", "period": 3, "clock": {"minutes": 13, "seconds": 19}, "offenseTimeouts": 3, "defenseTimeouts": 3, "yardline": 55, "yardsToGoal": 55, "down": 1, "distance": 10, "yardsGained": 12, "scoring": false, "playType": "Rush", "playText": "Emmett Johnson run for 12 yds to the MINN 43 for a 1ST down", "ppa": 0.9242431493855108, "wallclock": "2025-10-18T01:57:54.000Z"}, {"gameId": 401752872, "driveId": "40175287211", "id": "401752872103876101", "driveNumber": 11, "playNumber": 6, "offense": "Nebraska", "offenseConference": "Big Ten", "offenseScore": 6, "defense": "Minnesota", "defenseConference": "Big Ten", "defenseScore": 7, "home": "Minnesota", "away": "Nebraska", "period": 3, "clock": {"minutes": 12, "seconds": 38}, "offenseTimeouts": 3, "defenseTimeouts": 3, "yardline": 43, "yardsToGoal": 43, "down": 1, "distance": 10, "yardsGained": 1, "scoring": false, "playType": "Pass Reception", "playText": "Dylan Raiola pass complete to Jacory Barney Jr. for 1 yd to the MINN 42", "ppa": -0.7221421996351935, "wallclock": "2025-10-18T01:58:35.000Z"}, {"gameId": 401752872, "driveId": "40175287211", "id": "401752872103879001", "driveNumber": 11, "playNumber": 7, "offense": "Nebraska", "offenseConference": "Big Ten", "offenseScore": 6, "defense": "Minnesota", "defenseConference": "Big Ten", "defenseScore": 7, "home": "Minnesota", "away": "Nebraska", "period": 3, "clock": {"minutes": 12, "seconds": 9}, "offenseTimeouts": 3, "defenseTimeouts": 3, "yardline": 42, "yardsToGoal": 42, "down": 2, "distance": 9, "yardsGained": 0, "scoring": false, "playType": "Pass Incompletion", "playText": "Dylan Raiola pass incomplete to Dane Key", "ppa": -1.0560204971413256, "wallclock": "2025-10-18T01:59:07.000Z"}, {"gameId": 401752872, "driveId": "40175287211", "id": "401752872103879901", "driveNumber": 11, "playNumber": 8, "offense": "Nebraska", "offenseConference": "Big Ten", "offenseScore": 6, "defense": "Minnesota", "defenseConference": "Big Ten", "defenseScore": 7, "home": "Minnesota", "away": "Nebraska", "period": 3, "clock": {"minutes": 12, "seconds": 0}, "offenseTimeouts": 3, "defenseTimeouts": 3, "yardline": 42, "yardsToGoal": 42, "down": 3, "distance": 9, "yardsGained": -9, "scoring": false, "playType": "Sack", "playText": "Dylan Raiola sacked by Jaxon Howard for a loss of 9 yards to the NEB 49", "ppa": -1.9446354084337738, "wallclock": "2025-10-18T01:59:48.000Z"}, {"gameId": 401752872, "driveId": "40175287212", "id": "401752872103907801", "driveNumber": 12, "playNumber": 4, "offense": "Minnesota", "offenseConference": "Big Ten", "offenseScore": 7, "defense": "Nebraska", "defenseConference": "Big Ten", "defenseScore": 6, "home": "Minnesota", "away": "Nebraska", "period": 3, "clock": {"minutes": 9, "seconds": 21}, "offenseTimeouts": 3, "defenseTimeouts": 3, "yardline": 21, "yardsToGoal": 79, "down": 1, "distance": 10, "yardsGained": -5, "scoring": false, "playType": "Penalty", "playText": "PENALTY MINN False Start (Johnson,Greg) 5 yards from MINN21 to MINN16. NO PLAY.", "ppa": null, "wallclock": "2025-10-18T02:07:25.000Z"}, {"gameId": 401752872, "driveId": "40175287212", "id": "401752872103957501", "driveNumber": 12, "playNumber": 12, "offense": "Minnesota", "offenseConference": "Big Ten", "offenseScore": 7, "defense": "Nebraska", "defenseConference": "Big Ten", "defenseScore": 6, "home": "Minnesota", "away": "Nebraska", "period": 3, "clock": {"minutes": 4, "seconds": 24}, "offenseTimeouts": 3, "defenseTimeouts": 2, "yardline": 66, "yardsToGoal": 34, "down": 2, "distance": 3, "yardsGained": 0, "scoring": false, "playType": "Timeout", "playText": "Timeout Nebraska, clock 04:24", "ppa": null, "wallclock": "2025-10-18T01:53:44.000Z"}, {"gameId": 401752872, "driveId": "40175287212", "id": "401752872103967602", "driveNumber": 12, "playNumber": 15, "offense": "Minnesota", "offenseConference": "Big Ten", "offenseScore": 7, "defense": "Nebraska", "defenseConference": "Big Ten", "defenseScore": 6, "home": "Minnesota", "away": "Nebraska", "period": 3, "clock": {"minutes": 3, "seconds": 23}, "offenseTimeouts": 3, "defenseTimeouts": 2, "yardline": 66, "yardsToGoal": 34, "down": 4, "distance": 3, "yardsGained": 10, "scoring": false, "playType": "Penalty", "playText": "(03:26) Lindsey,Drake pass incomplete short left to Brockington,Lemeke thrown to NEB20 broken up by Jones,Donovan PENALTY NEB Holding (Marshall,Andrew) 10 yards from NEB34 to NEB24, 1ST DOWN. NO PLAY.", "ppa": null, "wallclock": "2025-10-18T02:17:21.000Z"}, {"gameId": 401752872, "driveId": "40175287212", "id": "401752872103889001", "driveNumber": 12, "playNumber": 1, "offense": "Minnesota", "offenseConference": "Big Ten", "offenseScore": 7, "defense": "Nebraska", "defenseConference": "Big Ten", "defenseScore": 6, "home": "Minnesota", "away": "Nebraska", "period": 3, "clock": {"minutes": 11, "seconds": 9}, "offenseTimeouts": 3, "defenseTimeouts": 3, "yardline": 2, "yardsToGoal": 98, "down": 1, "distance": 10, "yardsGained": 4, "scoring": false, "playType": "Rush", "playText": "Darius Taylor run for 4 yds to the MINN 6", "ppa": -0.028184277766515997, "wallclock": "2025-10-18T02:04:19.000Z"}, {"gameId": 401752872, "driveId": "40175287212", "id": "401752872103895801", "driveNumber": 12, "playNumber": 2, "offense": "Minnesota", "offenseConference": "Big Ten", "offenseScore": 7, "defense": "Nebraska", "defenseConference": "Big Ten", "defenseScore": 6, "home": "Minnesota", "away": "Nebraska", "period": 3, "clock": {"minutes": 10, "seconds": 41}, "offenseTimeouts": 3, "defenseTimeouts": 3, "yardline": 6, "yardsToGoal": 94, "down": 2, "distance": 6, "yardsGained": 3, "scoring": false, "playType": "Rush", "playText": "Darius Taylor run for 3 yds to the MINN 9", "ppa": -0.09418549908640106, "wallclock": "2025-10-18T02:06:01.000Z"}, {"gameId": 401752872, "driveId": "40175287212", "id": "401752872103904301", "driveNumber": 12, "playNumber": 3, "offense": "Minnesota", "offenseConference": "Big Ten", "offenseScore": 7, "defense": "Nebraska", "defenseConference": "Big Ten", "defenseScore": 6, "home": "Minnesota", "away": "Nebraska", "period": 3, "clock": {"minutes": 9, "seconds": 56}, "offenseTimeouts": 3, "defenseTimeouts": 3, "yardline": 9, "yardsToGoal": 91, "down": 3, "distance": 3, "yardsGained": 12, "scoring": false, "playType": "Pass Reception", "playText": "Drake Lindsey pass complete to Le'Meke Brockington for 12 yds to the MINN 21 for a 1ST down", "ppa": 0.767017287936488, "wallclock": "2025-10-18T02:06:40.000Z"}, {"gameId": 401752872, "driveId": "40175287212", "id": "401752872103915301", "driveNumber": 12, "playNumber": 5, "offense": "Minnesota", "offenseConference": "Big Ten", "offenseScore": 7, "defense": "Nebraska", "defenseConference": "Big Ten", "defenseScore": 6, "home": "Minnesota", "away": "Nebraska", "period": 3, "clock": {"minutes": 8, "seconds": 46}, "offenseTimeouts": 3, "defenseTimeouts": 3, "yardline": 16, "yardsToGoal": 84, "down": 1, "distance": 15, "yardsGained": 4, "scoring": false, "playType": "Rush", "playText": "Darius Taylor run for 4 yds to the MINN 20", "ppa": -0.04596405628661593, "wallclock": "2025-10-18T02:08:10.000Z"}, {"gameId": 401752872, "driveId": "40175287212", "id": "401752872103919301", "driveNumber": 12, "playNumber": 6, "offense": "Minnesota", "offenseConference": "Big Ten", "offenseScore": 7, "defense": "Nebraska", "defenseConference": "Big Ten", "defenseScore": 6, "home": "Minnesota", "away": "Nebraska", "period": 3, "clock": {"minutes": 8, "seconds": 6}, "offenseTimeouts": 3, "defenseTimeouts": 3, "yardline": 20, "yardsToGoal": 80, "down": 2, "distance": 11, "yardsGained": 11, "scoring": false, "playType": "Pass Reception", "playText": "Drake Lindsey pass complete to Jameson Geers for 11 yds to the MINN 31 for a 1ST down", "ppa": 1.3886181713137855, "wallclock": "2025-10-18T02:08:55.000Z"}, {"gameId": 401752872, "driveId": "40175287212", "id": "401752872103927601", "driveNumber": 12, "playNumber": 7, "offense": "Minnesota", "offenseConference": "Big Ten", "offenseScore": 7, "defense": "Nebraska", "defenseConference": "Big Ten", "defenseScore": 6, "home": "Minnesota", "away": "Nebraska", "period": 3, "clock": {"minutes": 7, "seconds": 23}, "offenseTimeouts": 3, "defenseTimeouts": 3, "yardline": 31, "yardsToGoal": 69, "down": 1, "distance": 10, "yardsGained": 8, "scoring": false, "playType": "Pass Reception", "playText": "Drake Lindsey pass complete to Darius Taylor for 8 yds to the MINN 39", "ppa": 1.0102722158723196, "wallclock": "2025-10-18T02:09:38.000Z"}, {"gameId": 401752872, "driveId": "40175287212", "id": "401752872103935401", "driveNumber": 12, "playNumber": 8, "offense": "Minnesota", "offenseConference": "Big Ten", "offenseScore": 7, "defense": "Nebraska", "defenseConference": "Big Ten", "defenseScore": 6, "home": "Minnesota", "away": "Nebraska", "period": 3, "clock": {"minutes": 6, "seconds": 45}, "offenseTimeouts": 3, "defenseTimeouts": 3, "yardline": 39, "yardsToGoal": 61, "down": 2, "distance": 2, "yardsGained": 7, "scoring": false, "playType": "Rush", "playText": "Fame Ijeboi run for 7 yds to the MINN 46 for a 1ST down", "ppa": 0.412121251557522, "wallclock": "2025-10-18T02:10:12.000Z"}, {"gameId": 401752872, "driveId": "40175287212", "id": "401752872103939701", "driveNumber": 12, "playNumber": 9, "offense": "Minnesota", "offenseConference": "Big Ten", "offenseScore": 7, "defense": "Nebraska", "defenseConference": "Big Ten", "defenseScore": 6, "home": "Minnesota", "away": "Nebraska", "period": 3, "clock": {"minutes": 6, "seconds": 2}, "offenseTimeouts": 3, "defenseTimeouts": 3, "yardline": 46, "yardsToGoal": 54, "down": 1, "distance": 10, "yardsGained": 5, "scoring": false, "playType": "Pass Reception", "playText": "Drake Lindsey pass complete to Javon Tracy for 5 yds to the NEB 49", "ppa": 0.1068990350586356, "wallclock": "2025-10-18T02:11:01.000Z"}, {"gameId": 401752872, "driveId": "40175287212", "id": "401752872103947901", "driveNumber": 12, "playNumber": 10, "offense": "Minnesota", "offenseConference": "Big Ten", "offenseScore": 7, "defense": "Nebraska", "defenseConference": "Big Ten", "defenseScore": 6, "home": "Minnesota", "away": "Nebraska", "period": 3, "clock": {"minutes": 5, "seconds": 20}, "offenseTimeouts": 3, "defenseTimeouts": 3, "yardline": 51, "yardsToGoal": 49, "down": 2, "distance": 5, "yardsGained": 8, "scoring": false, "playType": "Rush", "playText": "Fame Ijeboi run for 8 yds to the NEB 41 for a 1ST down", "ppa": 0.837478876730053, "wallclock": "2025-10-18T02:11:39.000Z"}, {"gameId": 401752872, "driveId": "40175287212", "id": "401752872103956201", "driveNumber": 12, "playNumber": 11, "offense": "Minnesota", "offenseConference": "Big Ten", "offenseScore": 7, "defense": "Nebraska", "defenseConference": "Big Ten", "defenseScore": 6, "home": "Minnesota", "away": "Nebraska", "period": 3, "clock": {"minutes": 4, "seconds": 37}, "offenseTimeouts": 3, "defenseTimeouts": 3, "yardline": 59, "yardsToGoal": 41, "down": 1, "distance": 10, "yardsGained": 7, "scoring": false, "playType": "Pass Reception", "playText": "Drake Lindsey pass complete to Logan Loya for 7 yds to the NEB 34", "ppa": 0.4598399849082394, "wallclock": "2025-10-18T02:12:19.000Z"}, {"gameId": 401752872, "driveId": "40175287212", "id": "401752872103958101", "driveNumber": 12, "playNumber": 13, "offense": "Minnesota", "offenseConference": "Big Ten", "offenseScore": 7, "defense": "Nebraska", "defenseConference": "Big Ten", "defenseScore": 6, "home": "Minnesota", "away": "Nebraska", "period": 3, "clock": {"minutes": 4, "seconds": 18}, "offenseTimeouts": 3, "defenseTimeouts": 2, "yardline": 66, "yardsToGoal": 34, "down": 2, "distance": 3, "yardsGained": 0, "scoring": false, "playType": "Rush", "playText": "Fame Ijeboi run for no gain to the NEB 34", "ppa": -0.8569052762428488, "wallclock": "2025-10-18T02:16:08.000Z"}, {"gameId": 401752872, "driveId": "40175287212", "id": "401752872103967101", "driveNumber": 12, "playNumber": 14, "offense": "Minnesota", "offenseConference": "Big Ten", "offenseScore": 7, "defense": "Nebraska", "defenseConference": "Big Ten", "defenseScore": 6, "home": "Minnesota", "away": "Nebraska", "period": 3, "clock": {"minutes": 3, "seconds": 28}, "offenseTimeouts": 3, "defenseTimeouts": 2, "yardline": 66, "yardsToGoal": 34, "down": 3, "distance": 3, "yardsGained": 0, "scoring": false, "playType": "Pass Incompletion", "playText": "Drake Lindsey pass incomplete to Le'Meke Brockington", "ppa": -1.0085139299529366, "wallclock": "2025-10-18T02:16:43.000Z"}, {"gameId": 401752872, "driveId": "40175287212", "id": "401752872103968401", "driveNumber": 12, "playNumber": 16, "offense": "Minnesota", "offenseConference": "Big Ten", "offenseScore": 7, "defense": "Nebraska", "defenseConference": "Big Ten", "defenseScore": 6, "home": "Minnesota", "away": "Nebraska", "period": 3, "clock": {"minutes": 3, "seconds": 15}, "offenseTimeouts": 3, "defenseTimeouts": 2, "yardline": 76, "yardsToGoal": 24, "down": 1, "distance": 10, "yardsGained": 4, "scoring": false, "playType": "Rush", "playText": "Fame Ijeboi run for 4 yds to the NEB 20", "ppa": -0.0334632336053265, "wallclock": "2025-10-18T02:18:38.000Z"}, {"gameId": 401752872, "driveId": "40175287212", "id": "401752872103976301", "driveNumber": 12, "playNumber": 17, "offense": "Minnesota", "offenseConference": "Big Ten", "offenseScore": 14, "defense": "Nebraska", "defenseConference": "Big Ten", "defenseScore": 6, "home": "Minnesota", "away": "Nebraska", "period": 3, "clock": {"minutes": 2, "seconds": 36}, "offenseTimeouts": 3, "defenseTimeouts": 2, "yardline": 80, "yardsToGoal": 20, "down": 2, "distance": 6, "yardsGained": 20, "scoring": true, "playType": "Passing Touchdown", "playText": "Drake Lindsey pass complete to Le'Meke Brockington for 20 yds for a TD (Brady Denaburg KICK)", "ppa": 2.7149011822123015, "wallclock": "2025-10-18T02:19:11.000Z"}, {"gameId": 401752872, "driveId": "40175287213", "id": "401752872103976701", "driveNumber": 13, "playNumber": 1, "offense": "Minnesota", "offenseConference": "Big Ten", "offenseScore": 14, "defense": "Nebraska", "defenseConference": "Big Ten", "defenseScore": 6, "home": "Minnesota", "away": "Nebraska", "period": 3, "clock": {"minutes": 2, "seconds": 32}, "offenseTimeouts": 3, "defenseTimeouts": 2, "yardline": 35, "yardsToGoal": 65, "down": 1, "distance": 10, "yardsGained": 12, "scoring": false, "playType": "Kickoff Return (Offense)", "playText": "Brady Denaburg kickoff for 60 yds , Kenneth Williams return for 12 yds to the NEB 17", "ppa": null, "wallclock": "2025-10-18T02:23:56.000Z"}, {"gameId": 401752872, "driveId": "40175287213", "id": "401752872103997901", "driveNumber": 13, "playNumber": 5, "offense": "Nebraska", "offenseConference": "Big Ten", "offenseScore": 6, "defense": "Minnesota", "defenseConference": "Big Ten", "defenseScore": 14, "home": "Minnesota", "away": "Nebraska", "period": 3, "clock": {"minutes": 0, "seconds": 20}, "offenseTimeouts": 2, "defenseTimeouts": 3, "yardline": 86, "yardsToGoal": 86, "down": 4, "distance": 13, "yardsGained": 0, "scoring": false, "playType": "Punt", "playText": "Archie Wilson punt for 48 yds", "ppa": null, "wallclock": "2025-10-18T02:26:37.000Z"}, {"gameId": 401752872, "driveId": "40175287213", "id": "401752872103977501", "driveNumber": 13, "playNumber": 2, "offense": "Nebraska", "offenseConference": "Big Ten", "offenseScore": 6, "defense": "Minnesota", "defenseConference": "Big Ten", "defenseScore": 14, "home": "Minnesota", "away": "Nebraska", "period": 3, "clock": {"minutes": 2, "seconds": 24}, "offenseTimeouts": 2, "defenseTimeouts": 3, "yardline": 83, "yardsToGoal": 83, "down": 1, "distance": 10, "yardsGained": 5, "scoring": false, "playType": "Rush", "playText": "Dylan Raiola run for 5 yds to the NEB 22", "ppa": 0.0803248403226124, "wallclock": "2025-10-18T02:24:35.000Z"}, {"gameId": 401752872, "driveId": "40175287213", "id": "401752872103986901", "driveNumber": 13, "playNumber": 3, "offense": "Nebraska", "offenseConference": "Big Ten", "offenseScore": 6, "defense": "Minnesota", "defenseConference": "Big Ten", "defenseScore": 14, "home": "Minnesota", "away": "Nebraska", "period": 3, "clock": {"minutes": 1, "seconds": 30}, "offenseTimeouts": 2, "defenseTimeouts": 3, "yardline": 78, "yardsToGoal": 78, "down": 2, "distance": 5, "yardsGained": 0, "scoring": false, "playType": "Rush", "playText": "Dylan Raiola run for no gain to the NEB 22", "ppa": -0.5298603767681547, "wallclock": "2025-10-18T02:25:26.000Z"}, {"gameId": 401752872, "driveId": "40175287213", "id": "401752872103989801", "driveNumber": 13, "playNumber": 4, "offense": "Nebraska", "offenseConference": "Big Ten", "offenseScore": 6, "defense": "Minnesota", "defenseConference": "Big Ten", "defenseScore": 14, "home": "Minnesota", "away": "Nebraska", "period": 3, "clock": {"minutes": 1, "seconds": 1}, "offenseTimeouts": 2, "defenseTimeouts": 3, "yardline": 78, "yardsToGoal": 78, "down": 3, "distance": 5, "yardsGained": -8, "scoring": false, "playType": "Sack", "playText": "Dylan Raiola sacked by Matt Kingsbury for a loss of 8 yards to the NEB 14", "ppa": -0.3831768033403229, "wallclock": "2025-10-18T02:25:52.000Z"}, {"gameId": 401752872, "driveId": "40175287214", "id": "401752872103999902", "driveNumber": 14, "playNumber": 2, "offense": "Minnesota", "offenseConference": "Big Ten", "offenseScore": 14, "defense": "Nebraska", "defenseConference": "Big Ten", "defenseScore": 6, "home": "Minnesota", "away": "Nebraska", "period": 3, "clock": {"minutes": 0, "seconds": 0}, "offenseTimeouts": 3, "defenseTimeouts": 2, "yardline": 38, "yardsToGoal": 62, "down": 0, "distance": 10, "yardsGained": 3, "scoring": false, "playType": "End Period", "playText": "End of 3rd Quarter", "ppa": null, "wallclock": "2025-10-18T02:27:44.000Z"}, {"gameId": 401752872, "driveId": "40175287214", "id": "401752872104859101", "driveNumber": 14, "playNumber": 4, "offense": "Minnesota", "offenseConference": "Big Ten", "offenseScore": 14, "defense": "Nebraska", "defenseConference": "Big Ten", "defenseScore": 6, "home": "Minnesota", "away": "Nebraska", "period": 4, "clock": {"minutes": 14, "seconds": 8}, "offenseTimeouts": 3, "defenseTimeouts": 2, "yardline": 45, "yardsToGoal": 55, "down": 3, "distance": 3, "yardsGained": 15, "scoring": false, "playType": "Penalty", "playText": "(14:16) Shotgun Lindsey,Drake pass intercepted by Marshall,Andrew at NEB35 QB hurried by Nwaneri,Williams PENALTY NEB Pass Interference (Jones,Donovan) 15 yards from MINN45 to NEB40, 1ST DOWN. NO PLAY.", "ppa": null, "wallclock": "2025-10-18T02:33:57.000Z"}, {"gameId": 401752872, "driveId": "40175287214", "id": "401752872103999901", "driveNumber": 14, "playNumber": 1, "offense": "Minnesota", "offenseConference": "Big Ten", "offenseScore": 14, "defense": "Nebraska", "defenseConference": "Big Ten", "defenseScore": 6, "home": "Minnesota", "away": "Nebraska", "period": 3, "clock": {"minutes": 0, "seconds": 0}, "offenseTimeouts": 3, "defenseTimeouts": 2, "yardline": 38, "yardsToGoal": 62, "down": 1, "distance": 10, "yardsGained": 3, "scoring": false, "playType": "Pass Reception", "playText": "Drake Lindsey pass complete to Darius Taylor for 3 yds to the MINN 41", "ppa": -0.4251117664036599, "wallclock": "2025-10-18T02:27:44.000Z"}, {"gameId": 401752872, "driveId": "40175287214", "id": "401752872104854501", "driveNumber": 14, "playNumber": 3, "offense": "Minnesota", "offenseConference": "Big Ten", "offenseScore": 14, "defense": "Nebraska", "defenseConference": "Big Ten", "defenseScore": 6, "home": "Minnesota", "away": "Nebraska", "period": 4, "clock": {"minutes": 14, "seconds": 54}, "offenseTimeouts": 3, "defenseTimeouts": 2, "yardline": 41, "yardsToGoal": 59, "down": 2, "distance": 7, "yardsGained": 4, "scoring": false, "playType": "Rush", "playText": "Fame Ijeboi run for 4 yds to the MINN 45", "ppa": -0.1564031970073749, "wallclock": "2025-10-18T02:32:23.000Z"}, {"gameId": 401752872, "driveId": "40175287215", "id": "401752872104864501", "driveNumber": 15, "playNumber": 1, "offense": "Minnesota", "offenseConference": "Big Ten", "offenseScore": 14, "defense": "Nebraska", "defenseConference": "Big Ten", "defenseScore": 6, "home": "Minnesota", "away": "Nebraska", "period": 4, "clock": {"minutes": 13, "seconds": 54}, "offenseTimeouts": 3, "defenseTimeouts": 2, "yardline": 60, "yardsToGoal": 40, "down": 1, "distance": 10, "yardsGained": 4, "scoring": false, "playType": "Rush", "playText": "Darius Taylor run for 4 yds to the NEB 36", "ppa": -0.090113775884788, "wallclock": "2025-10-18T02:34:32.000Z"}, {"gameId": 401752872, "driveId": "40175287215", "id": "401752872104867501", "driveNumber": 15, "playNumber": 2, "offense": "Minnesota", "offenseConference": "Big Ten", "offenseScore": 14, "defense": "Nebraska", "defenseConference": "Big Ten", "defenseScore": 6, "home": "Minnesota", "away": "Nebraska", "period": 4, "clock": {"minutes": 13, "seconds": 24}, "offenseTimeouts": 3, "defenseTimeouts": 2, "yardline": 64, "yardsToGoal": 36, "down": 2, "distance": 6, "yardsGained": 0, "scoring": false, "playType": "Pass Incompletion", "playText": "Drake Lindsey pass incomplete to Jalen Smith", "ppa": -0.8984915581842065, "wallclock": "2025-10-18T02:34:43.000Z"}, {"gameId": 401752872, "driveId": "40175287215", "id": "401752872104868601", "driveNumber": 15, "playNumber": 3, "offense": "Minnesota", "offenseConference": "Big Ten", "offenseScore": 14, "defense": "Nebraska", "defenseConference": "Big Ten", "defenseScore": 6, "home": "Minnesota", "away": "Nebraska", "period": 4, "clock": {"minutes": 13, "seconds": 13}, "offenseTimeouts": 3, "defenseTimeouts": 2, "yardline": 64, "yardsToGoal": 36, "down": 3, "distance": 6, "yardsGained": 35, "scoring": false, "playType": "Pass Reception", "playText": "Drake Lindsey pass complete to Jalen Smith for 35 yds to the NEB 1 for a 1ST down", "ppa": 3.2396332028858925, "wallclock": "2025-10-18T02:36:02.000Z"}, {"gameId": 401752872, "driveId": "40175287215", "id": "401752872104876701", "driveNumber": 15, "playNumber": 4, "offense": "Minnesota", "offenseConference": "Big Ten", "offenseScore": 21, "defense": "Nebraska", "defenseConference": "Big Ten", "defenseScore": 6, "home": "Minnesota", "away": "Nebraska", "period": 4, "clock": {"minutes": 12, "seconds": 32}, "offenseTimeouts": 3, "defenseTimeouts": 2, "yardline": 99, "yardsToGoal": 1, "down": 1, "distance": 1, "yardsGained": 1, "scoring": true, "playType": "Rushing Touchdown", "playText": "Darius Taylor run for 1 yd for a TD (Brady Denaburg KICK)", "ppa": 0.938021275120443, "wallclock": "2025-10-18T02:36:17.000Z"}, {"gameId": 401752872, "driveId": "40175287216", "id": "401752872104876703", "driveNumber": 16, "playNumber": 1, "offense": "Minnesota", "offenseConference": "Big Ten", "offenseScore": 21, "defense": "Nebraska", "defenseConference": "Big Ten", "defenseScore": 6, "home": "Minnesota", "away": "Nebraska", "period": 4, "clock": {"minutes": 12, "seconds": 32}, "offenseTimeouts": 3, "defenseTimeouts": 2, "yardline": 35, "yardsToGoal": 65, "down": 1, "distance": 10, "yardsGained": 0, "scoring": false, "playType": "Kickoff", "playText": "Brady Denaburg kickoff for 65 yds for a touchback", "ppa": null, "wallclock": "2025-10-18T02:40:16.000Z"}, {"gameId": 401752872, "driveId": "40175287216", "id": "401752872104906201", "driveNumber": 16, "playNumber": 8, "offense": "Nebraska", "offenseConference": "Big Ten", "offenseScore": 6, "defense": "Minnesota", "defenseConference": "Big Ten", "defenseScore": 21, "home": "Minnesota", "away": "Nebraska", "period": 4, "clock": {"minutes": 9, "seconds": 37}, "offenseTimeouts": 2, "defenseTimeouts": 3, "yardline": 63, "yardsToGoal": 63, "down": 4, "distance": 14, "yardsGained": 0, "scoring": false, "playType": "Punt", "playText": "Archie Wilson punt for 37 yds, fair catch by Koi Perich at the MINN 26", "ppa": null, "wallclock": "2025-10-18T02:44:29.000Z"}, {"gameId": 401752872, "driveId": "40175287216", "id": "401752872104877401", "driveNumber": 16, "playNumber": 2, "offense": "Nebraska", "offenseConference": "Big Ten", "offenseScore": 6, "defense": "Minnesota", "defenseConference": "Big Ten", "defenseScore": 21, "home": "Minnesota", "away": "Nebraska", "period": 4, "clock": {"minutes": 12, "seconds": 25}, "offenseTimeouts": 2, "defenseTimeouts": 3, "yardline": 75, "yardsToGoal": 75, "down": 1, "distance": 10, "yardsGained": 4, "scoring": false, "playType": "Rush", "playText": "Emmett Johnson run for 4 yds to the NEB 29", "ppa": -0.1142886249388964, "wallclock": "2025-10-18T02:41:11.000Z"}, {"gameId": 401752872, "driveId": "40175287216", "id": "401752872104884801", "driveNumber": 16, "playNumber": 3, "offense": "Nebraska", "offenseConference": "Big Ten", "offenseScore": 6, "defense": "Minnesota", "defenseConference": "Big Ten", "defenseScore": 21, "home": "Minnesota", "away": "Nebraska", "period": 4, "clock": {"minutes": 11, "seconds": 51}, "offenseTimeouts": 2, "defenseTimeouts": 3, "yardline": 71, "yardsToGoal": 71, "down": 2, "distance": 6, "yardsGained": 3, "scoring": false, "playType": "Pass Reception", "playText": "Dylan Raiola pass complete to Emmett Johnson for 3 yds to the NEB 32", "ppa": -0.2748655161762548, "wallclock": "2025-10-18T02:41:41.000Z"}, {"gameId": 401752872, "driveId": "40175287216", "id": "401752872104887901", "driveNumber": 16, "playNumber": 4, "offense": "Nebraska", "offenseConference": "Big Ten", "offenseScore": 6, "defense": "Minnesota", "defenseConference": "Big Ten", "defenseScore": 21, "home": "Minnesota", "away": "Nebraska", "period": 4, "clock": {"minutes": 11, "seconds": 20}, "offenseTimeouts": 2, "defenseTimeouts": 3, "yardline": 68, "yardsToGoal": 68, "down": 3, "distance": 3, "yardsGained": 9, "scoring": false, "playType": "Pass Reception", "playText": "Dylan Raiola pass complete to Emmett Johnson for 9 yds to the NEB 41 for a 1ST down", "ppa": 1.8078969110380454, "wallclock": "2025-10-18T02:42:14.000Z"}, {"gameId": 401752872, "driveId": "40175287216", "id": "401752872104894401", "driveNumber": 16, "playNumber": 5, "offense": "Nebraska", "offenseConference": "Big Ten", "offenseScore": 6, "defense": "Minnesota", "defenseConference": "Big Ten", "defenseScore": 21, "home": "Minnesota", "away": "Nebraska", "period": 4, "clock": {"minutes": 10, "seconds": 55}, "offenseTimeouts": 2, "defenseTimeouts": 3, "yardline": 59, "yardsToGoal": 59, "down": 1, "distance": 10, "yardsGained": 0, "scoring": false, "playType": "Pass Incompletion", "playText": "Dylan Raiola pass incomplete to Nyziah Hunter", "ppa": -1.1387859939569847, "wallclock": "2025-10-18T02:42:32.000Z"}, {"gameId": 401752872, "driveId": "40175287216", "id": "401752872104895001", "driveNumber": 16, "playNumber": 6, "offense": "Nebraska", "offenseConference": "Big Ten", "offenseScore": 6, "defense": "Minnesota", "defenseConference": "Big Ten", "defenseScore": 21, "home": "Minnesota", "away": "Nebraska", "period": 4, "clock": {"minutes": 10, "seconds": 49}, "offenseTimeouts": 2, "defenseTimeouts": 3, "yardline": 59, "yardsToGoal": 59, "down": 2, "distance": 10, "yardsGained": 2, "scoring": false, "playType": "Rush", "playText": "Isaiah Mozee run for 2 yds to the NEB 43", "ppa": -0.5021685129198507, "wallclock": "2025-10-18T02:43:30.000Z"}, {"gameId": 401752872, "driveId": "40175287216", "id": "401752872104898801", "driveNumber": 16, "playNumber": 7, "offense": "Nebraska", "offenseConference": "Big Ten", "offenseScore": 6, "defense": "Minnesota", "defenseConference": "Big Ten", "defenseScore": 21, "home": "Minnesota", "away": "Nebraska", "period": 4, "clock": {"minutes": 10, "seconds": 11}, "offenseTimeouts": 2, "defenseTimeouts": 3, "yardline": 57, "yardsToGoal": 57, "down": 3, "distance": 8, "yardsGained": -6, "scoring": false, "playType": "Sack", "playText": "Dylan Raiola sacked by Jaxon Howard for a loss of 6 yards to the NEB 37", "ppa": -0.9144639476734193, "wallclock": "2025-10-18T02:43:49.000Z"}, {"gameId": 401752872, "driveId": "40175287217", "id": "401752872104914802", "driveNumber": 17, "playNumber": 2, "offense": "Minnesota", "offenseConference": "Big Ten", "offenseScore": 21, "defense": "Nebraska", "defenseConference": "Big Ten", "defenseScore": 6, "home": "Minnesota", "away": "Nebraska", "period": 4, "clock": {"minutes": 8, "seconds": 51}, "offenseTimeouts": 3, "defenseTimeouts": 2, "yardline": 41, "yardsToGoal": 59, "down": 1, "distance": 10, "yardsGained": 5, "scoring": false, "playType": "Penalty", "playText": "(08:57) Taylor,Darius rush right for 1 yard loss to the MINN40 (Singleton,DeShon) PENALTY NEB Offside (Davis,Keona) 5 yards from MINN41 to MINN46. NO PLAY.", "ppa": null, "wallclock": "2025-10-18T02:49:14.000Z"}, {"gameId": 401752872, "driveId": "40175287217", "id": "401752872104947802", "driveNumber": 17, "playNumber": 8, "offense": "Minnesota", "offenseConference": "Big Ten", "offenseScore": 21, "defense": "Nebraska", "defenseConference": "Big Ten", "defenseScore": 6, "home": "Minnesota", "away": "Nebraska", "period": 4, "clock": {"minutes": 5, "seconds": 21}, "offenseTimeouts": 3, "defenseTimeouts": 1, "yardline": 88, "yardsToGoal": 12, "down": 3, "distance": 12, "yardsGained": 0, "scoring": false, "playType": "Timeout", "playText": "Timeout Nebraska, clock 05:21", "ppa": null, "wallclock": "2025-10-18T02:53:49.000Z"}, {"gameId": 401752872, "driveId": "40175287217", "id": "401752872104948501", "driveNumber": 17, "playNumber": 11, "offense": "Minnesota", "offenseConference": "Big Ten", "offenseScore": 24, "defense": "Nebraska", "defenseConference": "Big Ten", "defenseScore": 6, "home": "Minnesota", "away": "Nebraska", "period": 4, "clock": {"minutes": 5, "seconds": 14}, "offenseTimeouts": 3, "defenseTimeouts": 0, "yardline": 88, "yardsToGoal": 12, "down": 4, "distance": 12, "yardsGained": 30, "scoring": true, "playType": "Field Goal Good", "playText": "Brady Denaburg 30 yd FG GOOD", "ppa": null, "wallclock": "2025-10-18T02:56:30.000Z"}, {"gameId": 401752872, "driveId": "40175287217", "id": "401752872104948202", "driveNumber": 17, "playNumber": 10, "offense": "Minnesota", "offenseConference": "Big Ten", "offenseScore": 21, "defense": "Nebraska", "defenseConference": "Big Ten", "defenseScore": 6, "home": "Minnesota", "away": "Nebraska", "period": 4, "clock": {"minutes": 5, "seconds": 17}, "offenseTimeouts": 3, "defenseTimeouts": 0, "yardline": 88, "yardsToGoal": 12, "down": 4, "distance": 12, "yardsGained": 0, "scoring": false, "playType": "Timeout", "playText": "Timeout Nebraska, clock 05:17", "ppa": null, "wallclock": "2025-10-18T02:55:35.000Z"}, {"gameId": 401752872, "driveId": "40175287217", "id": "401752872104906901", "driveNumber": 17, "playNumber": 1, "offense": "Minnesota", "offenseConference": "Big Ten", "offenseScore": 21, "defense": "Nebraska", "defenseConference": "Big Ten", "defenseScore": 6, "home": "Minnesota", "away": "Nebraska", "period": 4, "clock": {"minutes": 9, "seconds": 30}, "offenseTimeouts": 3, "defenseTimeouts": 2, "yardline": 26, "yardsToGoal": 74, "down": 1, "distance": 10, "yardsGained": 15, "scoring": false, "playType": "Rush", "playText": "Darius Taylor run for 15 yds to the MINN 41 for a 1ST down", "ppa": 1.3477639626625386, "wallclock": "2025-10-18T02:48:20.000Z"}, {"gameId": 401752872, "driveId": "40175287217", "id": "401752872104918001", "driveNumber": 17, "playNumber": 3, "offense": "Minnesota", "offenseConference": "Big Ten", "offenseScore": 21, "defense": "Nebraska", "defenseConference": "Big Ten", "defenseScore": 6, "home": "Minnesota", "away": "Nebraska", "period": 4, "clock": {"minutes": 8, "seconds": 19}, "offenseTimeouts": 3, "defenseTimeouts": 2, "yardline": 46, "yardsToGoal": 54, "down": 1, "distance": 5, "yardsGained": 5, "scoring": false, "playType": "Rush", "playText": "Darius Taylor run for 5 yds to the NEB 49 for a 1ST down", "ppa": -0.5579740677897737, "wallclock": "2025-10-18T02:50:09.000Z"}, {"gameId": 401752872, "driveId": "40175287217", "id": "401752872104926802", "driveNumber": 17, "playNumber": 4, "offense": "Minnesota", "offenseConference": "Big Ten", "offenseScore": 21, "defense": "Nebraska", "defenseConference": "Big Ten", "defenseScore": 6, "home": "Minnesota", "away": "Nebraska", "period": 4, "clock": {"minutes": 7, "seconds": 31}, "offenseTimeouts": 3, "defenseTimeouts": 2, "yardline": 51, "yardsToGoal": 49, "down": 1, "distance": 10, "yardsGained": 26, "scoring": false, "playType": "Rush", "playText": "Darius Taylor run for 11 yds to the NEB 38 for a 1ST down Nebraska Penalty, Face Mask (15 yards) (Gabe Moore) to the NEB 23 for a 1ST down", "ppa": 1.0983528735660197, "wallclock": "2025-10-18T02:50:55.000Z"}, {"gameId": 401752872, "driveId": "40175287217", "id": "401752872104934501", "driveNumber": 17, "playNumber": 5, "offense": "Minnesota", "offenseConference": "Big Ten", "offenseScore": 21, "defense": "Nebraska", "defenseConference": "Big Ten", "defenseScore": 6, "home": "Minnesota", "away": "Nebraska", "period": 4, "clock": {"minutes": 6, "seconds": 54}, "offenseTimeouts": 3, "defenseTimeouts": 2, "yardline": 77, "yardsToGoal": 23, "down": 1, "distance": 10, "yardsGained": 14, "scoring": false, "playType": "Rush", "playText": "Fame Ijeboi run for 14 yds to the NEB 9 for a 1ST down", "ppa": 0.2397398544247605, "wallclock": "2025-10-18T02:52:03.000Z"}, {"gameId": 401752872, "driveId": "40175287217", "id": "401752872104939501", "driveNumber": 17, "playNumber": 6, "offense": "Minnesota", "offenseConference": "Big Ten", "offenseScore": 21, "defense": "Nebraska", "defenseConference": "Big Ten", "defenseScore": 6, "home": "Minnesota", "away": "Nebraska", "period": 4, "clock": {"minutes": 6, "seconds": 4}, "offenseTimeouts": 3, "defenseTimeouts": 2, "yardline": 91, "yardsToGoal": 9, "down": 1, "distance": 9, "yardsGained": -5, "scoring": false, "playType": "Rush", "playText": "Fame Ijeboi run for a loss of 5 yards to the NEB 14", "ppa": -0.6105100896172663, "wallclock": "2025-10-18T02:52:56.000Z"}, {"gameId": 401752872, "driveId": "40175287217", "id": "401752872104947801", "driveNumber": 17, "playNumber": 7, "offense": "Minnesota", "offenseConference": "Big Ten", "offenseScore": 21, "defense": "Nebraska", "defenseConference": "Big Ten", "defenseScore": 6, "home": "Minnesota", "away": "Nebraska", "period": 4, "clock": {"minutes": 5, "seconds": 21}, "offenseTimeouts": 3, "defenseTimeouts": 2, "yardline": 86, "yardsToGoal": 14, "down": 2, "distance": 14, "yardsGained": 2, "scoring": false, "playType": "Rush", "playText": "Darius Taylor run for 2 yds to the NEB 12", "ppa": -0.2002357298446427, "wallclock": "2025-10-18T02:53:49.000Z"}, {"gameId": 401752872, "driveId": "40175287217", "id": "401752872104948201", "driveNumber": 17, "playNumber": 9, "offense": "Minnesota", "offenseConference": "Big Ten", "offenseScore": 21, "defense": "Nebraska", "defenseConference": "Big Ten", "defenseScore": 6, "home": "Minnesota", "away": "Nebraska", "period": 4, "clock": {"minutes": 5, "seconds": 17}, "offenseTimeouts": 3, "defenseTimeouts": 1, "yardline": 88, "yardsToGoal": 12, "down": 3, "distance": 12, "yardsGained": 0, "scoring": false, "playType": "Rush", "playText": "Darius Taylor run for no gain to the NEB 12", "ppa": -0.5426183460122757, "wallclock": "2025-10-18T02:55:35.000Z"}, {"gameId": 401752872, "driveId": "40175287218", "id": "401752872104948502", "driveNumber": 18, "playNumber": 1, "offense": "Minnesota", "offenseConference": "Big Ten", "offenseScore": 24, "defense": "Nebraska", "defenseConference": "Big Ten", "defenseScore": 6, "home": "Minnesota", "away": "Nebraska", "period": 4, "clock": {"minutes": 5, "seconds": 14}, "offenseTimeouts": 3, "defenseTimeouts": 0, "yardline": 35, "yardsToGoal": 65, "down": 1, "distance": 10, "yardsGained": 0, "scoring": false, "playType": "Kickoff", "playText": "Brady Denaburg kickoff for 65 yds for a touchback", "ppa": null, "wallclock": "2025-10-18T03:00:12.000Z"}, {"gameId": 401752872, "driveId": "40175287218", "id": "401752872104949501", "driveNumber": 18, "playNumber": 2, "offense": "Nebraska", "offenseConference": "Big Ten", "offenseScore": 6, "defense": "Minnesota", "defenseConference": "Big Ten", "defenseScore": 24, "home": "Minnesota", "away": "Nebraska", "period": 4, "clock": {"minutes": 5, "seconds": 4}, "offenseTimeouts": 0, "defenseTimeouts": 3, "yardline": 75, "yardsToGoal": 75, "down": 1, "distance": 10, "yardsGained": 10, "scoring": false, "playType": "Pass Reception", "playText": "Dylan Raiola pass complete to Emmett Johnson for 10 yds to the NEB 35 for a 1ST down", "ppa": 0.8350381090299867, "wallclock": "2025-10-18T03:00:58.000Z"}, {"gameId": 401752872, "driveId": "40175287218", "id": "401752872104955701", "driveNumber": 18, "playNumber": 3, "offense": "Nebraska", "offenseConference": "Big Ten", "offenseScore": 6, "defense": "Minnesota", "defenseConference": "Big Ten", "defenseScore": 24, "home": "Minnesota", "away": "Nebraska", "period": 4, "clock": {"minutes": 4, "seconds": 42}, "offenseTimeouts": 0, "defenseTimeouts": 3, "yardline": 65, "yardsToGoal": 65, "down": 1, "distance": 10, "yardsGained": 9, "scoring": false, "playType": "Pass Reception", "playText": "Dylan Raiola pass complete to Luke Lindenmeyer for 9 yds to the NEB 44", "ppa": 1.3846699650971743, "wallclock": "2025-10-18T03:01:23.000Z"}, {"gameId": 401752872, "driveId": "40175287218", "id": "401752872104958701", "driveNumber": 18, "playNumber": 4, "offense": "Nebraska", "offenseConference": "Big Ten", "offenseScore": 6, "defense": "Minnesota", "defenseConference": "Big Ten", "defenseScore": 24, "home": "Minnesota", "away": "Nebraska", "period": 4, "clock": {"minutes": 4, "seconds": 12}, "offenseTimeouts": 0, "defenseTimeouts": 3, "yardline": 56, "yardsToGoal": 56, "down": 2, "distance": 1, "yardsGained": 10, "scoring": false, "playType": "Pass Reception", "playText": "Dylan Raiola pass complete to Nyziah Hunter for 10 yds to the MINN 46 for a 1ST down", "ppa": 0.3147596374596962, "wallclock": "2025-10-18T03:01:58.000Z"}, {"gameId": 401752872, "driveId": "40175287218", "id": "401752872104965301", "driveNumber": 18, "playNumber": 5, "offense": "Nebraska", "offenseConference": "Big Ten", "offenseScore": 6, "defense": "Minnesota", "defenseConference": "Big Ten", "defenseScore": 24, "home": "Minnesota", "away": "Nebraska", "period": 4, "clock": {"minutes": 3, "seconds": 46}, "offenseTimeouts": 0, "defenseTimeouts": 3, "yardline": 46, "yardsToGoal": 46, "down": 1, "distance": 10, "yardsGained": 9, "scoring": false, "playType": "Rush", "playText": "Emmett Johnson run for 9 yds to the MINN 37", "ppa": 0.9832760023277703, "wallclock": "2025-10-18T03:03:40.000Z"}, {"gameId": 401752872, "driveId": "40175287218", "id": "401752872104968001", "driveNumber": 18, "playNumber": 6, "offense": "Nebraska", "offenseConference": "Big Ten", "offenseScore": 6, "defense": "Minnesota", "defenseConference": "Big Ten", "defenseScore": 24, "home": "Minnesota", "away": "Nebraska", "period": 4, "clock": {"minutes": 3, "seconds": 19}, "offenseTimeouts": 0, "defenseTimeouts": 3, "yardline": 37, "yardsToGoal": 37, "down": 2, "distance": 1, "yardsGained": 0, "scoring": false, "playType": "Pass Incompletion", "playText": "Dylan Raiola pass incomplete to Emmett Johnson", "ppa": -1.0065878474640384, "wallclock": "2025-10-18T03:04:01.000Z"}, {"gameId": 401752872, "driveId": "40175287218", "id": "401752872104968401", "driveNumber": 18, "playNumber": 7, "offense": "Nebraska", "offenseConference": "Big Ten", "offenseScore": 6, "defense": "Minnesota", "defenseConference": "Big Ten", "defenseScore": 24, "home": "Minnesota", "away": "Nebraska", "period": 4, "clock": {"minutes": 3, "seconds": 15}, "offenseTimeouts": 0, "defenseTimeouts": 3, "yardline": 37, "yardsToGoal": 37, "down": 3, "distance": 1, "yardsGained": 0, "scoring": false, "playType": "Pass Incompletion", "playText": "Dylan Raiola pass incomplete to Luke Lindenmeyer", "ppa": -1.091197613624077, "wallclock": "2025-10-18T03:04:40.000Z"}, {"gameId": 401752872, "driveId": "40175287218", "id": "401752872104968901", "driveNumber": 18, "playNumber": 8, "offense": "Nebraska", "offenseConference": "Big Ten", "offenseScore": 6, "defense": "Minnesota", "defenseConference": "Big Ten", "defenseScore": 24, "home": "Minnesota", "away": "Nebraska", "period": 4, "clock": {"minutes": 3, "seconds": 10}, "offenseTimeouts": 0, "defenseTimeouts": 3, "yardline": 37, "yardsToGoal": 37, "down": 4, "distance": 1, "yardsGained": 0, "scoring": false, "playType": "Rush", "playText": "Emmett Johnson run for no gain to the MINN 37", "ppa": -2.3422031331051905, "wallclock": "2025-10-18T03:05:40.000Z"}, {"gameId": 401752872, "driveId": "40175287219", "id": "401752872104968905", "driveNumber": 19, "playNumber": 1, "offense": "Minnesota", "offenseConference": "Big Ten", "offenseScore": 24, "defense": "Nebraska", "defenseConference": "Big Ten", "defenseScore": 6, "home": "Minnesota", "away": "Nebraska", "period": 4, "clock": {"minutes": 3, "seconds": 10}, "offenseTimeouts": 2, "defenseTimeouts": 0, "yardline": 38, "yardsToGoal": 62, "down": 2, "distance": 9, "yardsGained": 0, "scoring": false, "playType": "Timeout", "playText": "Timeout Minnesota, clock 03:10", "ppa": null, "wallclock": "2025-10-18T03:05:40.000Z"}, {"gameId": 401752872, "driveId": "40175287219", "id": "401752872104979901", "driveNumber": 19, "playNumber": 4, "offense": "Minnesota", "offenseConference": "Big Ten", "offenseScore": 24, "defense": "Nebraska", "defenseConference": "Big Ten", "defenseScore": 6, "home": "Minnesota", "away": "Nebraska", "period": 4, "clock": {"minutes": 2, "seconds": 0}, "offenseTimeouts": 1, "defenseTimeouts": 0, "yardline": 39, "yardsToGoal": 61, "down": 3, "distance": 8, "yardsGained": 0, "scoring": false, "playType": "Timeout", "playText": "Timeout Minnesota, clock 02:00", "ppa": null, "wallclock": "2025-10-18T02:32:28.000Z"}, {"gameId": 401752872, "driveId": "40175287219", "id": "401752872104988601", "driveNumber": 19, "playNumber": 6, "offense": "Minnesota", "offenseConference": "Big Ten", "offenseScore": 24, "defense": "Nebraska", "defenseConference": "Big Ten", "defenseScore": 6, "home": "Minnesota", "away": "Nebraska", "period": 4, "clock": {"minutes": 1, "seconds": 13}, "offenseTimeouts": 0, "defenseTimeouts": 0, "yardline": 40, "yardsToGoal": 60, "down": 4, "distance": 7, "yardsGained": 0, "scoring": false, "playType": "Timeout", "playText": "Timeout Minnesota, clock 01:13", "ppa": null, "wallclock": "2025-10-18T02:32:28.000Z"}, {"gameId": 401752872, "driveId": "40175287219", "id": "401752872104994301", "driveNumber": 19, "playNumber": 7, "offense": "Minnesota", "offenseConference": "Big Ten", "offenseScore": 24, "defense": "Nebraska", "defenseConference": "Big Ten", "defenseScore": 6, "home": "Minnesota", "away": "Nebraska", "period": 4, "clock": {"minutes": 0, "seconds": 56}, "offenseTimeouts": 0, "defenseTimeouts": 0, "yardline": 40, "yardsToGoal": 60, "down": 4, "distance": 7, "yardsGained": 30, "scoring": false, "playType": "Punt", "playText": "Tom Weston punt for 45 yds, punt out-of-bounds at the NEB 45 , Jacory Barney Jr. returns for 30 yds to the NEB 45", "ppa": null, "wallclock": "2025-10-18T03:13:30.000Z"}, {"gameId": 401752872, "driveId": "40175287219", "id": "401752872104969501", "driveNumber": 19, "playNumber": 2, "offense": "Minnesota", "offenseConference": "Big Ten", "offenseScore": 24, "defense": "Nebraska", "defenseConference": "Big Ten", "defenseScore": 6, "home": "Minnesota", "away": "Nebraska", "period": 4, "clock": {"minutes": 3, "seconds": 4}, "offenseTimeouts": 2, "defenseTimeouts": 0, "yardline": 37, "yardsToGoal": 63, "down": 1, "distance": 10, "yardsGained": 1, "scoring": false, "playType": "Rush", "playText": "Darius Taylor run for 1 yd to the MINN 38", "ppa": -0.870939720055624, "wallclock": "2025-10-18T03:07:16.000Z"}, {"gameId": 401752872, "driveId": "40175287219", "id": "401752872104977501", "driveNumber": 19, "playNumber": 3, "offense": "Minnesota", "offenseConference": "Big Ten", "offenseScore": 24, "defense": "Nebraska", "defenseConference": "Big Ten", "defenseScore": 6, "home": "Minnesota", "away": "Nebraska", "period": 4, "clock": {"minutes": 2, "seconds": 24}, "offenseTimeouts": 2, "defenseTimeouts": 0, "yardline": 38, "yardsToGoal": 62, "down": 2, "distance": 9, "yardsGained": 1, "scoring": false, "playType": "Rush", "playText": "Darius Taylor run for 1 yd to the MINN 39", "ppa": -0.6220315049154719, "wallclock": "2025-10-18T03:07:50.000Z"}, {"gameId": 401752872, "driveId": "40175287219", "id": "401752872104984801", "driveNumber": 19, "playNumber": 5, "offense": "Minnesota", "offenseConference": "Big Ten", "offenseScore": 24, "defense": "Nebraska", "defenseConference": "Big Ten", "defenseScore": 6, "home": "Minnesota", "away": "Nebraska", "period": 4, "clock": {"minutes": 1, "seconds": 51}, "offenseTimeouts": 1, "defenseTimeouts": 0, "yardline": 39, "yardsToGoal": 61, "down": 3, "distance": 8, "yardsGained": 1, "scoring": false, "playType": "Rush", "playText": "Darius Taylor run for 1 yd to the MINN 40", "ppa": -0.3886933887665185, "wallclock": "2025-10-18T03:11:24.000Z"}, {"gameId": 401752872, "driveId": "40175287220", "id": "401752872104997602", "driveNumber": 20, "playNumber": 2, "offense": "Nebraska", "offenseConference": "Big Ten", "offenseScore": 6, "defense": "Minnesota", "defenseConference": "Big Ten", "defenseScore": 24, "home": "Minnesota", "away": "Nebraska", "period": 4, "clock": {"minutes": 0, "seconds": 0}, "offenseTimeouts": 0, "defenseTimeouts": 0, "yardline": 50, "yardsToGoal": 50, "down": 0, "distance": 5, "yardsGained": 0, "scoring": false, "playType": "End of Game", "playText": "End of 4th Quarter", "ppa": null, "wallclock": "2025-10-18T03:15:03.000Z"}, {"gameId": 401752872, "driveId": "40175287220", "id": "401752872104995201", "driveNumber": 20, "playNumber": 1, "offense": "Nebraska", "offenseConference": "Big Ten", "offenseScore": 6, "defense": "Minnesota", "defenseConference": "Big Ten", "defenseScore": 24, "home": "Minnesota", "away": "Nebraska", "period": 4, "clock": {"minutes": 0, "seconds": 47}, "offenseTimeouts": 0, "defenseTimeouts": 0, "yardline": 55, "yardsToGoal": 55, "down": 1, "distance": 10, "yardsGained": 5, "scoring": false, "playType": "Pass Reception", "playText": "Dylan Raiola pass complete to Luke Lindenmeyer for 5 yds to the 50 yard line", "ppa": 0.1079044232439195, "wallclock": "2025-10-18T03:14:16.000Z"}, {"gameId": 401752872, "driveId": "40175287220", "id": "401752872104999901", "driveNumber": 20, "playNumber": 3, "offense": "Nebraska", "offenseConference": "Big Ten", "offenseScore": 6, "defense": "Minnesota", "defenseConference": "Big Ten", "defenseScore": 24, "home": "Minnesota", "away": "Nebraska", "period": 4, "clock": {"minutes": 0, "seconds": 0}, "offenseTimeouts": 0, "defenseTimeouts": 0, "yardline": 50, "yardsToGoal": 50, "down": 2, "distance": 5, "yardsGained": -10, "scoring": false, "playType": "Sack", "playText": "Dylan Raiola sacked for a loss of 10 yards to the NEB 40", "ppa": -2.7497183428297225, "wallclock": "2025-10-18T03:15:03.000Z"}, {"gameId": 401752872, "driveId": "4017528727", "id": "401752872102899801", "driveNumber": 7, "playNumber": 4, "offense": "Minnesota", "offenseConference": "Big Ten", "offenseScore": 7, "defense": "Nebraska", "defenseConference": "Big Ten", "defenseScore": 3, "home": "Minnesota", "away": "Nebraska", "period": 2, "clock": {"minutes": 10, "seconds": 1}, "offenseTimeouts": 1, "defenseTimeouts": 3, "yardline": 47, "yardsToGoal": 53, "down": 4, "distance": 1, "yardsGained": 0, "scoring": false, "playType": "Timeout", "playText": "Timeout Minnesota, clock 10:01", "ppa": null, "wallclock": "2025-10-18T00:44:57.000Z"}, {"gameId": 401752872, "driveId": "4017528727", "id": "401752872102904601", "driveNumber": 7, "playNumber": 5, "offense": "Minnesota", "offenseConference": "Big Ten", "offenseScore": 7, "defense": "Nebraska", "defenseConference": "Big Ten", "defenseScore": 3, "home": "Minnesota", "away": "Nebraska", "period": 2, "clock": {"minutes": 9, "seconds": 53}, "offenseTimeouts": 1, "defenseTimeouts": 3, "yardline": 47, "yardsToGoal": 53, "down": 4, "distance": 1, "yardsGained": 0, "scoring": false, "playType": "Punt", "playText": "Tom Weston punt for 34 yds, fair catch by Jacory Barney Jr. at the NEB 19", "ppa": null, "wallclock": "2025-10-18T01:01:48.000Z"}, {"gameId": 401752872, "driveId": "4017528727", "id": "401752872102885901", "driveNumber": 7, "playNumber": 1, "offense": "Minnesota", "offenseConference": "Big Ten", "offenseScore": 7, "defense": "Nebraska", "defenseConference": "Big Ten", "defenseScore": 3, "home": "Minnesota", "away": "Nebraska", "period": 2, "clock": {"minutes": 11, "seconds": 40}, "offenseTimeouts": 2, "defenseTimeouts": 3, "yardline": 38, "yardsToGoal": 62, "down": 1, "distance": 10, "yardsGained": 1, "scoring": false, "playType": "Rush", "playText": "Darius Taylor run for 1 yd to the MINN 39", "ppa": -0.8867433222723466, "wallclock": "2025-10-18T00:58:39.000Z"}, {"gameId": 401752872, "driveId": "4017528727", "id": "401752872102889601", "driveNumber": 7, "playNumber": 2, "offense": "Minnesota", "offenseConference": "Big Ten", "offenseScore": 7, "defense": "Nebraska", "defenseConference": "Big Ten", "defenseScore": 3, "home": "Minnesota", "away": "Nebraska", "period": 2, "clock": {"minutes": 11, "seconds": 3}, "offenseTimeouts": 2, "defenseTimeouts": 3, "yardline": 39, "yardsToGoal": 61, "down": 2, "distance": 9, "yardsGained": 6, "scoring": false, "playType": "Rush", "playText": "Darius Taylor run for 6 yds to the MINN 45", "ppa": 0.3052283588613119, "wallclock": "2025-10-18T00:59:20.000Z"}, {"gameId": 401752872, "driveId": "4017528727", "id": "401752872102897201", "driveNumber": 7, "playNumber": 3, "offense": "Minnesota", "offenseConference": "Big Ten", "offenseScore": 7, "defense": "Nebraska", "defenseConference": "Big Ten", "defenseScore": 3, "home": "Minnesota", "away": "Nebraska", "period": 2, "clock": {"minutes": 10, "seconds": 27}, "offenseTimeouts": 2, "defenseTimeouts": 3, "yardline": 45, "yardsToGoal": 55, "down": 3, "distance": 3, "yardsGained": 2, "scoring": false, "playType": "Rush", "playText": "Darius Taylor run for 2 yds to the MINN 47", "ppa": -0.5717171851511065, "wallclock": "2025-10-18T01:00:04.000Z"}, {"gameId": 401752872, "driveId": "4017528728", "id": "401752872102957401", "driveNumber": 8, "playNumber": 8, "offense": "Nebraska", "offenseConference": "Big Ten", "offenseScore": 6, "defense": "Minnesota", "defenseConference": "Big Ten", "defenseScore": 7, "home": "Minnesota", "away": "Nebraska", "period": 2, "clock": {"minutes": 4, "seconds": 25}, "offenseTimeouts": 3, "defenseTimeouts": 1, "yardline": 12, "yardsToGoal": 12, "down": 4, "distance": 11, "yardsGained": 30, "scoring": true, "playType": "Field Goal Good", "playText": "Kyle Cunanan 30 yd FG GOOD", "ppa": null, "wallclock": "2025-10-18T01:12:10.000Z"}, {"gameId": 401752872, "driveId": "4017528728", "id": "401752872102905201", "driveNumber": 8, "playNumber": 1, "offense": "Nebraska", "offenseConference": "Big Ten", "offenseScore": 3, "defense": "Minnesota", "defenseConference": "Big Ten", "defenseScore": 7, "home": "Minnesota", "away": "Nebraska", "period": 2, "clock": {"minutes": 9, "seconds": 47}, "offenseTimeouts": 3, "defenseTimeouts": 1, "yardline": 81, "yardsToGoal": 81, "down": 1, "distance": 10, "yardsGained": 4, "scoring": false, "playType": "Rush", "playText": "Emmett Johnson run for 4 yds to the NEB 23", "ppa": -0.08358568772589688, "wallclock": "2025-10-18T01:02:25.000Z"}, {"gameId": 401752872, "driveId": "4017528728", "id": "401752872102909001", "driveNumber": 8, "playNumber": 2, "offense": "Nebraska", "offenseConference": "Big Ten", "offenseScore": 3, "defense": "Minnesota", "defenseConference": "Big Ten", "defenseScore": 7, "home": "Minnesota", "away": "Nebraska", "period": 2, "clock": {"minutes": 9, "seconds": 9}, "offenseTimeouts": 3, "defenseTimeouts": 1, "yardline": 77, "yardsToGoal": 77, "down": 2, "distance": 6, "yardsGained": 12, "scoring": false, "playType": "Pass Reception", "playText": "Dylan Raiola pass complete to Luke Lindenmeyer for 12 yds to the NEB 35 for a 1ST down", "ppa": 1.2794881980373587, "wallclock": "2025-10-18T01:03:07.000Z"}, {"gameId": 401752872, "driveId": "4017528728", "id": "401752872102917601", "driveNumber": 8, "playNumber": 3, "offense": "Nebraska", "offenseConference": "Big Ten", "offenseScore": 3, "defense": "Minnesota", "defenseConference": "Big Ten", "defenseScore": 7, "home": "Minnesota", "away": "Nebraska", "period": 2, "clock": {"minutes": 8, "seconds": 23}, "offenseTimeouts": 3, "defenseTimeouts": 1, "yardline": 65, "yardsToGoal": 65, "down": 1, "distance": 10, "yardsGained": 43, "scoring": false, "playType": "Pass Reception", "playText": "Dylan Raiola pass complete to Quinn Clark for 43 yds to the MINN 22 for a 1ST down", "ppa": 2.595094244042875, "wallclock": "2025-10-18T01:03:57.000Z"}, {"gameId": 401752872, "driveId": "4017528728", "id": "401752872102925401", "driveNumber": 8, "playNumber": 4, "offense": "Nebraska", "offenseConference": "Big Ten", "offenseScore": 3, "defense": "Minnesota", "defenseConference": "Big Ten", "defenseScore": 7, "home": "Minnesota", "away": "Nebraska", "period": 2, "clock": {"minutes": 7, "seconds": 45}, "offenseTimeouts": 3, "defenseTimeouts": 1, "yardline": 22, "yardsToGoal": 22, "down": 1, "distance": 10, "yardsGained": 11, "scoring": false, "playType": "Rush", "playText": "Emmett Johnson run for 11 yds to the MINN 11 for a 1ST down", "ppa": 0.125883353280535, "wallclock": "2025-10-18T01:04:41.000Z"}, {"gameId": 401752872, "driveId": "4017528728", "id": "401752872102934001", "driveNumber": 8, "playNumber": 5, "offense": "Nebraska", "offenseConference": "Big Ten", "offenseScore": 3, "defense": "Minnesota", "defenseConference": "Big Ten", "defenseScore": 7, "home": "Minnesota", "away": "Nebraska", "period": 2, "clock": {"minutes": 6, "seconds": 59}, "offenseTimeouts": 3, "defenseTimeouts": 1, "yardline": 11, "yardsToGoal": 11, "down": 1, "distance": 10, "yardsGained": -1, "scoring": false, "playType": "Rush", "playText": "Emmett Johnson run for a loss of 1 yard to the MINN 12", "ppa": -0.350629501927024, "wallclock": "2025-10-18T01:05:28.000Z"}, {"gameId": 401752872, "driveId": "4017528728", "id": "401752872102938301", "driveNumber": 8, "playNumber": 6, "offense": "Nebraska", "offenseConference": "Big Ten", "offenseScore": 3, "defense": "Minnesota", "defenseConference": "Big Ten", "defenseScore": 7, "home": "Minnesota", "away": "Nebraska", "period": 2, "clock": {"minutes": 6, "seconds": 16}, "offenseTimeouts": 3, "defenseTimeouts": 1, "yardline": 12, "yardsToGoal": 12, "down": 2, "distance": 11, "yardsGained": -6, "scoring": false, "playType": "Sack", "playText": "Dylan Raiola sacked by Karter Menz for a loss of 6 yards to the MINN 18", "ppa": -1.007935106437092, "wallclock": "2025-10-18T01:06:04.000Z"}, {"gameId": 401752872, "driveId": "4017528728", "id": "401752872102955201", "driveNumber": 8, "playNumber": 7, "offense": "Nebraska", "offenseConference": "Big Ten", "offenseScore": 3, "defense": "Minnesota", "defenseConference": "Big Ten", "defenseScore": 7, "home": "Minnesota", "away": "Nebraska", "period": 2, "clock": {"minutes": 4, "seconds": 47}, "offenseTimeouts": 3, "defenseTimeouts": 1, "yardline": 29, "yardsToGoal": 29, "down": 3, "distance": 28, "yardsGained": 17, "scoring": false, "playType": "Rush", "playText": "Dylan Raiola run for 17 yds to the MINN 12", "ppa": 2.314596480811315, "wallclock": "2025-10-18T01:11:46.000Z"}, {"gameId": 401752872, "driveId": "4017528729", "id": "401752872102957901", "driveNumber": 9, "playNumber": 1, "offense": "Nebraska", "offenseConference": "Big Ten", "offenseScore": 6, "defense": "Minnesota", "defenseConference": "Big Ten", "defenseScore": 7, "home": "Minnesota", "away": "Nebraska", "period": 2, "clock": {"minutes": 4, "seconds": 20}, "offenseTimeouts": 3, "defenseTimeouts": 1, "yardline": 65, "yardsToGoal": 65, "down": 1, "distance": 10, "yardsGained": 17, "scoring": false, "playType": "Kickoff Return (Offense)", "playText": "John Hohl kickoff for 63 yds , Cam Davis return for 17 yds to the MINN 19", "ppa": null, "wallclock": "2025-10-18T01:16:15.000Z"}, {"gameId": 401752872, "driveId": "4017528729", "id": "401752872102988802", "driveNumber": 9, "playNumber": 12, "offense": "Minnesota", "offenseConference": "Big Ten", "offenseScore": 7, "defense": "Nebraska", "defenseConference": "Big Ten", "defenseScore": 6, "home": "Minnesota", "away": "Nebraska", "period": 2, "clock": {"minutes": 1, "seconds": 11}, "offenseTimeouts": 0, "defenseTimeouts": 2, "yardline": 46, "yardsToGoal": 54, "down": 4, "distance": 10, "yardsGained": 0, "scoring": false, "playType": "Timeout", "playText": "Timeout Nebraska, clock 01:11", "ppa": null, "wallclock": "2025-10-18T01:25:53.000Z"}, {"gameId": 401752872, "driveId": "4017528729", "id": "401752872102989701", "driveNumber": 9, "playNumber": 13, "offense": "Minnesota", "offenseConference": "Big Ten", "offenseScore": 7, "defense": "Nebraska", "defenseConference": "Big Ten", "defenseScore": 6, "home": "Minnesota", "away": "Nebraska", "period": 2, "clock": {"minutes": 1, "seconds": 2}, "offenseTimeouts": 0, "defenseTimeouts": 2, "yardline": 46, "yardsToGoal": 54, "down": 4, "distance": 10, "yardsGained": 0, "scoring": false, "playType": "Punt", "playText": "Tom Weston punt for 40 yds , Jacory Barney Jr. returns for no gain to the NEB 6", "ppa": null, "wallclock": "2025-10-18T01:26:46.000Z"}, {"gameId": 401752872, "driveId": "4017528729", "id": "401752872102979901", "driveNumber": 9, "playNumber": 7, "offense": "Minnesota", "offenseConference": "Big Ten", "offenseScore": 7, "defense": "Nebraska", "defenseConference": "Big Ten", "defenseScore": 6, "home": "Minnesota", "away": "Nebraska", "period": 2, "clock": {"minutes": 2, "seconds": 0}, "offenseTimeouts": 0, "defenseTimeouts": 3, "yardline": 36, "yardsToGoal": 64, "down": 3, "distance": 9, "yardsGained": 0, "scoring": false, "playType": "Timeout", "playText": "Timeout Minnesota, clock 02:00", "ppa": null, "wallclock": "2025-10-18T00:44:57.000Z"}, {"gameId": 401752872, "driveId": "4017528729", "id": "401752872102969901", "driveNumber": 9, "playNumber": 5, "offense": "Minnesota", "offenseConference": "Big Ten", "offenseScore": 7, "defense": "Nebraska", "defenseConference": "Big Ten", "defenseScore": 6, "home": "Minnesota", "away": "Nebraska", "period": 2, "clock": {"minutes": 3, "seconds": 0}, "offenseTimeouts": 1, "defenseTimeouts": 3, "yardline": 35, "yardsToGoal": 65, "down": 1, "distance": 10, "yardsGained": 3, "scoring": false, "playType": "Rush", "playText": "Darius Taylor run for 3 yds to the MINN 38", "ppa": -0.4062307312880424, "wallclock": "2025-10-18T01:18:51.000Z"}, {"gameId": 401752872, "driveId": "4017528729", "id": "401752872102978001", "driveNumber": 9, "playNumber": 6, "offense": "Minnesota", "offenseConference": "Big Ten", "offenseScore": 7, "defense": "Nebraska", "defenseConference": "Big Ten", "defenseScore": 6, "home": "Minnesota", "away": "Nebraska", "period": 2, "clock": {"minutes": 2, "seconds": 19}, "offenseTimeouts": 1, "defenseTimeouts": 3, "yardline": 38, "yardsToGoal": 62, "down": 2, "distance": 7, "yardsGained": -2, "scoring": false, "playType": "Sack", "playText": "Drake Lindsey sacked for a loss of 2 yards to the MINN 36", "ppa": -1.1111155635905998, "wallclock": "2025-10-18T01:19:17.000Z"}, {"gameId": 401752872, "driveId": "4017528729", "id": "401752872102984701", "driveNumber": 9, "playNumber": 8, "offense": "Minnesota", "offenseConference": "Big Ten", "offenseScore": 7, "defense": "Nebraska", "defenseConference": "Big Ten", "defenseScore": 6, "home": "Minnesota", "away": "Nebraska", "period": 2, "clock": {"minutes": 1, "seconds": 52}, "offenseTimeouts": 0, "defenseTimeouts": 3, "yardline": 36, "yardsToGoal": 64, "down": 3, "distance": 9, "yardsGained": 10, "scoring": false, "playType": "Pass Reception", "playText": "Drake Lindsey pass complete to Jalen Smith for 10 yds to the MINN 46 for a 1ST down", "ppa": 2.575165767884769, "wallclock": "2025-10-18T01:23:35.000Z"}, {"gameId": 401752872, "driveId": "4017528729", "id": "401752872102986201", "driveNumber": 9, "playNumber": 9, "offense": "Minnesota", "offenseConference": "Big Ten", "offenseScore": 7, "defense": "Nebraska", "defenseConference": "Big Ten", "defenseScore": 6, "home": "Minnesota", "away": "Nebraska", "period": 2, "clock": {"minutes": 1, "seconds": 37}, "offenseTimeouts": 0, "defenseTimeouts": 3, "yardline": 46, "yardsToGoal": 54, "down": 1, "distance": 10, "yardsGained": 3, "scoring": false, "playType": "Pass Reception", "playText": "Drake Lindsey pass complete to Darius Taylor for 3 yds to the MINN 49", "ppa": -0.4184086843592085, "wallclock": "2025-10-18T01:24:18.000Z"}, {"gameId": 401752872, "driveId": "4017528729", "id": "401752872102988301", "driveNumber": 9, "playNumber": 10, "offense": "Minnesota", "offenseConference": "Big Ten", "offenseScore": 7, "defense": "Nebraska", "defenseConference": "Big Ten", "defenseScore": 6, "home": "Minnesota", "away": "Nebraska", "period": 2, "clock": {"minutes": 1, "seconds": 16}, "offenseTimeouts": 0, "defenseTimeouts": 3, "yardline": 49, "yardsToGoal": 51, "down": 2, "distance": 7, "yardsGained": 0, "scoring": false, "playType": "Pass Incompletion", "playText": "Drake Lindsey pass incomplete to Jameson Geers", "ppa": -1.1193582859534654, "wallclock": "2025-10-18T01:24:36.000Z"}, {"gameId": 401752872, "driveId": "4017528729", "id": "401752872102988801", "driveNumber": 9, "playNumber": 11, "offense": "Minnesota", "offenseConference": "Big Ten", "offenseScore": 7, "defense": "Nebraska", "defenseConference": "Big Ten", "defenseScore": 6, "home": "Minnesota", "away": "Nebraska", "period": 2, "clock": {"minutes": 1, "seconds": 11}, "offenseTimeouts": 0, "defenseTimeouts": 3, "yardline": 49, "yardsToGoal": 51, "down": 3, "distance": 7, "yardsGained": -3, "scoring": false, "playType": "Rush", "playText": "Darius Taylor run for a loss of 3 yards to the MINN 46", "ppa": -1.1378918507185194, "wallclock": "2025-10-18T01:25:25.000Z"}, {"gameId": 401752872, "driveId": "4017528729", "id": "401752872102958601", "driveNumber": 9, "playNumber": 2, "offense": "Minnesota", "offenseConference": "Big Ten", "offenseScore": 7, "defense": "Nebraska", "defenseConference": "Big Ten", "defenseScore": 6, "home": "Minnesota", "away": "Nebraska", "period": 2, "clock": {"minutes": 4, "seconds": 13}, "offenseTimeouts": 1, "defenseTimeouts": 3, "yardline": 19, "yardsToGoal": 81, "down": 1, "distance": 10, "yardsGained": 2, "scoring": false, "playType": "Rush", "playText": "Fame Ijeboi run for 2 yds to the MINN 21", "ppa": -0.345885638069002, "wallclock": "2025-10-18T01:16:44.000Z"}, {"gameId": 401752872, "driveId": "4017528729", "id": "401752872102966701", "driveNumber": 9, "playNumber": 3, "offense": "Minnesota", "offenseConference": "Big Ten", "offenseScore": 7, "defense": "Nebraska", "defenseConference": "Big Ten", "defenseScore": 6, "home": "Minnesota", "away": "Nebraska", "period": 2, "clock": {"minutes": 3, "seconds": 32}, "offenseTimeouts": 1, "defenseTimeouts": 3, "yardline": 21, "yardsToGoal": 79, "down": 2, "distance": 8, "yardsGained": 0, "scoring": false, "playType": "Pass Incompletion", "playText": "Drake Lindsey pass incomplete to Kenric Lanier II", "ppa": -0.3491696287441286, "wallclock": "2025-10-18T01:17:26.000Z"}, {"gameId": 401752872, "driveId": "4017528729", "id": "401752872102967701", "driveNumber": 9, "playNumber": 4, "offense": "Minnesota", "offenseConference": "Big Ten", "offenseScore": 7, "defense": "Nebraska", "defenseConference": "Big Ten", "defenseScore": 6, "home": "Minnesota", "away": "Nebraska", "period": 2, "clock": {"minutes": 3, "seconds": 22}, "offenseTimeouts": 1, "defenseTimeouts": 3, "yardline": 21, "yardsToGoal": 79, "down": 3, "distance": 8, "yardsGained": 14, "scoring": false, "playType": "Pass Reception", "playText": "Drake Lindsey pass complete to Jalen Smith for 14 yds to the MINN 35 for a 1ST down", "ppa": 1.8909577771245925, "wallclock": "2025-10-18T01:18:21.000Z"}, {"gameId": 401752872, "driveId": "40175287210", "id": "401752872102996802", "driveNumber": 10, "playNumber": 4, "offense": "Nebraska", "offenseConference": "Big Ten", "offenseScore": 6, "defense": "Minnesota", "defenseConference": "Big Ten", "defenseScore": 7, "home": "Minnesota", "away": "Nebraska", "period": 2, "clock": {"minutes": 0, "seconds": 31}, "offenseTimeouts": 1, "defenseTimeouts": 0, "yardline": 75, "yardsToGoal": 75, "down": 2, "distance": 3, "yardsGained": 0, "scoring": false, "playType": "Timeout", "playText": "Timeout Nebraska, clock 00:31", "ppa": null, "wallclock": "2025-10-18T01:28:51.000Z"}, {"gameId": 401752872, "driveId": "40175287210", "id": "401752872102997702", "driveNumber": 10, "playNumber": 5, "offense": "Nebraska", "offenseConference": "Big Ten", "offenseScore": 6, "defense": "Minnesota", "defenseConference": "Big Ten", "defenseScore": 7, "home": "Minnesota", "away": "Nebraska", "period": 2, "clock": {"minutes": 0, "seconds": 0}, "offenseTimeouts": 1, "defenseTimeouts": 0, "yardline": 75, "yardsToGoal": 75, "down": 0, "distance": 3, "yardsGained": 0, "scoring": false, "playType": "End of Half", "playText": "End of 2nd Quarter", "ppa": null, "wallclock": "2025-10-18T01:30:37.000Z"}, {"gameId": 401752872, "driveId": "40175287210", "id": "401752872102994301", "driveNumber": 10, "playNumber": 1, "offense": "Nebraska", "offenseConference": "Big Ten", "offenseScore": 6, "defense": "Minnesota", "defenseConference": "Big Ten", "defenseScore": 7, "home": "Minnesota", "away": "Nebraska", "period": 2, "clock": {"minutes": 0, "seconds": 56}, "offenseTimeouts": 2, "defenseTimeouts": 0, "yardline": 94, "yardsToGoal": 94, "down": 1, "distance": 10, "yardsGained": 0, "scoring": false, "playType": "Pass Incompletion", "playText": "Dylan Raiola pass incomplete to Nyziah Hunter", "ppa": -0.2935937291294204, "wallclock": "2025-10-18T01:27:31.000Z"}, {"gameId": 401752872, "driveId": "40175287210", "id": "401752872102994801", "driveNumber": 10, "playNumber": 2, "offense": "Nebraska", "offenseConference": "Big Ten", "offenseScore": 6, "defense": "Minnesota", "defenseConference": "Big Ten", "defenseScore": 7, "home": "Minnesota", "away": "Nebraska", "period": 2, "clock": {"minutes": 0, "seconds": 51}, "offenseTimeouts": 2, "defenseTimeouts": 0, "yardline": 94, "yardsToGoal": 94, "down": 2, "distance": 10, "yardsGained": 12, "scoring": false, "playType": "Pass Reception", "playText": "Dylan Raiola pass complete to Nyziah Hunter for 12 yds to the NEB 18 for a 1ST down", "ppa": 0.7019889406175963, "wallclock": "2025-10-18T01:28:13.000Z"}, {"gameId": 401752872, "driveId": "40175287210", "id": "401752872102996801", "driveNumber": 10, "playNumber": 3, "offense": "Nebraska", "offenseConference": "Big Ten", "offenseScore": 6, "defense": "Minnesota", "defenseConference": "Big Ten", "defenseScore": 7, "home": "Minnesota", "away": "Nebraska", "period": 2, "clock": {"minutes": 0, "seconds": 31}, "offenseTimeouts": 2, "defenseTimeouts": 0, "yardline": 82, "yardsToGoal": 82, "down": 1, "distance": 10, "yardsGained": 7, "scoring": false, "playType": "Rush", "playText": "Dylan Raiola run for 7 yds to the NEB 25", "ppa": 0.4935789008473366, "wallclock": "2025-10-18T01:28:39.000Z"}, {"gameId": 401752872, "driveId": "40175287210", "id": "401752872102999901", "driveNumber": 10, "playNumber": 6, "offense": "Nebraska", "offenseConference": "Big Ten", "offenseScore": 6, "defense": "Minnesota", "defenseConference": "Big Ten", "defenseScore": 7, "home": "Minnesota", "away": "Nebraska", "period": 2, "clock": {"minutes": 0, "seconds": 0}, "offenseTimeouts": 1, "defenseTimeouts": 0, "yardline": 75, "yardsToGoal": 75, "down": 2, "distance": 3, "yardsGained": -13, "scoring": false, "playType": "Sack", "playText": "Dylan Raiola sacked by Anthony Smith for a loss of 13 yards to the NEB 12", "ppa": -1.3550047103220297, "wallclock": "2025-10-18T01:30:37.000Z"}]