[{"gameId": 401752799, "driveId": "4017527991", "id": "401752799101914801", "driveNumber": 1, "playNumber": 14, "offense": "Iowa", "offenseConference": "Big Ten", "offenseScore": 3, "defense": "UAlbany", "defenseConference": "CAA", "defenseScore": 0, "home": "Iowa", "away": "UAlbany", "period": 1, "clock": {"minutes": 8, "seconds": 51}, "offenseTimeouts": 3, "defenseTimeouts": 3, "yardline": 90, "yardsToGoal": 10, "down": 4, "distance": 7, "yardsGained": 28, "scoring": true, "playType": "Field Goal Good", "playText": "Drew Stevens 28 yd FG GOOD", "ppa": null, "wallclock": "2025-08-30T22:25:07.000Z"}, {"gameId": 401752799, "driveId": "4017527991", "id": "401752799101849903", "driveNumber": 1, "playNumber": 1, "offense": "UAlbany", "offenseConference": "CAA", "offenseScore": 0, "defense": "Iowa", "defenseConference": "Big Ten", "defenseScore": 0, "home": "Iowa", "away": "UAlbany", "period": 1, "clock": {"minutes": 15, "seconds": 0}, "offenseTimeouts": 3, "defenseTimeouts": 3, "yardline": 65, "yardsToGoal": 65, "down": 1, "distance": 10, "yardsGained": 0, "scoring": false, "playType": "Kickoff", "playText": "James Bozek kickoff for 50 yds", "ppa": null, "wallclock": "2025-08-30T22:18:34.000Z"}, {"gameId": 401752799, "driveId": "4017527991", "id": "401752799101854701", "driveNumber": 1, "playNumber": 2, "offense": "Iowa", "offenseConference": "Big Ten", "offenseScore": 0, "defense": "UAlbany", "defenseConference": "CAA", "defenseScore": 0, "home": "Iowa", "away": "UAlbany", "period": 1, "clock": {"minutes": 14, "seconds": 52}, "offenseTimeouts": 3, "defenseTimeouts": 3, "yardline": 35, "yardsToGoal": 65, "down": 1, "distance": 10, "yardsGained": 10, "scoring": false, "playType": "Rush", "playText": "Kamari Moulton run for 10 yds to the IOWA 45 for a 1ST down", "ppa": 0.9661037733749698, "wallclock": "2025-08-30T22:18:34.000Z"}, {"gameId": 401752799, "driveId": "4017527991", "id": "401752799101859301", "driveNumber": 1, "playNumber": 3, "offense": "Iowa", "offenseConference": "Big Ten", "offenseScore": 0, "defense": "UAlbany", "defenseConference": "CAA", "defenseScore": 0, "home": "Iowa", "away": "UAlbany", "period": 1, "clock": {"minutes": 14, "seconds": 6}, "offenseTimeouts": 3, "defenseTimeouts": 3, "yardline": 45, "yardsToGoal": 55, "down": 1, "distance": 10, "yardsGained": 8, "scoring": false, "playType": "Pass Reception", "playText": "Mark Gronowski pass complete to Addison Ostrenga for 8 yds to the UALB 47", "ppa": 0.9420759997342945, "wallclock": "2025-08-30T22:18:34.000Z"}, {"gameId": 401752799, "driveId": "4017527991", "id": "401752799101865501", "driveNumber": 1, "playNumber": 4, "offense": "Iowa", "offenseConference": "Big Ten", "offenseScore": 0, "defense": "UAlbany", "defenseConference": "CAA", "defenseScore": 0, "home": "Iowa", "away": "UAlbany", "period": 1, "clock": {"minutes": 13, "seconds": 44}, "offenseTimeouts": 3, "defenseTimeouts": 3, "yardline": 53, "yardsToGoal": 47, "down": 2, "distance": 2, "yardsGained": 0, "scoring": false, "playType": "Pass Incompletion", "playText": "Mark Gronowski pass incomplete to Seth Anderson", "ppa": -1.267471633082744, "wallclock": "2025-08-30T22:18:34.000Z"}, {"gameId": 401752799, "driveId": "4017527991", "id": "401752799101866201", "driveNumber": 1, "playNumber": 5, "offense": "Iowa", "offenseConference": "Big Ten", "offenseScore": 0, "defense": "UAlbany", "defenseConference": "CAA", "defenseScore": 0, "home": "Iowa", "away": "UAlbany", "period": 1, "clock": {"minutes": 13, "seconds": 37}, "offenseTimeouts": 3, "defenseTimeouts": 3, "yardline": 53, "yardsToGoal": 47, "down": 3, "distance": 2, "yardsGained": 3, "scoring": false, "playType": "Rush", "playText": "Kamari Moulton run for 3 yds to the UALB 44 for a 1ST down", "ppa": 1.1891265131547932, "wallclock": "2025-08-30T22:19:28.000Z"}, {"gameId": 401752799, "driveId": "4017527991", "id": "401752799101874201", "driveNumber": 1, "playNumber": 6, "offense": "Iowa", "offenseConference": "Big Ten", "offenseScore": 0, "defense": "UAlbany", "defenseConference": "CAA", "defenseScore": 0, "home": "Iowa", "away": "UAlbany", "period": 1, "clock": {"minutes": 12, "seconds": 57}, "offenseTimeouts": 3, "defenseTimeouts": 3, "yardline": 56, "yardsToGoal": 44, "down": 1, "distance": 10, "yardsGained": 5, "scoring": false, "playType": "Rush", "playText": "Mark Gronowski run for 5 yds to the UALB 39", "ppa": 0.0928537506515159, "wallclock": "2025-08-30T22:19:51.000Z"}, {"gameId": 401752799, "driveId": "4017527991", "id": "401752799101878101", "driveNumber": 1, "playNumber": 7, "offense": "Iowa", "offenseConference": "Big Ten", "offenseScore": 0, "defense": "UAlbany", "defenseConference": "CAA", "defenseScore": 0, "home": "Iowa", "away": "UAlbany", "period": 1, "clock": {"minutes": 12, "seconds": 18}, "offenseTimeouts": 3, "defenseTimeouts": 3, "yardline": 61, "yardsToGoal": 39, "down": 2, "distance": 5, "yardsGained": 3, "scoring": false, "playType": "Rush", "playText": "Terrell Washington Jr. run for 3 yds to the UALB 36", "ppa": -0.3236338355316926, "wallclock": "2025-08-30T22:20:44.000Z"}, {"gameId": 401752799, "driveId": "4017527991", "id": "401752799101887001", "driveNumber": 1, "playNumber": 8, "offense": "Iowa", "offenseConference": "Big Ten", "offenseScore": 0, "defense": "UAlbany", "defenseConference": "CAA", "defenseScore": 0, "home": "Iowa", "away": "UAlbany", "period": 1, "clock": {"minutes": 11, "seconds": 29}, "offenseTimeouts": 3, "defenseTimeouts": 3, "yardline": 64, "yardsToGoal": 36, "down": 3, "distance": 2, "yardsGained": 6, "scoring": false, "playType": "Pass Reception", "playText": "Mark Gronowski pass complete to Hayden Large for 6 yds to the UALB 30 for a 1ST down", "ppa": 0.829419309467427, "wallclock": "2025-08-30T22:21:32.000Z"}, {"gameId": 401752799, "driveId": "4017527991", "id": "401752799101894401", "driveNumber": 1, "playNumber": 9, "offense": "Iowa", "offenseConference": "Big Ten", "offenseScore": 0, "defense": "UAlbany", "defenseConference": "CAA", "defenseScore": 0, "home": "Iowa", "away": "UAlbany", "period": 1, "clock": {"minutes": 10, "seconds": 55}, "offenseTimeouts": 3, "defenseTimeouts": 3, "yardline": 70, "yardsToGoal": 30, "down": 1, "distance": 10, "yardsGained": 8, "scoring": false, "playType": "Rush", "playText": "Mark Gronowski run for 8 yds to the UALB 22", "ppa": 0.512285959651141, "wallclock": "2025-08-30T22:22:01.000Z"}, {"gameId": 401752799, "driveId": "4017527991", "id": "401752799101898501", "driveNumber": 1, "playNumber": 10, "offense": "Iowa", "offenseConference": "Big Ten", "offenseScore": 0, "defense": "UAlbany", "defenseConference": "CAA", "defenseScore": 0, "home": "Iowa", "away": "UAlbany", "period": 1, "clock": {"minutes": 10, "seconds": 14}, "offenseTimeouts": 3, "defenseTimeouts": 3, "yardline": 78, "yardsToGoal": 22, "down": 2, "distance": 2, "yardsGained": 9, "scoring": false, "playType": "Rush", "playText": "Kamari Moulton run for 9 yds to the UALB 13 for a 1ST down", "ppa": -0.236972041774217, "wallclock": "2025-08-30T22:22:35.000Z"}, {"gameId": 401752799, "driveId": "4017527991", "id": "401752799101906001", "driveNumber": 1, "playNumber": 11, "offense": "Iowa", "offenseConference": "Big Ten", "offenseScore": 0, "defense": "UAlbany", "defenseConference": "CAA", "defenseScore": 0, "home": "Iowa", "away": "UAlbany", "period": 1, "clock": {"minutes": 9, "seconds": 39}, "offenseTimeouts": 3, "defenseTimeouts": 3, "yardline": 87, "yardsToGoal": 13, "down": 1, "distance": 10, "yardsGained": 0, "scoring": false, "playType": "Pass Incompletion", "playText": "Mark Gronowski pass incomplete to Sam Phillips", "ppa": -0.3048472994988835, "wallclock": "2025-08-30T22:23:07.000Z"}, {"gameId": 401752799, "driveId": "4017527991", "id": "401752799101906701", "driveNumber": 1, "playNumber": 12, "offense": "Iowa", "offenseConference": "Big Ten", "offenseScore": 0, "defense": "UAlbany", "defenseConference": "CAA", "defenseScore": 0, "home": "Iowa", "away": "UAlbany", "period": 1, "clock": {"minutes": 9, "seconds": 32}, "offenseTimeouts": 3, "defenseTimeouts": 3, "yardline": 87, "yardsToGoal": 13, "down": 2, "distance": 10, "yardsGained": 3, "scoring": false, "playType": "Rush", "playText": "Terrell Washington Jr. run for 3 yds to the UALB 10", "ppa": -0.0989376011541161, "wallclock": "2025-08-30T22:24:07.000Z"}, {"gameId": 401752799, "driveId": "4017527991", "id": "401752799101914501", "driveNumber": 1, "playNumber": 13, "offense": "Iowa", "offenseConference": "Big Ten", "offenseScore": 0, "defense": "UAlbany", "defenseConference": "CAA", "defenseScore": 0, "home": "Iowa", "away": "UAlbany", "period": 1, "clock": {"minutes": 8, "seconds": 54}, "offenseTimeouts": 3, "defenseTimeouts": 3, "yardline": 90, "yardsToGoal": 10, "down": 3, "distance": 7, "yardsGained": 0, "scoring": false, "playType": "Pass Incompletion", "playText": "Mark Gronowski pass incomplete to Terrell Washington Jr.", "ppa": -0.3837503518444549, "wallclock": "2025-08-30T22:24:40.000Z"}, {"gameId": 401752799, "driveId": "4017527992", "id": "401752799101935701", "driveNumber": 2, "playNumber": 5, "offense": "UAlbany", "offenseConference": "CAA", "offenseScore": 0, "defense": "Iowa", "defenseConference": "Big Ten", "defenseScore": 3, "home": "Iowa", "away": "UAlbany", "period": 1, "clock": {"minutes": 6, "seconds": 42}, "offenseTimeouts": 3, "defenseTimeouts": 3, "yardline": 67, "yardsToGoal": 67, "down": 4, "distance": 2, "yardsGained": 0, "scoring": false, "playType": "Punt", "playText": "Owen Lawson punt for 42 yds", "ppa": null, "wallclock": "2025-08-30T22:31:28.000Z"}, {"gameId": 401752799, "driveId": "4017527992", "id": "401752799101914802", "driveNumber": 2, "playNumber": 1, "offense": "Iowa", "offenseConference": "Big Ten", "offenseScore": 3, "defense": "UAlbany", "defenseConference": "CAA", "defenseScore": 0, "home": "Iowa", "away": "UAlbany", "period": 1, "clock": {"minutes": 8, "seconds": 51}, "offenseTimeouts": 3, "defenseTimeouts": 3, "yardline": 35, "yardsToGoal": 65, "down": 1, "distance": 10, "yardsGained": 0, "scoring": false, "playType": "Kickoff", "playText": "Drew Stevens kickoff for 65 yds for a touchback", "ppa": null, "wallclock": "2025-08-30T22:28:36.000Z"}, {"gameId": 401752799, "driveId": "4017527992", "id": "401752799101915601", "driveNumber": 2, "playNumber": 2, "offense": "UAlbany", "offenseConference": "CAA", "offenseScore": 0, "defense": "Iowa", "defenseConference": "Big Ten", "defenseScore": 3, "home": "Iowa", "away": "UAlbany", "period": 1, "clock": {"minutes": 8, "seconds": 43}, "offenseTimeouts": 3, "defenseTimeouts": 3, "yardline": 75, "yardsToGoal": 75, "down": 1, "distance": 10, "yardsGained": 3, "scoring": false, "playType": "Rush", "playText": "Jack Shields run for 3 yds to the UALB 28", "ppa": -0.2957674139440157, "wallclock": "2025-08-30T22:29:31.000Z"}, {"gameId": 401752799, "driveId": "4017527992", "id": "401752799101919001", "driveNumber": 2, "playNumber": 3, "offense": "UAlbany", "offenseConference": "CAA", "offenseScore": 0, "defense": "Iowa", "defenseConference": "Big Ten", "defenseScore": 3, "home": "Iowa", "away": "UAlbany", "period": 1, "clock": {"minutes": 8, "seconds": 9}, "offenseTimeouts": 3, "defenseTimeouts": 3, "yardline": 72, "yardsToGoal": 72, "down": 2, "distance": 7, "yardsGained": 0, "scoring": false, "playType": "Rush", "playText": "Griffin Woodell run for no gain to the UALB 28", "ppa": -0.5594317282120231, "wallclock": "2025-08-30T22:30:03.000Z"}, {"gameId": 401752799, "driveId": "4017527992", "id": "401752799101927401", "driveNumber": 2, "playNumber": 4, "offense": "UAlbany", "offenseConference": "CAA", "offenseScore": 0, "defense": "Iowa", "defenseConference": "Big Ten", "defenseScore": 3, "home": "Iowa", "away": "UAlbany", "period": 1, "clock": {"minutes": 7, "seconds": 25}, "offenseTimeouts": 3, "defenseTimeouts": 3, "yardline": 72, "yardsToGoal": 72, "down": 3, "distance": 7, "yardsGained": 5, "scoring": false, "playType": "Pass Reception", "playText": "Jack Shields pass complete to Tavahri Groves for 5 yds to the UALB 33", "ppa": 0.03429729127444769, "wallclock": "2025-08-30T22:30:57.000Z"}, {"gameId": 401752799, "driveId": "4017527993", "id": "401752799101948401", "driveNumber": 3, "playNumber": 3, "offense": "Iowa", "offenseConference": "Big Ten", "offenseScore": 3, "defense": "UAlbany", "defenseConference": "CAA", "defenseScore": 0, "home": "Iowa", "away": "UAlbany", "period": 1, "clock": {"minutes": 5, "seconds": 15}, "offenseTimeouts": 2, "defenseTimeouts": 3, "yardline": 17, "yardsToGoal": 83, "down": 3, "distance": 18, "yardsGained": 0, "scoring": false, "playType": "Timeout", "playText": "Timeout Iowa, clock 05:15", "ppa": null, "wallclock": "2025-08-30T22:19:00.000Z"}, {"gameId": 401752799, "driveId": "4017527993", "id": "401752799101956201", "driveNumber": 3, "playNumber": 5, "offense": "Iowa", "offenseConference": "Big Ten", "offenseScore": 3, "defense": "UAlbany", "defenseConference": "CAA", "defenseScore": 0, "home": "Iowa", "away": "UAlbany", "period": 1, "clock": {"minutes": 4, "seconds": 37}, "offenseTimeouts": 2, "defenseTimeouts": 3, "yardline": 21, "yardsToGoal": 79, "down": 4, "distance": 14, "yardsGained": 0, "scoring": false, "playType": "Punt", "playText": "Rhys Dakin punt for 47 yds, fair catch by Lasalle Rose Jr. at the UALB 32", "ppa": null, "wallclock": "2025-08-30T22:41:32.000Z"}, {"gameId": 401752799, "driveId": "4017527993", "id": "401752799101936401", "driveNumber": 3, "playNumber": 1, "offense": "Iowa", "offenseConference": "Big Ten", "offenseScore": 3, "defense": "UAlbany", "defenseConference": "CAA", "defenseScore": 0, "home": "Iowa", "away": "UAlbany", "period": 1, "clock": {"minutes": 6, "seconds": 35}, "offenseTimeouts": 3, "defenseTimeouts": 3, "yardline": 25, "yardsToGoal": 75, "down": 1, "distance": 10, "yardsGained": 0, "scoring": false, "playType": "Rush", "playText": "Terrell Washington Jr. run for no gain to the IOWA 25", "ppa": -0.7029700220436519, "wallclock": "2025-08-30T22:35:19.000Z"}, {"gameId": 401752799, "driveId": "4017527993", "id": "401752799101945301", "driveNumber": 3, "playNumber": 2, "offense": "Iowa", "offenseConference": "Big Ten", "offenseScore": 3, "defense": "UAlbany", "defenseConference": "CAA", "defenseScore": 0, "home": "Iowa", "away": "UAlbany", "period": 1, "clock": {"minutes": 5, "seconds": 46}, "offenseTimeouts": 3, "defenseTimeouts": 3, "yardline": 25, "yardsToGoal": 75, "down": 2, "distance": 10, "yardsGained": -8, "scoring": false, "playType": "Sack", "playText": "Mark Gronowski sacked by Nick Totten for a loss of 8 yards to the IOWA 17", "ppa": -0.5613069718334982, "wallclock": "2025-08-30T22:36:30.000Z"}, {"gameId": 401752799, "driveId": "4017527993", "id": "401752799101949201", "driveNumber": 3, "playNumber": 4, "offense": "Iowa", "offenseConference": "Big Ten", "offenseScore": 3, "defense": "UAlbany", "defenseConference": "CAA", "defenseScore": 0, "home": "Iowa", "away": "UAlbany", "period": 1, "clock": {"minutes": 5, "seconds": 7}, "offenseTimeouts": 2, "defenseTimeouts": 3, "yardline": 17, "yardsToGoal": 83, "down": 3, "distance": 18, "yardsGained": 4, "scoring": false, "playType": "Rush", "playText": "Mark Gronowski run for 4 yds to the IOWA 21", "ppa": -0.00773933029553664, "wallclock": "2025-08-30T22:41:05.000Z"}, {"gameId": 401752799, "driveId": "4017527994", "id": "401752799101968001", "driveNumber": 4, "playNumber": 4, "offense": "UAlbany", "offenseConference": "CAA", "offenseScore": 0, "defense": "Iowa", "defenseConference": "Big Ten", "defenseScore": 3, "home": "Iowa", "away": "UAlbany", "period": 1, "clock": {"minutes": 3, "seconds": 19}, "offenseTimeouts": 2, "defenseTimeouts": 2, "yardline": 59, "yardsToGoal": 59, "down": 4, "distance": 1, "yardsGained": 0, "scoring": false, "playType": "Timeout", "playText": "Timeout UAlbany, clock 03:19", "ppa": null, "wallclock": "2025-08-30T22:19:00.000Z"}, {"gameId": 401752799, "driveId": "4017527994", "id": "401752799101978001", "driveNumber": 4, "playNumber": 9, "offense": "UAlbany", "offenseConference": "CAA", "offenseScore": 0, "defense": "Iowa", "defenseConference": "Big Ten", "defenseScore": 3, "home": "Iowa", "away": "UAlbany", "period": 1, "clock": {"minutes": 2, "seconds": 19}, "offenseTimeouts": 2, "defenseTimeouts": 2, "yardline": 50, "yardsToGoal": 50, "down": 4, "distance": 10, "yardsGained": 0, "scoring": false, "playType": "Punt", "playText": "Owen Lawson punt for 35 yds, fair catch by Kaden Wetjen at the IOWA 15", "ppa": null, "wallclock": "2025-08-30T22:50:37.000Z"}, {"gameId": 401752799, "driveId": "4017527994", "id": "401752799101956801", "driveNumber": 4, "playNumber": 1, "offense": "UAlbany", "offenseConference": "CAA", "offenseScore": 0, "defense": "Iowa", "defenseConference": "Big Ten", "defenseScore": 3, "home": "Iowa", "away": "UAlbany", "period": 1, "clock": {"minutes": 4, "seconds": 31}, "offenseTimeouts": 3, "defenseTimeouts": 2, "yardline": 68, "yardsToGoal": 68, "down": 1, "distance": 10, "yardsGained": 4, "scoring": false, "playType": "Rush", "playText": "Griffin Woodell run for 4 yds to the UALB 36", "ppa": -0.1488498506411844, "wallclock": "2025-08-30T22:42:22.000Z"}, {"gameId": 401752799, "driveId": "4017527994", "id": "401752799101959901", "driveNumber": 4, "playNumber": 2, "offense": "UAlbany", "offenseConference": "CAA", "offenseScore": 0, "defense": "Iowa", "defenseConference": "Big Ten", "defenseScore": 3, "home": "Iowa", "away": "UAlbany", "period": 1, "clock": {"minutes": 4, "seconds": 0}, "offenseTimeouts": 3, "defenseTimeouts": 2, "yardline": 64, "yardsToGoal": 64, "down": 2, "distance": 6, "yardsGained": 0, "scoring": false, "playType": "Pass Incompletion", "playText": "Jack Shields pass incomplete to Carter Moses", "ppa": -0.8719338593954031, "wallclock": "2025-08-30T22:42:50.000Z"}, {"gameId": 401752799, "driveId": "4017527994", "id": "401752799101965101", "driveNumber": 4, "playNumber": 3, "offense": "UAlbany", "offenseConference": "CAA", "offenseScore": 0, "defense": "Iowa", "defenseConference": "Big Ten", "defenseScore": 3, "home": "Iowa", "away": "UAlbany", "period": 1, "clock": {"minutes": 3, "seconds": 48}, "offenseTimeouts": 3, "defenseTimeouts": 2, "yardline": 64, "yardsToGoal": 64, "down": 3, "distance": 6, "yardsGained": 5, "scoring": false, "playType": "Rush", "playText": "Jack Shields run for 5 yds to the UALB 41", "ppa": 0.0513827863815797, "wallclock": "2025-08-30T22:43:38.000Z"}, {"gameId": 401752799, "driveId": "4017527994", "id": "401752799101968901", "driveNumber": 4, "playNumber": 5, "offense": "UAlbany", "offenseConference": "CAA", "offenseScore": 0, "defense": "Iowa", "defenseConference": "Big Ten", "defenseScore": 3, "home": "Iowa", "away": "UAlbany", "period": 1, "clock": {"minutes": 3, "seconds": 10}, "offenseTimeouts": 2, "defenseTimeouts": 2, "yardline": 59, "yardsToGoal": 59, "down": 4, "distance": 1, "yardsGained": 9, "scoring": false, "playType": "Rush", "playText": "Jack Shields run for 9 yds to the 50 yard line for a 1ST down", "ppa": 2.6472997071754945, "wallclock": "2025-08-30T22:47:52.000Z"}, {"gameId": 401752799, "driveId": "4017527994", "id": "401752799101976401", "driveNumber": 4, "playNumber": 6, "offense": "UAlbany", "offenseConference": "CAA", "offenseScore": 0, "defense": "Iowa", "defenseConference": "Big Ten", "defenseScore": 3, "home": "Iowa", "away": "UAlbany", "period": 1, "clock": {"minutes": 2, "seconds": 35}, "offenseTimeouts": 2, "defenseTimeouts": 2, "yardline": 50, "yardsToGoal": 50, "down": 1, "distance": 10, "yardsGained": 0, "scoring": false, "playType": "Pass Incompletion", "playText": "Jack Shields pass incomplete to Lasalle Rose Jr.", "ppa": -1.1143038065675126, "wallclock": "2025-08-30T22:48:19.000Z"}, {"gameId": 401752799, "driveId": "4017527994", "id": "401752799101976901", "driveNumber": 4, "playNumber": 7, "offense": "UAlbany", "offenseConference": "CAA", "offenseScore": 0, "defense": "Iowa", "defenseConference": "Big Ten", "defenseScore": 3, "home": "Iowa", "away": "UAlbany", "period": 1, "clock": {"minutes": 2, "seconds": 30}, "offenseTimeouts": 2, "defenseTimeouts": 2, "yardline": 50, "yardsToGoal": 50, "down": 2, "distance": 10, "yardsGained": 0, "scoring": false, "playType": "Pass Incompletion", "playText": "Jack Shields pass incomplete to Carter Moses", "ppa": -1.0237730924311421, "wallclock": "2025-08-30T22:49:11.000Z"}, {"gameId": 401752799, "driveId": "4017527994", "id": "401752799101977301", "driveNumber": 4, "playNumber": 8, "offense": "UAlbany", "offenseConference": "CAA", "offenseScore": 0, "defense": "Iowa", "defenseConference": "Big Ten", "defenseScore": 3, "home": "Iowa", "away": "UAlbany", "period": 1, "clock": {"minutes": 2, "seconds": 26}, "offenseTimeouts": 2, "defenseTimeouts": 2, "yardline": 50, "yardsToGoal": 50, "down": 3, "distance": 10, "yardsGained": 0, "scoring": false, "playType": "Pass Incompletion", "playText": "Jack Shields pass incomplete to Tavahri Groves", "ppa": -0.7052334563220866, "wallclock": "2025-08-30T22:49:38.000Z"}, {"gameId": 401752799, "driveId": "4017527995", "id": "401752799101987501", "driveNumber": 5, "playNumber": 4, "offense": "Iowa", "offenseConference": "Big Ten", "offenseScore": 3, "defense": "UAlbany", "defenseConference": "CAA", "defenseScore": 0, "home": "Iowa", "away": "UAlbany", "period": 1, "clock": {"minutes": 1, "seconds": 24}, "offenseTimeouts": 2, "defenseTimeouts": 2, "yardline": 15, "yardsToGoal": 85, "down": 4, "distance": 10, "yardsGained": 0, "scoring": false, "playType": "Punt", "playText": "Rhys Dakin punt for 53 yds, fair catch by Lasalle Rose Jr. at the UALB 32", "ppa": null, "wallclock": "2025-08-30T22:56:09.000Z"}, {"gameId": 401752799, "driveId": "4017527995", "id": "401752799101978801", "driveNumber": 5, "playNumber": 1, "offense": "Iowa", "offenseConference": "Big Ten", "offenseScore": 3, "defense": "UAlbany", "defenseConference": "CAA", "defenseScore": 0, "home": "Iowa", "away": "UAlbany", "period": 1, "clock": {"minutes": 2, "seconds": 11}, "offenseTimeouts": 2, "defenseTimeouts": 2, "yardline": 15, "yardsToGoal": 85, "down": 1, "distance": 10, "yardsGained": 0, "scoring": false, "playType": "Pass Incompletion", "playText": "Mark Gronowski pass incomplete to Jacob Gill", "ppa": -0.4404078956667625, "wallclock": "2025-08-30T22:51:30.000Z"}, {"gameId": 401752799, "driveId": "4017527995", "id": "401752799101984001", "driveNumber": 5, "playNumber": 2, "offense": "Iowa", "offenseConference": "Big Ten", "offenseScore": 3, "defense": "UAlbany", "defenseConference": "CAA", "defenseScore": 0, "home": "Iowa", "away": "UAlbany", "period": 1, "clock": {"minutes": 1, "seconds": 59}, "offenseTimeouts": 2, "defenseTimeouts": 2, "yardline": 15, "yardsToGoal": 85, "down": 2, "distance": 10, "yardsGained": 0, "scoring": false, "playType": "Pass Incompletion", "playText": "Mark Gronowski pass incomplete to Seth Anderson", "ppa": -0.19768513834417423, "wallclock": "2025-08-30T22:52:24.000Z"}, {"gameId": 401752799, "driveId": "4017527995", "id": "401752799101986801", "driveNumber": 5, "playNumber": 3, "offense": "Iowa", "offenseConference": "Big Ten", "offenseScore": 3, "defense": "UAlbany", "defenseConference": "CAA", "defenseScore": 0, "home": "Iowa", "away": "UAlbany", "period": 1, "clock": {"minutes": 1, "seconds": 31}, "offenseTimeouts": 2, "defenseTimeouts": 2, "yardline": 15, "yardsToGoal": 85, "down": 3, "distance": 10, "yardsGained": 0, "scoring": false, "playType": "Pass Incompletion", "playText": "Mark Gronowski pass incomplete to KJ Parker", "ppa": -0.08613457617564713, "wallclock": "2025-08-30T22:55:16.000Z"}, {"gameId": 401752799, "driveId": "4017527996", "id": "401752799101999902", "driveNumber": 6, "playNumber": 4, "offense": "UAlbany", "offenseConference": "CAA", "offenseScore": 0, "defense": "Iowa", "defenseConference": "Big Ten", "defenseScore": 3, "home": "Iowa", "away": "UAlbany", "period": 1, "clock": {"minutes": 0, "seconds": 0}, "offenseTimeouts": 2, "defenseTimeouts": 2, "yardline": 57, "yardsToGoal": 57, "down": 0, "distance": 10, "yardsGained": 2, "scoring": false, "playType": "End Period", "playText": "End of 1st Quarter", "ppa": null, "wallclock": "2025-08-30T22:58:13.000Z"}, {"gameId": 401752799, "driveId": "4017527996", "id": "401752799102857301", "driveNumber": 6, "playNumber": 6, "offense": "UAlbany", "offenseConference": "CAA", "offenseScore": 0, "defense": "Iowa", "defenseConference": "Big Ten", "defenseScore": 3, "home": "Iowa", "away": "UAlbany", "period": 2, "clock": {"minutes": 14, "seconds": 26}, "offenseTimeouts": 2, "defenseTimeouts": 2, "yardline": 36, "yardsToGoal": 36, "down": 1, "distance": 10, "yardsGained": -5, "scoring": false, "playType": "Penalty", "playText": "(14:26) No Huddle-Shotgun Woodell,Griffin rush right for 2 yards gain to the Iowa34 (Hurkett,Ethan; Llewellyn,Max) PENALTY UA Illegal Formation 5 yards from Iowa36 to Iowa41. NO PLAY.", "ppa": null, "wallclock": "2025-08-30T23:04:14.000Z"}, {"gameId": 401752799, "driveId": "4017527996", "id": "401752799102879901", "driveNumber": 6, "playNumber": 11, "offense": "UAlbany", "offenseConference": "CAA", "offenseScore": 0, "defense": "Iowa", "defenseConference": "Big Ten", "defenseScore": 3, "home": "Iowa", "away": "UAlbany", "period": 2, "clock": {"minutes": 12, "seconds": 0}, "offenseTimeouts": 2, "defenseTimeouts": 2, "yardline": 4, "yardsToGoal": 4, "down": 3, "distance": 2, "yardsGained": -5, "scoring": false, "playType": "Penalty", "playText": "PENALTY UA False Start (Burti,Caden) 5 yards from Iowa04 to Iowa09. NO PLAY.", "ppa": null, "wallclock": "2025-08-30T23:07:29.000Z"}, {"gameId": 401752799, "driveId": "4017527996", "id": "401752799101988301", "driveNumber": 6, "playNumber": 1, "offense": "UAlbany", "offenseConference": "CAA", "offenseScore": 0, "defense": "Iowa", "defenseConference": "Big Ten", "defenseScore": 3, "home": "Iowa", "away": "UAlbany", "period": 1, "clock": {"minutes": 1, "seconds": 16}, "offenseTimeouts": 2, "defenseTimeouts": 2, "yardline": 68, "yardsToGoal": 68, "down": 1, "distance": 10, "yardsGained": 4, "scoring": false, "playType": "Rush", "playText": "Jack Shields run for 4 yds to the UALB 36", "ppa": -0.1488498506411844, "wallclock": "2025-08-30T22:56:44.000Z"}, {"gameId": 401752799, "driveId": "4017527996", "id": "401752799101996001", "driveNumber": 6, "playNumber": 2, "offense": "UAlbany", "offenseConference": "CAA", "offenseScore": 0, "defense": "Iowa", "defenseConference": "Big Ten", "defenseScore": 3, "home": "Iowa", "away": "UAlbany", "period": 1, "clock": {"minutes": 0, "seconds": 39}, "offenseTimeouts": 2, "defenseTimeouts": 2, "yardline": 64, "yardsToGoal": 64, "down": 2, "distance": 6, "yardsGained": 7, "scoring": false, "playType": "Pass Reception", "playText": "Jack Shields pass complete to Jasiah Barron for 7 yds to the UALB 43 for a 1ST down", "ppa": 1.2028438687717173, "wallclock": "2025-08-30T22:57:41.000Z"}, {"gameId": 401752799, "driveId": "4017527996", "id": "401752799101999901", "driveNumber": 6, "playNumber": 3, "offense": "UAlbany", "offenseConference": "CAA", "offenseScore": 0, "defense": "Iowa", "defenseConference": "Big Ten", "defenseScore": 3, "home": "Iowa", "away": "UAlbany", "period": 1, "clock": {"minutes": 0, "seconds": 0}, "offenseTimeouts": 2, "defenseTimeouts": 2, "yardline": 57, "yardsToGoal": 57, "down": 1, "distance": 10, "yardsGained": 2, "scoring": false, "playType": "Rush", "playText": "Jojo Uga run for 2 yds to the UALB 45", "ppa": -0.6861929923492786, "wallclock": "2025-08-30T22:58:13.000Z"}, {"gameId": 401752799, "driveId": "4017527996", "id": "401752799102856001", "driveNumber": 6, "playNumber": 5, "offense": "UAlbany", "offenseConference": "CAA", "offenseScore": 0, "defense": "Iowa", "defenseConference": "Big Ten", "defenseScore": 3, "home": "Iowa", "away": "UAlbany", "period": 2, "clock": {"minutes": 14, "seconds": 39}, "offenseTimeouts": 2, "defenseTimeouts": 2, "yardline": 55, "yardsToGoal": 55, "down": 2, "distance": 8, "yardsGained": 19, "scoring": false, "playType": "Pass Reception", "playText": "Jack Shields pass complete to Jasiah Barron for 19 yds to the IOWA 36 for a 1ST down", "ppa": 2.140731594846809, "wallclock": "2025-08-30T23:03:44.000Z"}, {"gameId": 401752799, "driveId": "4017527996", "id": "401752799102864203", "driveNumber": 6, "playNumber": 7, "offense": "UAlbany", "offenseConference": "CAA", "offenseScore": 0, "defense": "Iowa", "defenseConference": "Big Ten", "defenseScore": 3, "home": "Iowa", "away": "UAlbany", "period": 2, "clock": {"minutes": 13, "seconds": 57}, "offenseTimeouts": 2, "defenseTimeouts": 2, "yardline": 41, "yardsToGoal": 41, "down": 1, "distance": 15, "yardsGained": 2, "scoring": false, "playType": "Pass Reception", "playText": "Jack Shields pass complete to Griffin Woodell for 2 yds to the IOWA 39", "ppa": -0.5167576552376029, "wallclock": "2025-08-30T23:05:06.000Z"}, {"gameId": 401752799, "driveId": "4017527996", "id": "401752799102867101", "driveNumber": 6, "playNumber": 8, "offense": "UAlbany", "offenseConference": "CAA", "offenseScore": 0, "defense": "Iowa", "defenseConference": "Big Ten", "defenseScore": 3, "home": "Iowa", "away": "UAlbany", "period": 2, "clock": {"minutes": 13, "seconds": 28}, "offenseTimeouts": 2, "defenseTimeouts": 2, "yardline": 39, "yardsToGoal": 39, "down": 2, "distance": 13, "yardsGained": 27, "scoring": false, "playType": "Pass Reception", "playText": "Jack Shields pass complete to Caden Burti for 27 yds to the IOWA 12 for a 1ST down", "ppa": 1.775473781435581, "wallclock": "2025-08-30T23:05:33.000Z"}, {"gameId": 401752799, "driveId": "4017527996", "id": "401752799102869601", "driveNumber": 6, "playNumber": 9, "offense": "UAlbany", "offenseConference": "CAA", "offenseScore": 0, "defense": "Iowa", "defenseConference": "Big Ten", "defenseScore": 3, "home": "Iowa", "away": "UAlbany", "period": 2, "clock": {"minutes": 13, "seconds": 3}, "offenseTimeouts": 2, "defenseTimeouts": 2, "yardline": 12, "yardsToGoal": 12, "down": 1, "distance": 10, "yardsGained": 2, "scoring": false, "playType": "Rush", "playText": "Jack Shields run for 2 yds to the IOWA 10", "ppa": -0.1686350677656265, "wallclock": "2025-08-30T23:05:59.000Z"}, {"gameId": 401752799, "driveId": "4017527996", "id": "401752799102878101", "driveNumber": 6, "playNumber": 10, "offense": "UAlbany", "offenseConference": "CAA", "offenseScore": 0, "defense": "Iowa", "defenseConference": "Big Ten", "defenseScore": 3, "home": "Iowa", "away": "UAlbany", "period": 2, "clock": {"minutes": 12, "seconds": 18}, "offenseTimeouts": 2, "defenseTimeouts": 2, "yardline": 10, "yardsToGoal": 10, "down": 2, "distance": 8, "yardsGained": 6, "scoring": false, "playType": "Pass Reception", "playText": "Jack Shields pass complete to Alex Jreige for 6 yds to the IOWA 4", "ppa": 0.134204764299201, "wallclock": "2025-08-30T23:06:57.000Z"}, {"gameId": 401752799, "driveId": "4017527996", "id": "401752799102886601", "driveNumber": 6, "playNumber": 12, "offense": "UAlbany", "offenseConference": "CAA", "offenseScore": 7, "defense": "Iowa", "defenseConference": "Big Ten", "defenseScore": 3, "home": "Iowa", "away": "UAlbany", "period": 2, "clock": {"minutes": 11, "seconds": 33}, "offenseTimeouts": 2, "defenseTimeouts": 2, "yardline": 9, "yardsToGoal": 9, "down": 3, "distance": 7, "yardsGained": 9, "scoring": true, "playType": "Passing Touchdown", "playText": "Jack Shields pass complete to Lasalle Rose Jr. for 9 yds for a TD (James Bozek KICK)", "ppa": 2.921952491477786, "wallclock": "2025-08-30T23:08:20.000Z"}, {"gameId": 401752799, "driveId": "4017527997", "id": "401752799102886604", "driveNumber": 7, "playNumber": 1, "offense": "UAlbany", "offenseConference": "CAA", "offenseScore": 7, "defense": "Iowa", "defenseConference": "Big Ten", "defenseScore": 3, "home": "Iowa", "away": "UAlbany", "period": 2, "clock": {"minutes": 11, "seconds": 33}, "offenseTimeouts": 2, "defenseTimeouts": 2, "yardline": 65, "yardsToGoal": 65, "down": 1, "distance": 10, "yardsGained": 0, "scoring": false, "playType": "Kickoff", "playText": "James Bozek kickoff for 63 yds", "ppa": null, "wallclock": "2025-08-30T23:13:12.000Z"}, {"gameId": 401752799, "driveId": "4017527997", "id": "401752799102887301", "driveNumber": 7, "playNumber": 2, "offense": "Iowa", "offenseConference": "Big Ten", "offenseScore": 3, "defense": "UAlbany", "defenseConference": "CAA", "defenseScore": 7, "home": "Iowa", "away": "UAlbany", "period": 2, "clock": {"minutes": 11, "seconds": 26}, "offenseTimeouts": 2, "defenseTimeouts": 2, "yardline": 35, "yardsToGoal": 65, "down": 1, "distance": 10, "yardsGained": 14, "scoring": false, "playType": "Rush", "playText": "Xavier Williams run for 14 yds to the IOWA 49 for a 1ST down", "ppa": 1.3193498067983958, "wallclock": "2025-08-30T23:13:48.000Z"}, {"gameId": 401752799, "driveId": "4017527997", "id": "401752799102895001", "driveNumber": 7, "playNumber": 3, "offense": "Iowa", "offenseConference": "Big Ten", "offenseScore": 3, "defense": "UAlbany", "defenseConference": "CAA", "defenseScore": 7, "home": "Iowa", "away": "UAlbany", "period": 2, "clock": {"minutes": 10, "seconds": 49}, "offenseTimeouts": 2, "defenseTimeouts": 2, "yardline": 49, "yardsToGoal": 51, "down": 1, "distance": 10, "yardsGained": 27, "scoring": false, "playType": "Rush", "playText": "Xavier Williams run for 27 yds to the UALB 24 for a 1ST down", "ppa": 1.241929255285964, "wallclock": "2025-08-30T23:14:37.000Z"}, {"gameId": 401752799, "driveId": "4017527997", "id": "401752799102899401", "driveNumber": 7, "playNumber": 4, "offense": "Iowa", "offenseConference": "Big Ten", "offenseScore": 3, "defense": "UAlbany", "defenseConference": "CAA", "defenseScore": 7, "home": "Iowa", "away": "UAlbany", "period": 2, "clock": {"minutes": 10, "seconds": 5}, "offenseTimeouts": 2, "defenseTimeouts": 2, "yardline": 76, "yardsToGoal": 24, "down": 1, "distance": 10, "yardsGained": 5, "scoring": false, "playType": "Pass Reception", "playText": "Mark Gronowski pass complete to Seth Anderson for 5 yds to the UALB 19", "ppa": 0.075070788233958, "wallclock": "2025-08-30T23:15:08.000Z"}, {"gameId": 401752799, "driveId": "4017527997", "id": "401752799102907001", "driveNumber": 7, "playNumber": 5, "offense": "Iowa", "offenseConference": "Big Ten", "offenseScore": 3, "defense": "UAlbany", "defenseConference": "CAA", "defenseScore": 7, "home": "Iowa", "away": "UAlbany", "period": 2, "clock": {"minutes": 9, "seconds": 29}, "offenseTimeouts": 2, "defenseTimeouts": 2, "yardline": 81, "yardsToGoal": 19, "down": 2, "distance": 5, "yardsGained": 7, "scoring": false, "playType": "Rush", "playText": "Terrell Washington Jr. run for 7 yds to the UALB 12 for a 1ST down", "ppa": 0.0762726183370915, "wallclock": "2025-08-30T23:15:46.000Z"}, {"gameId": 401752799, "driveId": "4017527997", "id": "401752799102915501", "driveNumber": 7, "playNumber": 6, "offense": "Iowa", "offenseConference": "Big Ten", "offenseScore": 3, "defense": "UAlbany", "defenseConference": "CAA", "defenseScore": 7, "home": "Iowa", "away": "UAlbany", "period": 2, "clock": {"minutes": 8, "seconds": 44}, "offenseTimeouts": 2, "defenseTimeouts": 2, "yardline": 88, "yardsToGoal": 12, "down": 1, "distance": 10, "yardsGained": 5, "scoring": false, "playType": "Rush", "playText": "Terrell Washington Jr. run for 5 yds to the UALB 7", "ppa": 0.0748456356820665, "wallclock": "2025-08-30T23:16:46.000Z"}, {"gameId": 401752799, "driveId": "4017527997", "id": "401752799102919701", "driveNumber": 7, "playNumber": 7, "offense": "Iowa", "offenseConference": "Big Ten", "offenseScore": 3, "defense": "UAlbany", "defenseConference": "CAA", "defenseScore": 7, "home": "Iowa", "away": "UAlbany", "period": 2, "clock": {"minutes": 8, "seconds": 2}, "offenseTimeouts": 2, "defenseTimeouts": 2, "yardline": 93, "yardsToGoal": 7, "down": 2, "distance": 5, "yardsGained": 4, "scoring": false, "playType": "Rush", "playText": "Mark Gronowski run for 4 yds to the UALB 3", "ppa": -0.01693015803508, "wallclock": "2025-08-30T23:17:21.000Z"}, {"gameId": 401752799, "driveId": "4017527997", "id": "401752799102927101", "driveNumber": 7, "playNumber": 8, "offense": "Iowa", "offenseConference": "Big Ten", "offenseScore": 10, "defense": "UAlbany", "defenseConference": "CAA", "defenseScore": 7, "home": "Iowa", "away": "UAlbany", "period": 2, "clock": {"minutes": 7, "seconds": 28}, "offenseTimeouts": 2, "defenseTimeouts": 2, "yardline": 97, "yardsToGoal": 3, "down": 3, "distance": 1, "yardsGained": 3, "scoring": true, "playType": "Rushing Touchdown", "playText": "Xavier Williams run for 3 yds for a TD (Drew Stevens KICK)", "ppa": 2.472179064388939, "wallclock": "2025-08-30T23:17:51.000Z"}, {"gameId": 401752799, "driveId": "4017527998", "id": "401752799102927701", "driveNumber": 8, "playNumber": 1, "offense": "Iowa", "offenseConference": "Big Ten", "offenseScore": 10, "defense": "UAlbany", "defenseConference": "CAA", "defenseScore": 7, "home": "Iowa", "away": "UAlbany", "period": 2, "clock": {"minutes": 7, "seconds": 22}, "offenseTimeouts": 2, "defenseTimeouts": 2, "yardline": 35, "yardsToGoal": 65, "down": 1, "distance": 10, "yardsGained": 11, "scoring": false, "playType": "Kickoff Return (Offense)", "playText": "Drew Stevens kickoff for 61 yds , Lasalle Rose Jr. return for 11 yds to the UALB 15", "ppa": null, "wallclock": "2025-08-30T23:22:41.000Z"}, {"gameId": 401752799, "driveId": "4017527998", "id": "401752799102939601", "driveNumber": 8, "playNumber": 4, "offense": "UAlbany", "offenseConference": "CAA", "offenseScore": 7, "defense": "Iowa", "defenseConference": "Big Ten", "defenseScore": 10, "home": "Iowa", "away": "UAlbany", "period": 2, "clock": {"minutes": 6, "seconds": 3}, "offenseTimeouts": 2, "defenseTimeouts": 2, "yardline": 68, "yardsToGoal": 68, "down": 1, "distance": 10, "yardsGained": 4, "scoring": false, "playType": "Rush", "playText": "Jojo Uga run for 4 yds to the UALB 36", "ppa": -0.1488498506411844, "wallclock": "2025-08-30T23:24:30.000Z"}, {"gameId": 401752799, "driveId": "4017527998", "id": "401752799102947402", "driveNumber": 8, "playNumber": 5, "offense": "UAlbany", "offenseConference": "CAA", "offenseScore": 7, "defense": "Iowa", "defenseConference": "Big Ten", "defenseScore": 10, "home": "Iowa", "away": "UAlbany", "period": 2, "clock": {"minutes": 5, "seconds": 25}, "offenseTimeouts": 2, "defenseTimeouts": 2, "yardline": 64, "yardsToGoal": 64, "down": 2, "distance": 6, "yardsGained": -5, "scoring": false, "playType": "Penalty", "playText": "(05:31) No Huddle-Shotgun Shields,Jack pass incomplete deep middle to Barron,Jasiah thrown to Iowa20 PENALTY UA Illegal Formation 5 yards from UA 36 to UA 31. NO PLAY.", "ppa": null, "wallclock": "2025-08-30T23:25:02.000Z"}, {"gameId": 401752799, "driveId": "4017527998", "id": "401752799102955901", "driveNumber": 8, "playNumber": 8, "offense": "UAlbany", "offenseConference": "CAA", "offenseScore": 7, "defense": "Iowa", "defenseConference": "Big Ten", "defenseScore": 10, "home": "Iowa", "away": "UAlbany", "period": 2, "clock": {"minutes": 4, "seconds": 40}, "offenseTimeouts": 2, "defenseTimeouts": 2, "yardline": 62, "yardsToGoal": 62, "down": 4, "distance": 4, "yardsGained": 17, "scoring": false, "playType": "Punt", "playText": "Owen Lawson punt for 40 yds , Kaden Wetjen returns for 17 yds to the IOWA 39", "ppa": null, "wallclock": "2025-08-30T23:27:41.000Z"}, {"gameId": 401752799, "driveId": "4017527998", "id": "401752799102928701", "driveNumber": 8, "playNumber": 2, "offense": "UAlbany", "offenseConference": "CAA", "offenseScore": 7, "defense": "Iowa", "defenseConference": "Big Ten", "defenseScore": 10, "home": "Iowa", "away": "UAlbany", "period": 2, "clock": {"minutes": 7, "seconds": 12}, "offenseTimeouts": 2, "defenseTimeouts": 2, "yardline": 85, "yardsToGoal": 85, "down": 1, "distance": 10, "yardsGained": 6, "scoring": false, "playType": "Pass Reception", "playText": "Jack Shields pass complete to Griffin Woodell for 6 yds to the UALB 21", "ppa": 0.246959168535291, "wallclock": "2025-08-30T23:23:34.000Z"}, {"gameId": 401752799, "driveId": "4017527998", "id": "401752799102936001", "driveNumber": 8, "playNumber": 3, "offense": "UAlbany", "offenseConference": "CAA", "offenseScore": 7, "defense": "Iowa", "defenseConference": "Big Ten", "defenseScore": 10, "home": "Iowa", "away": "UAlbany", "period": 2, "clock": {"minutes": 6, "seconds": 39}, "offenseTimeouts": 2, "defenseTimeouts": 2, "yardline": 79, "yardsToGoal": 79, "down": 2, "distance": 4, "yardsGained": 11, "scoring": false, "playType": "Rush", "playText": "Jack Shields run for 11 yds to the UALB 32 for a 1ST down", "ppa": 0.8546916656980592, "wallclock": "2025-08-30T23:24:02.000Z"}, {"gameId": 401752799, "driveId": "4017527998", "id": "401752799102947801", "driveNumber": 8, "playNumber": 6, "offense": "UAlbany", "offenseConference": "CAA", "offenseScore": 7, "defense": "Iowa", "defenseConference": "Big Ten", "defenseScore": 10, "home": "Iowa", "away": "UAlbany", "period": 2, "clock": {"minutes": 5, "seconds": 21}, "offenseTimeouts": 2, "defenseTimeouts": 2, "yardline": 69, "yardsToGoal": 69, "down": 2, "distance": 11, "yardsGained": 0, "scoring": false, "playType": "Pass Incompletion", "playText": "Jack Shields pass incomplete to Jasiah Barron", "ppa": -0.4433837408098391, "wallclock": "2025-08-30T23:26:09.000Z"}, {"gameId": 401752799, "driveId": "4017527998", "id": "401752799102948601", "driveNumber": 8, "playNumber": 7, "offense": "UAlbany", "offenseConference": "CAA", "offenseScore": 7, "defense": "Iowa", "defenseConference": "Big Ten", "defenseScore": 10, "home": "Iowa", "away": "UAlbany", "period": 2, "clock": {"minutes": 5, "seconds": 13}, "offenseTimeouts": 2, "defenseTimeouts": 2, "yardline": 69, "yardsToGoal": 69, "down": 3, "distance": 11, "yardsGained": 7, "scoring": false, "playType": "Rush", "playText": "Jack Shields run for 7 yds to the UALB 38", "ppa": 0.1827006149922763, "wallclock": "2025-08-30T23:27:08.000Z"}, {"gameId": 401752799, "driveId": "4017527999", "id": "401752799102956501", "driveNumber": 9, "playNumber": 1, "offense": "Iowa", "offenseConference": "Big Ten", "offenseScore": 10, "defense": "UAlbany", "defenseConference": "CAA", "defenseScore": 7, "home": "Iowa", "away": "UAlbany", "period": 2, "clock": {"minutes": 4, "seconds": 34}, "offenseTimeouts": 2, "defenseTimeouts": 2, "yardline": 39, "yardsToGoal": 61, "down": 1, "distance": 10, "yardsGained": 9, "scoring": false, "playType": "Penalty", "playText": "UAlbany Penalty, Defensive Offside (Ron Holmes) declined", "ppa": null, "wallclock": "2025-08-30T23:31:53.000Z"}, {"gameId": 401752799, "driveId": "4017527999", "id": "401752799102979901", "driveNumber": 9, "playNumber": 6, "offense": "Iowa", "offenseConference": "Big Ten", "offenseScore": 10, "defense": "UAlbany", "defenseConference": "CAA", "defenseScore": 7, "home": "Iowa", "away": "UAlbany", "period": 2, "clock": {"minutes": 2, "seconds": 0}, "offenseTimeouts": 1, "defenseTimeouts": 2, "yardline": 96, "yardsToGoal": 4, "down": 3, "distance": 4, "yardsGained": 0, "scoring": false, "playType": "Timeout", "playText": "Timeout Iowa, clock 02:00", "ppa": null, "wallclock": "2025-08-30T23:03:44.000Z"}, {"gameId": 401752799, "driveId": "4017527999", "id": "401752799102984501", "driveNumber": 9, "playNumber": 8, "offense": "Iowa", "offenseConference": "Big Ten", "offenseScore": 10, "defense": "UAlbany", "defenseConference": "CAA", "defenseScore": 7, "home": "Iowa", "away": "UAlbany", "period": 2, "clock": {"minutes": 1, "seconds": 54}, "offenseTimeouts": 1, "defenseTimeouts": 1, "yardline": 98, "yardsToGoal": 2, "down": 4, "distance": 2, "yardsGained": 0, "scoring": false, "playType": "Timeout", "playText": "Timeout UAlbany, clock 01:54", "ppa": null, "wallclock": "2025-08-30T23:03:44.000Z"}, {"gameId": 401752799, "driveId": "4017527999", "id": "401752799102959301", "driveNumber": 9, "playNumber": 2, "offense": "Iowa", "offenseConference": "Big Ten", "offenseScore": 10, "defense": "UAlbany", "defenseConference": "CAA", "defenseScore": 7, "home": "Iowa", "away": "UAlbany", "period": 2, "clock": {"minutes": 4, "seconds": 6}, "offenseTimeouts": 2, "defenseTimeouts": 2, "yardline": 48, "yardsToGoal": 52, "down": 2, "distance": 1, "yardsGained": 0, "scoring": false, "playType": "Rush", "playText": "Terrell Washington Jr. run for no gain to the IOWA 48", "ppa": -1.4113338120086834, "wallclock": "2025-08-30T23:32:51.000Z"}, {"gameId": 401752799, "driveId": "4017527999", "id": "401752799102968001", "driveNumber": 9, "playNumber": 3, "offense": "Iowa", "offenseConference": "Big Ten", "offenseScore": 10, "defense": "UAlbany", "defenseConference": "CAA", "defenseScore": 7, "home": "Iowa", "away": "UAlbany", "period": 2, "clock": {"minutes": 3, "seconds": 19}, "offenseTimeouts": 2, "defenseTimeouts": 2, "yardline": 48, "yardsToGoal": 52, "down": 3, "distance": 1, "yardsGained": 43, "scoring": false, "playType": "Rush", "playText": "Xavier Williams run for 43 yds to the UALB 9 for a 1ST down", "ppa": 2.4878374922217166, "wallclock": "2025-08-30T23:33:46.000Z"}, {"gameId": 401752799, "driveId": "4017527999", "id": "401752799102974801", "driveNumber": 9, "playNumber": 4, "offense": "Iowa", "offenseConference": "Big Ten", "offenseScore": 10, "defense": "UAlbany", "defenseConference": "CAA", "defenseScore": 7, "home": "Iowa", "away": "UAlbany", "period": 2, "clock": {"minutes": 2, "seconds": 51}, "offenseTimeouts": 2, "defenseTimeouts": 2, "yardline": 91, "yardsToGoal": 9, "down": 1, "distance": 9, "yardsGained": 3, "scoring": false, "playType": "Rush", "playText": "Xavier Williams run for 3 yds to the UALB 6", "ppa": -0.10442916913547, "wallclock": "2025-08-30T23:33:48.000Z"}, {"gameId": 401752799, "driveId": "4017527999", "id": "401752799102979001", "driveNumber": 9, "playNumber": 5, "offense": "Iowa", "offenseConference": "Big Ten", "offenseScore": 10, "defense": "UAlbany", "defenseConference": "CAA", "defenseScore": 7, "home": "Iowa", "away": "UAlbany", "period": 2, "clock": {"minutes": 2, "seconds": 9}, "offenseTimeouts": 2, "defenseTimeouts": 2, "yardline": 94, "yardsToGoal": 6, "down": 2, "distance": 6, "yardsGained": 2, "scoring": false, "playType": "Rush", "playText": "Mark Gronowski run for 2 yds to the UALB 4", "ppa": -0.1673059286946435, "wallclock": "2025-08-30T23:34:41.000Z"}, {"gameId": 401752799, "driveId": "4017527999", "id": "401752799102984401", "driveNumber": 9, "playNumber": 7, "offense": "Iowa", "offenseConference": "Big Ten", "offenseScore": 10, "defense": "UAlbany", "defenseConference": "CAA", "defenseScore": 7, "home": "Iowa", "away": "UAlbany", "period": 2, "clock": {"minutes": 1, "seconds": 55}, "offenseTimeouts": 1, "defenseTimeouts": 2, "yardline": 96, "yardsToGoal": 4, "down": 3, "distance": 4, "yardsGained": 2, "scoring": false, "playType": "Rush", "playText": "Mark Gronowski run for 2 yds to the UALB 2", "ppa": -0.1553797797778205, "wallclock": "2025-08-30T23:03:44.000Z"}, {"gameId": 401752799, "driveId": "4017527999", "id": "401752799102984801", "driveNumber": 9, "playNumber": 9, "offense": "Iowa", "offenseConference": "Big Ten", "offenseScore": 17, "defense": "UAlbany", "defenseConference": "CAA", "defenseScore": 7, "home": "Iowa", "away": "UAlbany", "period": 2, "clock": {"minutes": 1, "seconds": 51}, "offenseTimeouts": 1, "defenseTimeouts": 1, "yardline": 98, "yardsToGoal": 2, "down": 4, "distance": 2, "yardsGained": 2, "scoring": true, "playType": "Passing Touchdown", "playText": "Mark Gronowski pass complete to Kaden Wetjen for 2 yds for a TD (Drew Stevens KICK)", "ppa": 2.851352701254402, "wallclock": "2025-08-30T23:03:44.000Z"}, {"gameId": 401752799, "driveId": "40175279910", "id": "401752799102984803", "driveNumber": 10, "playNumber": 1, "offense": "Iowa", "offenseConference": "Big Ten", "offenseScore": 17, "defense": "UAlbany", "defenseConference": "CAA", "defenseScore": 7, "home": "Iowa", "away": "UAlbany", "period": 2, "clock": {"minutes": 1, "seconds": 51}, "offenseTimeouts": 1, "defenseTimeouts": 1, "yardline": 35, "yardsToGoal": 65, "down": 1, "distance": 10, "yardsGained": 0, "scoring": false, "playType": "Kickoff", "playText": "Drew Stevens kickoff for 65 yds for a touchback", "ppa": null, "wallclock": "2025-08-30T23:03:44.000Z"}, {"gameId": 401752799, "driveId": "40175279910", "id": "401752799102999101", "driveNumber": 10, "playNumber": 6, "offense": "UAlbany", "offenseConference": "CAA", "offenseScore": 7, "defense": "Iowa", "defenseConference": "Big Ten", "defenseScore": 17, "home": "Iowa", "away": "UAlbany", "period": 2, "clock": {"minutes": 0, "seconds": 8}, "offenseTimeouts": 1, "defenseTimeouts": 1, "yardline": 48, "yardsToGoal": 48, "down": 4, "distance": 8, "yardsGained": 0, "scoring": false, "playType": "Punt", "playText": "Owen Lawson punt for 39 yds", "ppa": null, "wallclock": "2025-08-30T23:45:45.000Z"}, {"gameId": 401752799, "driveId": "40175279910", "id": "401752799102985301", "driveNumber": 10, "playNumber": 2, "offense": "UAlbany", "offenseConference": "CAA", "offenseScore": 7, "defense": "Iowa", "defenseConference": "Big Ten", "defenseScore": 17, "home": "Iowa", "away": "UAlbany", "period": 2, "clock": {"minutes": 1, "seconds": 46}, "offenseTimeouts": 1, "defenseTimeouts": 1, "yardline": 75, "yardsToGoal": 75, "down": 1, "distance": 10, "yardsGained": 25, "scoring": false, "playType": "Pass Reception", "playText": "Jack Shields pass complete to Caden Burti for 25 yds to the 50 yard line for a 1ST down", "ppa": 2.2363431875999487, "wallclock": "2025-08-30T23:42:47.000Z"}, {"gameId": 401752799, "driveId": "40175279910", "id": "401752799102986001", "driveNumber": 10, "playNumber": 3, "offense": "UAlbany", "offenseConference": "CAA", "offenseScore": 7, "defense": "Iowa", "defenseConference": "Big Ten", "defenseScore": 17, "home": "Iowa", "away": "UAlbany", "period": 2, "clock": {"minutes": 1, "seconds": 39}, "offenseTimeouts": 1, "defenseTimeouts": 1, "yardline": 50, "yardsToGoal": 50, "down": 1, "distance": 10, "yardsGained": -6, "scoring": false, "playType": "Sack", "playText": "Jack Shields sacked by Max Llewellyn for a loss of 6 yards to the UALB 44", "ppa": -2.358868019121446, "wallclock": "2025-08-30T23:43:18.000Z"}, {"gameId": 401752799, "driveId": "40175279910", "id": "401752799102989801", "driveNumber": 10, "playNumber": 4, "offense": "UAlbany", "offenseConference": "CAA", "offenseScore": 7, "defense": "Iowa", "defenseConference": "Big Ten", "defenseScore": 17, "home": "Iowa", "away": "UAlbany", "period": 2, "clock": {"minutes": 1, "seconds": 1}, "offenseTimeouts": 1, "defenseTimeouts": 1, "yardline": 56, "yardsToGoal": 56, "down": 2, "distance": 16, "yardsGained": 8, "scoring": false, "playType": "Rush", "playText": "Jack Shields run for 8 yds to the IOWA 48", "ppa": 0.6240162819472923, "wallclock": "2025-08-30T23:44:19.000Z"}, {"gameId": 401752799, "driveId": "40175279910", "id": "401752799102997701", "driveNumber": 10, "playNumber": 5, "offense": "UAlbany", "offenseConference": "CAA", "offenseScore": 7, "defense": "Iowa", "defenseConference": "Big Ten", "defenseScore": 17, "home": "Iowa", "away": "UAlbany", "period": 2, "clock": {"minutes": 0, "seconds": 22}, "offenseTimeouts": 1, "defenseTimeouts": 1, "yardline": 48, "yardsToGoal": 48, "down": 3, "distance": 8, "yardsGained": 0, "scoring": false, "playType": "Pass Incompletion", "playText": "Jack Shields pass incomplete to Caden Burti", "ppa": -0.8552184337457032, "wallclock": "2025-08-30T23:44:22.000Z"}, {"gameId": 401752799, "driveId": "40175279911", "id": "401752799102999902", "driveNumber": 11, "playNumber": 2, "offense": "Iowa", "offenseConference": "Big Ten", "offenseScore": 17, "defense": "UAlbany", "defenseConference": "CAA", "defenseScore": 7, "home": "Iowa", "away": "UAlbany", "period": 2, "clock": {"minutes": 0, "seconds": 0}, "offenseTimeouts": 1, "defenseTimeouts": 1, "yardline": 9, "yardsToGoal": 91, "down": 0, "distance": 10, "yardsGained": 4, "scoring": false, "playType": "End of Half", "playText": "End of 2nd Quarter", "ppa": null, "wallclock": "2025-08-30T23:46:41.000Z"}, {"gameId": 401752799, "driveId": "40175279911", "id": "401752799102999901", "driveNumber": 11, "playNumber": 1, "offense": "Iowa", "offenseConference": "Big Ten", "offenseScore": 17, "defense": "UAlbany", "defenseConference": "CAA", "defenseScore": 7, "home": "Iowa", "away": "UAlbany", "period": 2, "clock": {"minutes": 0, "seconds": 0}, "offenseTimeouts": 1, "defenseTimeouts": 1, "yardline": 9, "yardsToGoal": 91, "down": 1, "distance": 10, "yardsGained": 4, "scoring": false, "playType": "Rush", "playText": "Xavier Williams run for 4 yds to the IOWA 13", "ppa": -0.04486009398484114, "wallclock": "2025-08-30T23:46:41.000Z"}, {"gameId": 401752799, "driveId": "40175279912", "id": "401752799103854301", "driveNumber": 12, "playNumber": 1, "offense": "Iowa", "offenseConference": "Big Ten", "offenseScore": 17, "defense": "UAlbany", "defenseConference": "CAA", "defenseScore": 7, "home": "Iowa", "away": "UAlbany", "period": 3, "clock": {"minutes": 14, "seconds": 56}, "offenseTimeouts": 3, "defenseTimeouts": 3, "yardline": 35, "yardsToGoal": 65, "down": 1, "distance": 10, "yardsGained": 6, "scoring": false, "playType": "Kickoff Return (Offense)", "playText": "Drew Stevens kickoff for 56 yds , Lasalle Rose Jr. return for 6 yds to the UALB 15", "ppa": null, "wallclock": "2025-08-31T00:08:24.000Z"}, {"gameId": 401752799, "driveId": "40175279912", "id": "401752799103864401", "driveNumber": 12, "playNumber": 5, "offense": "UAlbany", "offenseConference": "CAA", "offenseScore": 7, "defense": "Iowa", "defenseConference": "Big Ten", "defenseScore": 17, "home": "Iowa", "away": "UAlbany", "period": 3, "clock": {"minutes": 13, "seconds": 55}, "offenseTimeouts": 3, "defenseTimeouts": 3, "yardline": 76, "yardsToGoal": 76, "down": 4, "distance": 1, "yardsGained": 0, "scoring": false, "playType": "Punt", "playText": "Owen Lawson punt for 36 yds, punt out-of-bounds at the IOWA 40", "ppa": null, "wallclock": "2025-08-31T00:10:54.000Z"}, {"gameId": 401752799, "driveId": "40175279912", "id": "401752799103854801", "driveNumber": 12, "playNumber": 2, "offense": "UAlbany", "offenseConference": "CAA", "offenseScore": 7, "defense": "Iowa", "defenseConference": "Big Ten", "defenseScore": 17, "home": "Iowa", "away": "UAlbany", "period": 3, "clock": {"minutes": 14, "seconds": 51}, "offenseTimeouts": 3, "defenseTimeouts": 3, "yardline": 85, "yardsToGoal": 85, "down": 1, "distance": 10, "yardsGained": 0, "scoring": false, "playType": "Pass Incompletion", "playText": "Jack Shields pass incomplete to Caden Burti", "ppa": -0.4404078956667625, "wallclock": "2025-08-31T00:08:53.000Z"}, {"gameId": 401752799, "driveId": "40175279912", "id": "401752799103855101", "driveNumber": 12, "playNumber": 3, "offense": "UAlbany", "offenseConference": "CAA", "offenseScore": 7, "defense": "Iowa", "defenseConference": "Big Ten", "defenseScore": 17, "home": "Iowa", "away": "UAlbany", "period": 3, "clock": {"minutes": 14, "seconds": 48}, "offenseTimeouts": 3, "defenseTimeouts": 3, "yardline": 85, "yardsToGoal": 85, "down": 2, "distance": 10, "yardsGained": 0, "scoring": false, "playType": "Pass Incompletion", "playText": "Jack Shields pass incomplete to Lasalle Rose Jr.", "ppa": -0.19768513834417423, "wallclock": "2025-08-31T00:09:25.000Z"}, {"gameId": 401752799, "driveId": "40175279912", "id": "401752799103856101", "driveNumber": 12, "playNumber": 4, "offense": "UAlbany", "offenseConference": "CAA", "offenseScore": 7, "defense": "Iowa", "defenseConference": "Big Ten", "defenseScore": 17, "home": "Iowa", "away": "UAlbany", "period": 3, "clock": {"minutes": 14, "seconds": 38}, "offenseTimeouts": 3, "defenseTimeouts": 3, "yardline": 85, "yardsToGoal": 85, "down": 3, "distance": 10, "yardsGained": 9, "scoring": false, "playType": "Pass Reception", "playText": "Jack Shields pass complete to Carter Moses for 9 yds to the UALB 24", "ppa": 0.19786232937530457, "wallclock": "2025-08-31T00:10:21.000Z"}, {"gameId": 401752799, "driveId": "40175279913", "id": "401752799103926702", "driveNumber": 13, "playNumber": 11, "offense": "Iowa", "offenseConference": "Big Ten", "offenseScore": 17, "defense": "UAlbany", "defenseConference": "CAA", "defenseScore": 7, "home": "Iowa", "away": "UAlbany", "period": 3, "clock": {"minutes": 7, "seconds": 32}, "offenseTimeouts": 3, "defenseTimeouts": 3, "yardline": 86, "yardsToGoal": 14, "down": 2, "distance": 8, "yardsGained": 5, "scoring": false, "playType": "Penalty", "playText": "(07:36) Shotgun Gronowski,Mark pass complete short left to Parker,KJ caught at UA 10, for 4 yards to the UA 10 (Harris,Khian'Dre) PENALTY Iowa Ineligible Downfield on Pass (Dunker,Gennings) 5 yards from UA 14 to UA 19. NO PLAY.", "ppa": null, "wallclock": "2025-08-31T00:19:06.000Z"}, {"gameId": 401752799, "driveId": "40175279913", "id": "401752799103865001", "driveNumber": 13, "playNumber": 1, "offense": "Iowa", "offenseConference": "Big Ten", "offenseScore": 17, "defense": "UAlbany", "defenseConference": "CAA", "defenseScore": 7, "home": "Iowa", "away": "UAlbany", "period": 3, "clock": {"minutes": 13, "seconds": 49}, "offenseTimeouts": 3, "defenseTimeouts": 3, "yardline": 40, "yardsToGoal": 60, "down": 1, "distance": 10, "yardsGained": 7, "scoring": false, "playType": "Rush", "playText": "Terrell Washington Jr. run for 7 yds to the IOWA 47", "ppa": 0.7032387839448688, "wallclock": "2025-08-31T00:11:54.000Z"}, {"gameId": 401752799, "driveId": "40175279913", "id": "401752799103869101", "driveNumber": 13, "playNumber": 2, "offense": "Iowa", "offenseConference": "Big Ten", "offenseScore": 17, "defense": "UAlbany", "defenseConference": "CAA", "defenseScore": 7, "home": "Iowa", "away": "UAlbany", "period": 3, "clock": {"minutes": 13, "seconds": 8}, "offenseTimeouts": 3, "defenseTimeouts": 3, "yardline": 47, "yardsToGoal": 53, "down": 2, "distance": 3, "yardsGained": 2, "scoring": false, "playType": "Rush", "playText": "Terrell Washington Jr. run for 2 yds to the IOWA 49", "ppa": -0.7604178938581772, "wallclock": "2025-08-31T00:12:28.000Z"}, {"gameId": 401752799, "driveId": "40175279913", "id": "401752799103877001", "driveNumber": 13, "playNumber": 3, "offense": "Iowa", "offenseConference": "Big Ten", "offenseScore": 17, "defense": "UAlbany", "defenseConference": "CAA", "defenseScore": 7, "home": "Iowa", "away": "UAlbany", "period": 3, "clock": {"minutes": 12, "seconds": 29}, "offenseTimeouts": 3, "defenseTimeouts": 3, "yardline": 49, "yardsToGoal": 51, "down": 3, "distance": 1, "yardsGained": 13, "scoring": false, "playType": "Rush", "playText": "Mark Gronowski run for 13 yds to the UALB 38 for a 1ST down", "ppa": 1.7194870654717958, "wallclock": "2025-08-31T00:13:06.000Z"}, {"gameId": 401752799, "driveId": "40175279913", "id": "401752799103885201", "driveNumber": 13, "playNumber": 4, "offense": "Iowa", "offenseConference": "Big Ten", "offenseScore": 17, "defense": "UAlbany", "defenseConference": "CAA", "defenseScore": 7, "home": "Iowa", "away": "UAlbany", "period": 3, "clock": {"minutes": 11, "seconds": 47}, "offenseTimeouts": 3, "defenseTimeouts": 3, "yardline": 62, "yardsToGoal": 38, "down": 1, "distance": 10, "yardsGained": 6, "scoring": false, "playType": "Rush", "playText": "Mark Gronowski run for 6 yds to the UALB 32", "ppa": 0.2517020867787, "wallclock": "2025-08-31T00:13:41.000Z"}, {"gameId": 401752799, "driveId": "40175279913", "id": "401752799103889301", "driveNumber": 13, "playNumber": 5, "offense": "Iowa", "offenseConference": "Big Ten", "offenseScore": 17, "defense": "UAlbany", "defenseConference": "CAA", "defenseScore": 7, "home": "Iowa", "away": "UAlbany", "period": 3, "clock": {"minutes": 11, "seconds": 6}, "offenseTimeouts": 3, "defenseTimeouts": 3, "yardline": 68, "yardsToGoal": 32, "down": 2, "distance": 4, "yardsGained": 0, "scoring": false, "playType": "Pass Incompletion", "playText": "Mark Gronowski pass incomplete", "ppa": -0.781180687607332, "wallclock": "2025-08-31T00:14:48.000Z"}, {"gameId": 401752799, "driveId": "40175279913", "id": "401752799103895001", "driveNumber": 13, "playNumber": 6, "offense": "Iowa", "offenseConference": "Big Ten", "offenseScore": 17, "defense": "UAlbany", "defenseConference": "CAA", "defenseScore": 7, "home": "Iowa", "away": "UAlbany", "period": 3, "clock": {"minutes": 10, "seconds": 49}, "offenseTimeouts": 3, "defenseTimeouts": 3, "yardline": 68, "yardsToGoal": 32, "down": 3, "distance": 4, "yardsGained": 3, "scoring": false, "playType": "Pass Reception", "playText": "Mark Gronowski pass complete to Xavier Williams for 3 yds to the UALB 29", "ppa": -0.3203887765644834, "wallclock": "2025-08-31T00:15:25.000Z"}, {"gameId": 401752799, "driveId": "40175279913", "id": "401752799103898401", "driveNumber": 13, "playNumber": 7, "offense": "Iowa", "offenseConference": "Big Ten", "offenseScore": 17, "defense": "UAlbany", "defenseConference": "CAA", "defenseScore": 7, "home": "Iowa", "away": "UAlbany", "period": 3, "clock": {"minutes": 10, "seconds": 15}, "offenseTimeouts": 3, "defenseTimeouts": 3, "yardline": 71, "yardsToGoal": 29, "down": 4, "distance": 1, "yardsGained": 2, "scoring": false, "playType": "Rush", "playText": "Mark Gronowski run for 2 yds to the UALB 27 for a 1ST down", "ppa": 1.2031791845868174, "wallclock": "2025-08-31T00:15:57.000Z"}, {"gameId": 401752799, "driveId": "40175279913", "id": "401752799103906301", "driveNumber": 13, "playNumber": 8, "offense": "Iowa", "offenseConference": "Big Ten", "offenseScore": 17, "defense": "UAlbany", "defenseConference": "CAA", "defenseScore": 7, "home": "Iowa", "away": "UAlbany", "period": 3, "clock": {"minutes": 9, "seconds": 36}, "offenseTimeouts": 3, "defenseTimeouts": 3, "yardline": 73, "yardsToGoal": 27, "down": 1, "distance": 10, "yardsGained": 6, "scoring": false, "playType": "Rush", "playText": "Terrell Washington Jr. run for 6 yds to the UALB 21", "ppa": 0.2009551098411215, "wallclock": "2025-08-31T00:16:57.000Z"}, {"gameId": 401752799, "driveId": "40175279913", "id": "401752799103914601", "driveNumber": 13, "playNumber": 9, "offense": "Iowa", "offenseConference": "Big Ten", "offenseScore": 17, "defense": "UAlbany", "defenseConference": "CAA", "defenseScore": 7, "home": "Iowa", "away": "UAlbany", "period": 3, "clock": {"minutes": 8, "seconds": 53}, "offenseTimeouts": 3, "defenseTimeouts": 3, "yardline": 79, "yardsToGoal": 21, "down": 2, "distance": 4, "yardsGained": 5, "scoring": false, "playType": "Rush", "playText": "Terrell Washington Jr. run for 5 yds to the UALB 16 for a 1ST down", "ppa": -0.0283969897420099, "wallclock": "2025-08-31T00:17:29.000Z"}, {"gameId": 401752799, "driveId": "40175279913", "id": "401752799103924001", "driveNumber": 13, "playNumber": 10, "offense": "Iowa", "offenseConference": "Big Ten", "offenseScore": 17, "defense": "UAlbany", "defenseConference": "CAA", "defenseScore": 7, "home": "Iowa", "away": "UAlbany", "period": 3, "clock": {"minutes": 7, "seconds": 59}, "offenseTimeouts": 3, "defenseTimeouts": 3, "yardline": 84, "yardsToGoal": 16, "down": 1, "distance": 10, "yardsGained": 2, "scoring": false, "playType": "Pass Reception", "playText": "Mark Gronowski pass complete to Terrell Washington Jr. for 2 yds to the UALB 14", "ppa": -0.1838209433726501, "wallclock": "2025-08-31T00:18:05.000Z"}, {"gameId": 401752799, "driveId": "40175279913", "id": "401752799103929901", "driveNumber": 13, "playNumber": 12, "offense": "Iowa", "offenseConference": "Big Ten", "offenseScore": 17, "defense": "UAlbany", "defenseConference": "CAA", "defenseScore": 7, "home": "Iowa", "away": "UAlbany", "period": 3, "clock": {"minutes": 7, "seconds": 0}, "offenseTimeouts": 3, "defenseTimeouts": 3, "yardline": 81, "yardsToGoal": 19, "down": 2, "distance": 13, "yardsGained": 3, "scoring": false, "playType": "Rush", "playText": "Xavier Williams run for 3 yds to the UALB 16", "ppa": -0.152293885867788, "wallclock": "2025-08-31T00:19:33.000Z"}, {"gameId": 401752799, "driveId": "40175279913", "id": "401752799103937801", "driveNumber": 13, "playNumber": 13, "offense": "Iowa", "offenseConference": "Big Ten", "offenseScore": 17, "defense": "UAlbany", "defenseConference": "CAA", "defenseScore": 7, "home": "Iowa", "away": "UAlbany", "period": 3, "clock": {"minutes": 6, "seconds": 21}, "offenseTimeouts": 3, "defenseTimeouts": 3, "yardline": 84, "yardsToGoal": 16, "down": 3, "distance": 10, "yardsGained": 13, "scoring": false, "playType": "Pass Reception", "playText": "Mark Gronowski pass complete to Jacob Gill for 13 yds to the UALB 3 for a 1ST down", "ppa": 1.81524133855549, "wallclock": "2025-08-31T00:20:42.000Z"}, {"gameId": 401752799, "driveId": "40175279913", "id": "401752799103939701", "driveNumber": 13, "playNumber": 14, "offense": "Iowa", "offenseConference": "Big Ten", "offenseScore": 17, "defense": "UAlbany", "defenseConference": "CAA", "defenseScore": 7, "home": "Iowa", "away": "UAlbany", "period": 3, "clock": {"minutes": 6, "seconds": 2}, "offenseTimeouts": 3, "defenseTimeouts": 3, "yardline": 97, "yardsToGoal": 3, "down": 1, "distance": 3, "yardsGained": 2, "scoring": false, "playType": "Rush", "playText": "Terrell Washington Jr. run for 2 yds to the UALB 1", "ppa": -0.435900504741669, "wallclock": "2025-08-31T00:21:19.000Z"}, {"gameId": 401752799, "driveId": "40175279913", "id": "401752799103947201", "driveNumber": 13, "playNumber": 15, "offense": "Iowa", "offenseConference": "Big Ten", "offenseScore": 24, "defense": "UAlbany", "defenseConference": "CAA", "defenseScore": 7, "home": "Iowa", "away": "UAlbany", "period": 3, "clock": {"minutes": 5, "seconds": 27}, "offenseTimeouts": 3, "defenseTimeouts": 3, "yardline": 99, "yardsToGoal": 1, "down": 2, "distance": 1, "yardsGained": 1, "scoring": true, "playType": "Rushing Touchdown", "playText": "Mark Gronowski run for 1 yd for a TD (Drew Stevens KICK)", "ppa": 1.900352237473006, "wallclock": "2025-08-31T00:21:30.000Z"}, {"gameId": 401752799, "driveId": "40175279914", "id": "401752799103947203", "driveNumber": 14, "playNumber": 1, "offense": "Iowa", "offenseConference": "Big Ten", "offenseScore": 24, "defense": "UAlbany", "defenseConference": "CAA", "defenseScore": 7, "home": "Iowa", "away": "UAlbany", "period": 3, "clock": {"minutes": 5, "seconds": 27}, "offenseTimeouts": 3, "defenseTimeouts": 3, "yardline": 35, "yardsToGoal": 65, "down": 1, "distance": 10, "yardsGained": 0, "scoring": false, "playType": "Kickoff", "playText": "Drew Stevens kickoff for 65 yds for a touchback", "ppa": null, "wallclock": "2025-08-31T00:26:48.000Z"}, {"gameId": 401752799, "driveId": "40175279914", "id": "401752799103958301", "driveNumber": 14, "playNumber": 5, "offense": "UAlbany", "offenseConference": "CAA", "offenseScore": 7, "defense": "Iowa", "defenseConference": "Big Ten", "defenseScore": 24, "home": "Iowa", "away": "UAlbany", "period": 3, "clock": {"minutes": 4, "seconds": 16}, "offenseTimeouts": 3, "defenseTimeouts": 3, "yardline": 74, "yardsToGoal": 74, "down": 4, "distance": 9, "yardsGained": 0, "scoring": false, "playType": "Punt", "playText": "Owen Lawson punt for 60 yds", "ppa": null, "wallclock": "2025-08-31T00:33:23.000Z"}, {"gameId": 401752799, "driveId": "40175279914", "id": "401752799103948101", "driveNumber": 14, "playNumber": 2, "offense": "UAlbany", "offenseConference": "CAA", "offenseScore": 7, "defense": "Iowa", "defenseConference": "Big Ten", "defenseScore": 24, "home": "Iowa", "away": "UAlbany", "period": 3, "clock": {"minutes": 5, "seconds": 18}, "offenseTimeouts": 3, "defenseTimeouts": 3, "yardline": 75, "yardsToGoal": 75, "down": 1, "distance": 10, "yardsGained": 1, "scoring": false, "playType": "Rush", "playText": "Jack Shields run for 1 yd to the UALB 26", "ppa": -0.5874795431016855, "wallclock": "2025-08-31T00:31:02.000Z"}, {"gameId": 401752799, "driveId": "40175279914", "id": "401752799103956501", "driveNumber": 14, "playNumber": 3, "offense": "UAlbany", "offenseConference": "CAA", "offenseScore": 7, "defense": "Iowa", "defenseConference": "Big Ten", "defenseScore": 24, "home": "Iowa", "away": "UAlbany", "period": 3, "clock": {"minutes": 4, "seconds": 34}, "offenseTimeouts": 3, "defenseTimeouts": 3, "yardline": 74, "yardsToGoal": 74, "down": 2, "distance": 9, "yardsGained": 0, "scoring": false, "playType": "Pass Incompletion", "playText": "Jack Shields pass incomplete to Caden Burti", "ppa": -0.40831395320271024, "wallclock": "2025-08-31T00:32:12.000Z"}, {"gameId": 401752799, "driveId": "40175279914", "id": "401752799103956801", "driveNumber": 14, "playNumber": 4, "offense": "UAlbany", "offenseConference": "CAA", "offenseScore": 7, "defense": "Iowa", "defenseConference": "Big Ten", "defenseScore": 24, "home": "Iowa", "away": "UAlbany", "period": 3, "clock": {"minutes": 4, "seconds": 31}, "offenseTimeouts": 3, "defenseTimeouts": 3, "yardline": 74, "yardsToGoal": 74, "down": 3, "distance": 9, "yardsGained": 0, "scoring": false, "playType": "Pass Incompletion", "playText": "Jack Shields pass incomplete to Tavahri Groves", "ppa": -0.18876768235831598, "wallclock": "2025-08-31T00:32:17.000Z"}, {"gameId": 401752799, "driveId": "40175279915", "id": "401752799103999902", "driveNumber": 15, "playNumber": 9, "offense": "Iowa", "offenseConference": "Big Ten", "offenseScore": 24, "defense": "UAlbany", "defenseConference": "CAA", "defenseScore": 7, "home": "Iowa", "away": "UAlbany", "period": 3, "clock": {"minutes": 0, "seconds": 0}, "offenseTimeouts": 3, "defenseTimeouts": 3, "yardline": 60, "yardsToGoal": 40, "down": 0, "distance": 7, "yardsGained": 4, "scoring": false, "playType": "End Period", "playText": "End of 3rd Quarter", "ppa": null, "wallclock": "2025-08-31T00:44:18.000Z"}, {"gameId": 401752799, "driveId": "40175279915", "id": "401752799104858101", "driveNumber": 15, "playNumber": 11, "offense": "Iowa", "offenseConference": "Big Ten", "offenseScore": 27, "defense": "UAlbany", "defenseConference": "CAA", "defenseScore": 7, "home": "Iowa", "away": "UAlbany", "period": 4, "clock": {"minutes": 14, "seconds": 18}, "offenseTimeouts": 3, "defenseTimeouts": 3, "yardline": 63, "yardsToGoal": 37, "down": 4, "distance": 4, "yardsGained": 55, "scoring": true, "playType": "Field Goal Good", "playText": "Drew Stevens 55 yd FG GOOD", "ppa": null, "wallclock": "2025-08-31T00:49:05.000Z"}, {"gameId": 401752799, "driveId": "40175279915", "id": "401752799103959001", "driveNumber": 15, "playNumber": 1, "offense": "Iowa", "offenseConference": "Big Ten", "offenseScore": 24, "defense": "UAlbany", "defenseConference": "CAA", "defenseScore": 7, "home": "Iowa", "away": "UAlbany", "period": 3, "clock": {"minutes": 4, "seconds": 9}, "offenseTimeouts": 3, "defenseTimeouts": 3, "yardline": 14, "yardsToGoal": 86, "down": 1, "distance": 10, "yardsGained": 13, "scoring": false, "playType": "Rush", "playText": "Terrell Washington Jr. run for 13 yds to the IOWA 27 for a 1ST down", "ppa": 0.7273513821069626, "wallclock": "2025-08-31T00:36:22.000Z"}, {"gameId": 401752799, "driveId": "40175279915", "id": "401752799103966801", "driveNumber": 15, "playNumber": 2, "offense": "Iowa", "offenseConference": "Big Ten", "offenseScore": 24, "defense": "UAlbany", "defenseConference": "CAA", "defenseScore": 7, "home": "Iowa", "away": "UAlbany", "period": 3, "clock": {"minutes": 3, "seconds": 31}, "offenseTimeouts": 3, "defenseTimeouts": 3, "yardline": 27, "yardsToGoal": 73, "down": 1, "distance": 10, "yardsGained": 9, "scoring": false, "playType": "Rush", "playText": "Xavier Williams run for 9 yds to the IOWA 36", "ppa": 1.2988785897355477, "wallclock": "2025-08-31T00:37:17.000Z"}, {"gameId": 401752799, "driveId": "40175279915", "id": "401752799103975301", "driveNumber": 15, "playNumber": 3, "offense": "Iowa", "offenseConference": "Big Ten", "offenseScore": 24, "defense": "UAlbany", "defenseConference": "CAA", "defenseScore": 7, "home": "Iowa", "away": "UAlbany", "period": 3, "clock": {"minutes": 2, "seconds": 46}, "offenseTimeouts": 3, "defenseTimeouts": 3, "yardline": 36, "yardsToGoal": 64, "down": 2, "distance": 1, "yardsGained": 9, "scoring": false, "playType": "Rush", "playText": "Xavier Williams run for 9 yds to the IOWA 45 for a 1ST down", "ppa": 0.357223607170024, "wallclock": "2025-08-31T00:37:56.000Z"}, {"gameId": 401752799, "driveId": "40175279915", "id": "401752799103978901", "driveNumber": 15, "playNumber": 4, "offense": "Iowa", "offenseConference": "Big Ten", "offenseScore": 24, "defense": "UAlbany", "defenseConference": "CAA", "defenseScore": 7, "home": "Iowa", "away": "UAlbany", "period": 3, "clock": {"minutes": 2, "seconds": 10}, "offenseTimeouts": 3, "defenseTimeouts": 3, "yardline": 45, "yardsToGoal": 55, "down": 1, "distance": 10, "yardsGained": -1, "scoring": false, "playType": "Rush", "playText": "Terrell Washington Jr. run for a loss of 1 yard to the IOWA 44", "ppa": -1.3838406426271828, "wallclock": "2025-08-31T00:38:28.000Z"}, {"gameId": 401752799, "driveId": "40175279915", "id": "401752799103986901", "driveNumber": 15, "playNumber": 5, "offense": "Iowa", "offenseConference": "Big Ten", "offenseScore": 24, "defense": "UAlbany", "defenseConference": "CAA", "defenseScore": 7, "home": "Iowa", "away": "UAlbany", "period": 3, "clock": {"minutes": 1, "seconds": 30}, "offenseTimeouts": 3, "defenseTimeouts": 3, "yardline": 44, "yardsToGoal": 56, "down": 2, "distance": 11, "yardsGained": 8, "scoring": false, "playType": "Rush", "playText": "Terrell Washington Jr. run for 8 yds to the UALB 48", "ppa": 0.7930347964328313, "wallclock": "2025-08-31T00:39:08.000Z"}, {"gameId": 401752799, "driveId": "40175279915", "id": "401752799103988801", "driveNumber": 15, "playNumber": 6, "offense": "Iowa", "offenseConference": "Big Ten", "offenseScore": 24, "defense": "UAlbany", "defenseConference": "CAA", "defenseScore": 7, "home": "Iowa", "away": "UAlbany", "period": 3, "clock": {"minutes": 1, "seconds": 11}, "offenseTimeouts": 3, "defenseTimeouts": 3, "yardline": 52, "yardsToGoal": 48, "down": 3, "distance": 3, "yardsGained": 5, "scoring": false, "playType": "Pass Reception", "playText": "Mark Gronowski pass complete to Zach Ortwerth for 5 yds to the UALB 43 for a 1ST down", "ppa": 1.5150489955798623, "wallclock": "2025-08-31T00:39:42.000Z"}, {"gameId": 401752799, "driveId": "40175279915", "id": "401752799103994901", "driveNumber": 15, "playNumber": 7, "offense": "Iowa", "offenseConference": "Big Ten", "offenseScore": 24, "defense": "UAlbany", "defenseConference": "CAA", "defenseScore": 7, "home": "Iowa", "away": "UAlbany", "period": 3, "clock": {"minutes": 0, "seconds": 50}, "offenseTimeouts": 3, "defenseTimeouts": 3, "yardline": 57, "yardsToGoal": 43, "down": 1, "distance": 10, "yardsGained": 3, "scoring": false, "playType": "Rush", "playText": "Xavier Williams run for 3 yds to the UALB 40", "ppa": -0.3057652594509188, "wallclock": "2025-08-31T00:43:39.000Z"}, {"gameId": 401752799, "driveId": "40175279915", "id": "401752799103999901", "driveNumber": 15, "playNumber": 8, "offense": "Iowa", "offenseConference": "Big Ten", "offenseScore": 24, "defense": "UAlbany", "defenseConference": "CAA", "defenseScore": 7, "home": "Iowa", "away": "UAlbany", "period": 3, "clock": {"minutes": 0, "seconds": 0}, "offenseTimeouts": 3, "defenseTimeouts": 3, "yardline": 60, "yardsToGoal": 40, "down": 2, "distance": 7, "yardsGained": 4, "scoring": false, "playType": "Rush", "playText": "Xavier Williams run for 4 yds to the UALB 36", "ppa": -0.125917794315347, "wallclock": "2025-08-31T00:44:18.000Z"}, {"gameId": 401752799, "driveId": "40175279915", "id": "401752799104855101", "driveNumber": 15, "playNumber": 10, "offense": "Iowa", "offenseConference": "Big Ten", "offenseScore": 24, "defense": "UAlbany", "defenseConference": "CAA", "defenseScore": 7, "home": "Iowa", "away": "UAlbany", "period": 4, "clock": {"minutes": 14, "seconds": 48}, "offenseTimeouts": 3, "defenseTimeouts": 3, "yardline": 64, "yardsToGoal": 36, "down": 3, "distance": 3, "yardsGained": -1, "scoring": false, "playType": "Rush", "playText": "Hank Brown run for a loss of 1 yard to the UALB 37", "ppa": -1.2857537300516082, "wallclock": "2025-08-31T00:48:29.000Z"}, {"gameId": 401752799, "driveId": "40175279916", "id": "401752799104858601", "driveNumber": 16, "playNumber": 1, "offense": "Iowa", "offenseConference": "Big Ten", "offenseScore": 27, "defense": "UAlbany", "defenseConference": "CAA", "defenseScore": 7, "home": "Iowa", "away": "UAlbany", "period": 4, "clock": {"minutes": 14, "seconds": 13}, "offenseTimeouts": 3, "defenseTimeouts": 3, "yardline": 35, "yardsToGoal": 65, "down": 1, "distance": 10, "yardsGained": 12, "scoring": false, "playType": "Kickoff Return (Offense)", "playText": "Drew Stevens kickoff for 57 yds , Lasalle Rose Jr. return for 12 yds to the UALB 20", "ppa": null, "wallclock": "2025-08-31T00:53:02.000Z"}, {"gameId": 401752799, "driveId": "40175279916", "id": "401752799104896301", "driveNumber": 16, "playNumber": 8, "offense": "UAlbany", "offenseConference": "CAA", "offenseScore": 7, "defense": "Iowa", "defenseConference": "Big Ten", "defenseScore": 27, "home": "Iowa", "away": "UAlbany", "period": 4, "clock": {"minutes": 10, "seconds": 36}, "offenseTimeouts": 3, "defenseTimeouts": 3, "yardline": 70, "yardsToGoal": 70, "down": 4, "distance": 21, "yardsGained": 36, "scoring": false, "playType": "Blocked Punt", "playText": "punt blocked by Preston Ries blocked by Preston Ries", "ppa": null, "wallclock": "2025-08-31T01:01:52.000Z"}, {"gameId": 401752799, "driveId": "40175279916", "id": "401752799104859601", "driveNumber": 16, "playNumber": 2, "offense": "UAlbany", "offenseConference": "CAA", "offenseScore": 7, "defense": "Iowa", "defenseConference": "Big Ten", "defenseScore": 27, "home": "Iowa", "away": "UAlbany", "period": 4, "clock": {"minutes": 14, "seconds": 3}, "offenseTimeouts": 3, "defenseTimeouts": 3, "yardline": 80, "yardsToGoal": 80, "down": 1, "distance": 10, "yardsGained": 3, "scoring": false, "playType": "Pass Reception", "playText": "Jack Shields pass complete to Tavahri Groves for 3 yds to the UALB 23", "ppa": -0.2366097161141063, "wallclock": "2025-08-31T00:53:35.000Z"}, {"gameId": 401752799, "driveId": "40175279916", "id": "401752799104867401", "driveNumber": 16, "playNumber": 3, "offense": "UAlbany", "offenseConference": "CAA", "offenseScore": 7, "defense": "Iowa", "defenseConference": "Big Ten", "defenseScore": 27, "home": "Iowa", "away": "UAlbany", "period": 4, "clock": {"minutes": 13, "seconds": 25}, "offenseTimeouts": 3, "defenseTimeouts": 3, "yardline": 77, "yardsToGoal": 77, "down": 2, "distance": 7, "yardsGained": 3, "scoring": false, "playType": "Rush", "playText": "Alex Jreige run for 3 yds to the UALB 26", "ppa": -0.18622825165887136, "wallclock": "2025-08-31T00:54:10.000Z"}, {"gameId": 401752799, "driveId": "40175279916", "id": "401752799104875602", "driveNumber": 16, "playNumber": 4, "offense": "UAlbany", "offenseConference": "CAA", "offenseScore": 7, "defense": "Iowa", "defenseConference": "Big Ten", "defenseScore": 27, "home": "Iowa", "away": "UAlbany", "period": 4, "clock": {"minutes": 12, "seconds": 43}, "offenseTimeouts": 3, "defenseTimeouts": 3, "yardline": 74, "yardsToGoal": 74, "down": 3, "distance": 4, "yardsGained": -15, "scoring": false, "playType": "Penalty", "playText": "(12:47) No Huddle-Shotgun Shields,Jack pass incomplete deep left to Jreige,Alex thrown to UA 49 PENALTY Iowa Pass Interference (Harrell,Jaden) 15 yards from UA 26 to UA 41, 1ST DOWN. NO PLAY.", "ppa": null, "wallclock": "2025-08-31T00:54:44.000Z"}, {"gameId": 401752799, "driveId": "40175279916", "id": "401752799104876301", "driveNumber": 16, "playNumber": 5, "offense": "UAlbany", "offenseConference": "CAA", "offenseScore": 7, "defense": "Iowa", "defenseConference": "Big Ten", "defenseScore": 27, "home": "Iowa", "away": "UAlbany", "period": 4, "clock": {"minutes": 12, "seconds": 36}, "offenseTimeouts": 3, "defenseTimeouts": 3, "yardline": 59, "yardsToGoal": 59, "down": 1, "distance": 10, "yardsGained": -4, "scoring": false, "playType": "Rush", "playText": "Jojo Uga run for a loss of 4 yards to the UALB 37", "ppa": -1.8327551994755824, "wallclock": "2025-08-31T00:56:21.000Z"}, {"gameId": 401752799, "driveId": "40175279916", "id": "401752799104879601", "driveNumber": 16, "playNumber": 6, "offense": "UAlbany", "offenseConference": "CAA", "offenseScore": 7, "defense": "Iowa", "defenseConference": "Big Ten", "defenseScore": 27, "home": "Iowa", "away": "UAlbany", "period": 4, "clock": {"minutes": 12, "seconds": 3}, "offenseTimeouts": 3, "defenseTimeouts": 3, "yardline": 63, "yardsToGoal": 63, "down": 2, "distance": 14, "yardsGained": 4, "scoring": false, "playType": "Pass Reception", "playText": "Jack Shields pass complete to Caden Burti for 4 yds to the UALB 41", "ppa": -0.09547362932026, "wallclock": "2025-08-31T00:57:00.000Z"}, {"gameId": 401752799, "driveId": "40175279916", "id": "401752799104887201", "driveNumber": 16, "playNumber": 7, "offense": "UAlbany", "offenseConference": "CAA", "offenseScore": 7, "defense": "Iowa", "defenseConference": "Big Ten", "defenseScore": 27, "home": "Iowa", "away": "UAlbany", "period": 4, "clock": {"minutes": 11, "seconds": 27}, "offenseTimeouts": 3, "defenseTimeouts": 3, "yardline": 59, "yardsToGoal": 59, "down": 3, "distance": 10, "yardsGained": -11, "scoring": false, "playType": "Sack", "playText": "Jack Shields sacked by Aaron Graves for a loss of 11 yards to the UALB 30", "ppa": -0.7646873957866722, "wallclock": "2025-08-31T00:57:05.000Z"}, {"gameId": 401752799, "driveId": "40175279917", "id": "401752799104896901", "driveNumber": 17, "playNumber": 1, "offense": "Iowa", "offenseConference": "Big Ten", "offenseScore": 27, "defense": "UAlbany", "defenseConference": "CAA", "defenseScore": 7, "home": "Iowa", "away": "UAlbany", "period": 4, "clock": {"minutes": 10, "seconds": 30}, "offenseTimeouts": 3, "defenseTimeouts": 3, "yardline": 34, "yardsToGoal": 66, "down": 1, "distance": 10, "yardsGained": 17, "scoring": false, "playType": "Rush", "playText": "Jaziun Patterson run for 17 yds to the UALB 49 for a 1ST down", "ppa": 1.574438838092366, "wallclock": "2025-08-31T01:01:55.000Z"}, {"gameId": 401752799, "driveId": "40175279917", "id": "401752799104904701", "driveNumber": 17, "playNumber": 2, "offense": "Iowa", "offenseConference": "Big Ten", "offenseScore": 27, "defense": "UAlbany", "defenseConference": "CAA", "defenseScore": 7, "home": "Iowa", "away": "UAlbany", "period": 4, "clock": {"minutes": 9, "seconds": 52}, "offenseTimeouts": 3, "defenseTimeouts": 3, "yardline": 51, "yardsToGoal": 49, "down": 1, "distance": 10, "yardsGained": 4, "scoring": false, "playType": "Rush", "playText": "Jaziun Patterson run for 4 yds to the UALB 45", "ppa": -0.1369390380115582, "wallclock": "2025-08-31T01:02:30.000Z"}, {"gameId": 401752799, "driveId": "40175279917", "id": "401752799104908501", "driveNumber": 17, "playNumber": 3, "offense": "Iowa", "offenseConference": "Big Ten", "offenseScore": 27, "defense": "UAlbany", "defenseConference": "CAA", "defenseScore": 7, "home": "Iowa", "away": "UAlbany", "period": 4, "clock": {"minutes": 9, "seconds": 14}, "offenseTimeouts": 3, "defenseTimeouts": 3, "yardline": 55, "yardsToGoal": 45, "down": 2, "distance": 6, "yardsGained": 7, "scoring": false, "playType": "Rush", "playText": "Jaziun Patterson run for 7 yds to the UALB 38 for a 1ST down", "ppa": 0.8046769410636185, "wallclock": "2025-08-31T01:03:06.000Z"}, {"gameId": 401752799, "driveId": "40175279917", "id": "401752799104917301", "driveNumber": 17, "playNumber": 4, "offense": "Iowa", "offenseConference": "Big Ten", "offenseScore": 27, "defense": "UAlbany", "defenseConference": "CAA", "defenseScore": 7, "home": "Iowa", "away": "UAlbany", "period": 4, "clock": {"minutes": 8, "seconds": 26}, "offenseTimeouts": 3, "defenseTimeouts": 3, "yardline": 62, "yardsToGoal": 38, "down": 1, "distance": 10, "yardsGained": 4, "scoring": false, "playType": "Pass Reception", "playText": "Hank Brown pass complete to Seth Anderson for 4 yds to the UALB 34", "ppa": -0.080462810572756, "wallclock": "2025-08-31T01:03:46.000Z"}, {"gameId": 401752799, "driveId": "40175279917", "id": "401752799104924201", "driveNumber": 17, "playNumber": 5, "offense": "Iowa", "offenseConference": "Big Ten", "offenseScore": 27, "defense": "UAlbany", "defenseConference": "CAA", "defenseScore": 7, "home": "Iowa", "away": "UAlbany", "period": 4, "clock": {"minutes": 7, "seconds": 57}, "offenseTimeouts": 3, "defenseTimeouts": 3, "yardline": 66, "yardsToGoal": 34, "down": 2, "distance": 6, "yardsGained": 5, "scoring": false, "playType": "Rush", "playText": "Nathan McNeil run for 5 yds to the UALB 29", "ppa": 0.0866607914072527, "wallclock": "2025-08-31T01:04:19.000Z"}, {"gameId": 401752799, "driveId": "40175279917", "id": "401752799104927101", "driveNumber": 17, "playNumber": 6, "offense": "Iowa", "offenseConference": "Big Ten", "offenseScore": 27, "defense": "UAlbany", "defenseConference": "CAA", "defenseScore": 7, "home": "Iowa", "away": "UAlbany", "period": 4, "clock": {"minutes": 7, "seconds": 28}, "offenseTimeouts": 3, "defenseTimeouts": 3, "yardline": 71, "yardsToGoal": 29, "down": 3, "distance": 1, "yardsGained": 4, "scoring": false, "playType": "Rush", "playText": "Jaziun Patterson run for 4 yds to the UALB 25 for a 1ST down", "ppa": 0.3883103054846338, "wallclock": "2025-08-31T01:04:52.000Z"}, {"gameId": 401752799, "driveId": "40175279917", "id": "401752799104935001", "driveNumber": 17, "playNumber": 7, "offense": "Iowa", "offenseConference": "Big Ten", "offenseScore": 27, "defense": "UAlbany", "defenseConference": "CAA", "defenseScore": 7, "home": "Iowa", "away": "UAlbany", "period": 4, "clock": {"minutes": 6, "seconds": 49}, "offenseTimeouts": 3, "defenseTimeouts": 3, "yardline": 75, "yardsToGoal": 25, "down": 1, "distance": 10, "yardsGained": 0, "scoring": false, "playType": "Rush", "playText": "Nathan McNeil run for no gain to the UALB 25", "ppa": -0.4522778946200265, "wallclock": "2025-08-31T01:06:03.000Z"}, {"gameId": 401752799, "driveId": "40175279917", "id": "401752799104937301", "driveNumber": 17, "playNumber": 8, "offense": "Iowa", "offenseConference": "Big Ten", "offenseScore": 27, "defense": "UAlbany", "defenseConference": "CAA", "defenseScore": 7, "home": "Iowa", "away": "UAlbany", "period": 4, "clock": {"minutes": 6, "seconds": 26}, "offenseTimeouts": 3, "defenseTimeouts": 3, "yardline": 75, "yardsToGoal": 25, "down": 2, "distance": 10, "yardsGained": 9, "scoring": false, "playType": "Rush", "playText": "Nathan McNeil run for 9 yds to the UALB 16", "ppa": 0.492372996200846, "wallclock": "2025-08-31T01:09:50.000Z"}, {"gameId": 401752799, "driveId": "40175279917", "id": "401752799104945101", "driveNumber": 17, "playNumber": 9, "offense": "Iowa", "offenseConference": "Big Ten", "offenseScore": 27, "defense": "UAlbany", "defenseConference": "CAA", "defenseScore": 7, "home": "Iowa", "away": "UAlbany", "period": 4, "clock": {"minutes": 5, "seconds": 48}, "offenseTimeouts": 3, "defenseTimeouts": 3, "yardline": 84, "yardsToGoal": 16, "down": 3, "distance": 1, "yardsGained": 8, "scoring": false, "playType": "Rush", "playText": "Jaziun Patterson run for 8 yds to the UALB 8 for a 1ST down", "ppa": 0.340389691985546, "wallclock": "2025-08-31T01:10:24.000Z"}, {"gameId": 401752799, "driveId": "40175279917", "id": "401752799104949001", "driveNumber": 17, "playNumber": 10, "offense": "Iowa", "offenseConference": "Big Ten", "offenseScore": 27, "defense": "UAlbany", "defenseConference": "CAA", "defenseScore": 7, "home": "Iowa", "away": "UAlbany", "period": 4, "clock": {"minutes": 5, "seconds": 9}, "offenseTimeouts": 3, "defenseTimeouts": 3, "yardline": 92, "yardsToGoal": 8, "down": 1, "distance": 8, "yardsGained": 7, "scoring": false, "playType": "Rush", "playText": "Jaziun Patterson run for 7 yds to the UALB 1", "ppa": 0.419247331226686, "wallclock": "2025-08-31T01:11:07.000Z"}, {"gameId": 401752799, "driveId": "40175279917", "id": "401752799104958601", "driveNumber": 17, "playNumber": 11, "offense": "Iowa", "offenseConference": "Big Ten", "offenseScore": 27, "defense": "UAlbany", "defenseConference": "CAA", "defenseScore": 7, "home": "Iowa", "away": "UAlbany", "period": 4, "clock": {"minutes": 4, "seconds": 13}, "offenseTimeouts": 3, "defenseTimeouts": 3, "yardline": 99, "yardsToGoal": 1, "down": 2, "distance": 1, "yardsGained": 0, "scoring": false, "playType": "Rush", "playText": "Jaziun Patterson run for no gain to the UALB 1", "ppa": -0.553645991706544, "wallclock": "2025-08-31T01:11:51.000Z"}, {"gameId": 401752799, "driveId": "40175279917", "id": "401752799104965701", "driveNumber": 17, "playNumber": 12, "offense": "Iowa", "offenseConference": "Big Ten", "offenseScore": 34, "defense": "UAlbany", "defenseConference": "CAA", "defenseScore": 7, "home": "Iowa", "away": "UAlbany", "period": 4, "clock": {"minutes": 3, "seconds": 42}, "offenseTimeouts": 3, "defenseTimeouts": 3, "yardline": 99, "yardsToGoal": 1, "down": 3, "distance": 1, "yardsGained": 1, "scoring": true, "playType": "Rushing Touchdown", "playText": "Hank Brown run for 1 yd for a TD UAlbany Penalty, Defensive Offside (Balansama Kamara) declined (Drew Stevens KICK)", "ppa": 2.45399822917955, "wallclock": "2025-08-31T01:13:05.000Z"}, {"gameId": 401752799, "driveId": "40175279918", "id": "401752799104965703", "driveNumber": 18, "playNumber": 1, "offense": "Iowa", "offenseConference": "Big Ten", "offenseScore": 34, "defense": "UAlbany", "defenseConference": "CAA", "defenseScore": 7, "home": "Iowa", "away": "UAlbany", "period": 4, "clock": {"minutes": 3, "seconds": 42}, "offenseTimeouts": 3, "defenseTimeouts": 3, "yardline": 35, "yardsToGoal": 65, "down": 1, "distance": 10, "yardsGained": 0, "scoring": false, "playType": "Kickoff", "playText": "Drew Stevens kickoff for 65 yds for a touchback", "ppa": null, "wallclock": "2025-08-31T01:13:38.000Z"}, {"gameId": 401752799, "driveId": "40175279918", "id": "401752799104984901", "driveNumber": 18, "playNumber": 5, "offense": "UAlbany", "offenseConference": "CAA", "offenseScore": 7, "defense": "Iowa", "defenseConference": "Big Ten", "defenseScore": 34, "home": "Iowa", "away": "UAlbany", "period": 4, "clock": {"minutes": 1, "seconds": 50}, "offenseTimeouts": 3, "defenseTimeouts": 3, "yardline": 82, "yardsToGoal": 82, "down": 4, "distance": 17, "yardsGained": 46, "scoring": false, "playType": "Punt", "playText": "Owen Lawson punt for 75 yds, punt out-of-bounds at the UALB 47 , Sam Phillips returns for 46 yds to the UALB 47", "ppa": null, "wallclock": "2025-08-31T01:18:29.000Z"}, {"gameId": 401752799, "driveId": "40175279918", "id": "401752799104966001", "driveNumber": 18, "playNumber": 2, "offense": "UAlbany", "offenseConference": "CAA", "offenseScore": 7, "defense": "Iowa", "defenseConference": "Big Ten", "defenseScore": 34, "home": "Iowa", "away": "UAlbany", "period": 4, "clock": {"minutes": 3, "seconds": 39}, "offenseTimeouts": 3, "defenseTimeouts": 3, "yardline": 75, "yardsToGoal": 75, "down": 1, "distance": 10, "yardsGained": 0, "scoring": false, "playType": "Pass Incompletion", "playText": "Jack Shields pass incomplete to Jasiah Barron", "ppa": -0.7029700220436519, "wallclock": "2025-08-31T01:16:00.000Z"}, {"gameId": 401752799, "driveId": "40175279918", "id": "401752799104966801", "driveNumber": 18, "playNumber": 3, "offense": "UAlbany", "offenseConference": "CAA", "offenseScore": 7, "defense": "Iowa", "defenseConference": "Big Ten", "defenseScore": 34, "home": "Iowa", "away": "UAlbany", "period": 4, "clock": {"minutes": 3, "seconds": 31}, "offenseTimeouts": 3, "defenseTimeouts": 3, "yardline": 75, "yardsToGoal": 75, "down": 2, "distance": 10, "yardsGained": -4, "scoring": false, "playType": "Rush", "playText": "Caden Burti run for a loss of 4 yards to the UALB 21", "ppa": -0.49047952318612786, "wallclock": "2025-08-31T01:16:32.000Z"}, {"gameId": 401752799, "driveId": "40175279918", "id": "401752799104975301", "driveNumber": 18, "playNumber": 4, "offense": "UAlbany", "offenseConference": "CAA", "offenseScore": 7, "defense": "Iowa", "defenseConference": "Big Ten", "defenseScore": 34, "home": "Iowa", "away": "UAlbany", "period": 4, "clock": {"minutes": 2, "seconds": 46}, "offenseTimeouts": 3, "defenseTimeouts": 3, "yardline": 79, "yardsToGoal": 79, "down": 3, "distance": 14, "yardsGained": -3, "scoring": false, "playType": "Rush", "playText": "Jack Shields run for a loss of 3 yards to the UALB 18", "ppa": -0.1036267815512515, "wallclock": "2025-08-31T01:17:08.000Z"}, {"gameId": 401752799, "driveId": "40175279919", "id": "401752799104985501", "driveNumber": 19, "playNumber": 1, "offense": "Iowa", "offenseConference": "Big Ten", "offenseScore": 34, "defense": "UAlbany", "defenseConference": "CAA", "defenseScore": 7, "home": "Iowa", "away": "UAlbany", "period": 4, "clock": {"minutes": 1, "seconds": 44}, "offenseTimeouts": 3, "defenseTimeouts": 3, "yardline": 53, "yardsToGoal": 47, "down": 1, "distance": 10, "yardsGained": -3, "scoring": false, "playType": "Fumble Recovery (Opponent)", "playText": "Hank Brown run for a loss of 3 yards to the 50 yard line Hank Brown fumbled, recovered by UALB Abdul Osholake , return to the 50 yard line", "ppa": -3.38679775873357, "wallclock": "2025-08-31T01:22:47.000Z"}, {"gameId": 401752799, "driveId": "40175279920", "id": "401752799104999902", "driveNumber": 20, "playNumber": 6, "offense": "UAlbany", "offenseConference": "CAA", "offenseScore": 7, "defense": "Iowa", "defenseConference": "Big Ten", "defenseScore": 34, "home": "Iowa", "away": "UAlbany", "period": 4, "clock": {"minutes": 0, "seconds": 0}, "offenseTimeouts": 3, "defenseTimeouts": 3, "yardline": 34, "yardsToGoal": 34, "down": 0, "distance": 10, "yardsGained": 4, "scoring": false, "playType": "End of Game", "playText": "End of 4th Quarter", "ppa": null, "wallclock": "2025-08-31T01:26:35.000Z"}, {"gameId": 401752799, "driveId": "40175279920", "id": "401752799104986301", "driveNumber": 20, "playNumber": 1, "offense": "UAlbany", "offenseConference": "CAA", "offenseScore": 7, "defense": "Iowa", "defenseConference": "Big Ten", "defenseScore": 34, "home": "Iowa", "away": "UAlbany", "period": 4, "clock": {"minutes": 1, "seconds": 36}, "offenseTimeouts": 3, "defenseTimeouts": 3, "yardline": 50, "yardsToGoal": 50, "down": 1, "distance": 10, "yardsGained": 4, "scoring": false, "playType": "Rush", "playText": "Jojo Uga run for 4 yds to the IOWA 46", "ppa": -0.141734208558013, "wallclock": "2025-08-31T01:22:55.000Z"}, {"gameId": 401752799, "driveId": "40175279920", "id": "401752799104994101", "driveNumber": 20, "playNumber": 2, "offense": "UAlbany", "offenseConference": "CAA", "offenseScore": 7, "defense": "Iowa", "defenseConference": "Big Ten", "defenseScore": 34, "home": "Iowa", "away": "UAlbany", "period": 4, "clock": {"minutes": 0, "seconds": 58}, "offenseTimeouts": 3, "defenseTimeouts": 3, "yardline": 46, "yardsToGoal": 46, "down": 2, "distance": 6, "yardsGained": 0, "scoring": false, "playType": "Pass Incompletion", "playText": "Jack Shields pass incomplete to Caden Burti", "ppa": -1.1389049167660108, "wallclock": "2025-08-31T01:23:59.000Z"}, {"gameId": 401752799, "driveId": "40175279920", "id": "401752799104994701", "driveNumber": 20, "playNumber": 3, "offense": "UAlbany", "offenseConference": "CAA", "offenseScore": 7, "defense": "Iowa", "defenseConference": "Big Ten", "defenseScore": 34, "home": "Iowa", "away": "UAlbany", "period": 4, "clock": {"minutes": 0, "seconds": 52}, "offenseTimeouts": 3, "defenseTimeouts": 3, "yardline": 46, "yardsToGoal": 46, "down": 3, "distance": 6, "yardsGained": 12, "scoring": false, "playType": "Pass Reception", "playText": "Jack Shields pass complete to Carter Moses for 12 yds to the IOWA 34 for a 1ST down", "ppa": 2.1853248965317267, "wallclock": "2025-08-31T01:24:36.000Z"}, {"gameId": 401752799, "driveId": "40175279920", "id": "401752799104998101", "driveNumber": 20, "playNumber": 4, "offense": "UAlbany", "offenseConference": "CAA", "offenseScore": 7, "defense": "Iowa", "defenseConference": "Big Ten", "defenseScore": 34, "home": "Iowa", "away": "UAlbany", "period": 4, "clock": {"minutes": 0, "seconds": 18}, "offenseTimeouts": 3, "defenseTimeouts": 3, "yardline": 34, "yardsToGoal": 34, "down": 1, "distance": 10, "yardsGained": 0, "scoring": false, "playType": "Pass Incompletion", "playText": "Jack Shields pass incomplete to Jasiah Barron", "ppa": -0.6630222646782312, "wallclock": "2025-08-31T01:25:13.000Z"}, {"gameId": 401752799, "driveId": "40175279920", "id": "401752799104999901", "driveNumber": 20, "playNumber": 5, "offense": "UAlbany", "offenseConference": "CAA", "offenseScore": 7, "defense": "Iowa", "defenseConference": "Big Ten", "defenseScore": 34, "home": "Iowa", "away": "UAlbany", "period": 4, "clock": {"minutes": 0, "seconds": 0}, "offenseTimeouts": 3, "defenseTimeouts": 3, "yardline": 34, "yardsToGoal": 34, "down": 2, "distance": 10, "yardsGained": 4, "scoring": false, "playType": "Rush", "playText": "Jojo Uga run for 4 yds to the IOWA 30", "ppa": -0.1121278119288398, "wallclock": "2025-08-31T01:26:35.000Z"}]